Workbook

Sheet ReadMe
A1: Landova Proforma v2
A2: Every Landova use, one engine. Parcel facts + use defaults + cost library -> what fits -> cost -> three exits -> max offer.
A4: Start here
A5: 1. Parcel | B5: Enter or paste the parcel's facts and the asking price.
A6: 2. Best_Use | B6: Every use ranked by the most you could pay for this land. This is the 'land value today to its best use' screen.
A7: 3. Deal_View | B7: Pick one use and read its numbers top to bottom: yield, quantities, budget, income, exits, max offer.
A9: How it is built
A10: Four engines | B10: For-Sale (lots, homes, condos) · Income (anything 5+ units or commercial: valued on NOI and cap rate) · Operator Pad (Landova delivers a pad, an operator runs the business) · Land Play (leases and entitle-and-sell).
A11: Three exits for every use | B11: 1) Land / pad sale 2) Build & sell 3) Build & hold / lease. Use_Library says which are allowed.
A12: Use_Library | B12: One row per use: how it is sized, what it costs, what it earns, and where it works. Add a use = add a row.
A13: Engine | B13: One row per use, one column per step. This tab is the spec Ryan codes from - every column header is a calculation step.
A14: Max offer | B14: The engine solves for the land price that leaves exactly the required margin. Costs that rise with land price (closing, carry, financing, property tax) are included, so the answer is exact.
A15: Market cap | B15: Max usable acres stops the model from pretending 20 acres can all be QSR pads. Leftover acres are resold at the raw land value.
A17: Color code
A18: Blue on yellow | B18: Input - edit
A19: Black | B19: Formula - don't edit
A20: Green | B20: Link to another tab
A22: Before using on a live deal
A23: Placeholders | B23: Every cost, price, rent, cap rate, county factor and land value is a placeholder chosen to show the mechanics. Replace with real comps, bids and your actuals.
A24: Location tests | B24: Traffic, households, highway distance, corner and substation minimums in Use_Library are enforced: a use that fails gets no capacity and drops to the bottom. The written location notes are NOT enforced - the land search must apply them.
A25: Not in this workbook | B25: Monthly cash flow / IRR, multifamily unit mix and LP/GP waterfall, operating-business P&Ls. See the build guide.

Sheet Parcel
A1: Parcel Inputs
A2: One parcel. In the software these fill from Landova's site analysis. Blue on yellow = input.
B4: Input | C4: Value | D4: Unit | E4: Source in Landova
B5: Parcel name | C5: Sample Parcel - Grayson County | E5: User
B6: County | C6: Grayson | E6: Parcel record
B7: Cost scenario | C7: Base | D7: Low/Base/High | E7: User
B8: Gross acres | C8: 20 | D8: ac | E8: Parcel boundary
B9: Buildable % | C9: 0.78 | D9: % of gross | E9: Buildable-land analysis
B10: Average slope | C10: 0.04 | D10: % | E10: Topography
B11: Tree cover | C11: 0.35 | D11: % | E11: 3D tree coverage
B12: Road frontage | C12: 660 | D12: LF | E12: Frontage analysis
B13: Public water at site | C13: Y | D13: Y/N | E13: Utilities layer
B14: Distance to water main | C14: 0 | D14: LF | E14: Utilities layer
B15: Public sewer at site | C15: N | D15: Y/N | E15: Utilities layer
B16: Distance to sewer main | C16: 6000 | D16: LF | E16: Utilities layer
B17: Septic soil rating | C17: Fair | D17: Good/Fair/Poor | E17: Soil composition
B18: Asking / offer price (whole parcel) | C18: 300000 | D18: $ | E18: Listing or user
B19: Traffic count on frontage road | C19: 4000 | D19: vehicles/day | E19: TxDOT counts
B20: Households within 3 miles | C20: 2500 | D20: households | E20: Census / growth layer
B21: Miles to nearest highway interchange | C21: 6 | D21: miles | E21: Road network
B22: Corner lot (hard corner on two roads) | C22: N | D22: Y/N | E22: Frontage analysis
B23: Miles to substation with capacity | C23: 3 | D23: miles | E23: Utility / transmission layer
B25: Derived (formulas)
B26: Net buildable acres | C26: =Parcel!$C$8*Parcel!$C$9 -> 15.6
B27: Public water used (1 = yes) | C27: =IF(OR(Parcel!$C$13="Y",Parcel!$C$14<=Assumptions!$C$5),1,0) -> 1
B28: Public sewer used (1 = yes) | C28: =IF(OR(Parcel!$C$15="Y",Parcel!$C$16<=Assumptions!$C$6),1,0) -> 0
B29: Off-site water extension LF | C29: =IF(Parcel!$C$13="Y",0,Parcel!$C$14)*Parcel!$C$27 -> 0
B30: Off-site sewer extension LF | C30: =IF(Parcel!$C$15="Y",0,Parcel!$C$16)*Parcel!$C$28 -> 0
B31: Scenario column | C31: =MATCH(Parcel!$C$7,Lookups!$J$5:$J$7,0) -> 2
B32: Regional cost factor | C32: =IFERROR(INDEX(Lookups!$B$5:$B$10,MATCH(Parcel!$C$6,Lookups!$A$5:$A$10,0)),1) -> 1
B33: Grading multiplier (slope) | C33: =INDEX(Lookups!$H$5:$H$7,MATCH(TRUE(),INDEX(Parcel!$C$10<=Lookups!$G$5:$G$7,0),0)) -> 1
B34: Septic multiplier (soil) | C34: =IFERROR(INDEX(Lookups!$E$5:$E$7,MATCH(Parcel!$C$17,Lookups!$D$5:$D$7,0)),1) -> 1.2

Sheet Best_Use
A1: Best Use - what this parcel is worth to each use
A2: Every use in the library run against the parcel on the Parcel tab, ranked by max offer. This is the 'land value today to its best use' screen.
B3: Parcel: | C3: =Parcel!$C$5 -> Sample Parcel - Grayson County | E3: Asking: | F3: =Parcel!$C$18 -> 300000
A5: Rank | B5: Use | C5: Engine | D5: Capacity | E5: Unit | F5: Best exit | G5: Max offer | H5: Opening offer | I5: Max - asking | J5: Max / gross ac | K5: Max / unit | L5: Binding constraint | M5: Flags | N5: row
A6: 1 | B6: =INDEX(Engine!$A$6:$A$58,$N6) -> Boat & RV storage | C6: =INDEX(Engine!$B$6:$B$58,$N6) -> Income | D6: =INDEX(Engine!$S$6:$S$58,$N6) -> 373 | E6: =INDEX(Engine!$C$6:$C$58,$N6) -> stall | F6: =INDEX(Engine!$CW$6:$CW$58,$N6) -> Build & hold / lease | G6: =INDEX(Engine!$CV$6:$CV$58,$N6) -> 1485094.8 | H6: =INDEX(Engine!$CX$6:$CX$58,$N6) -> 1262330.6 | I6: =INDEX(Engine!$CY$6:$CY$58,$N6) -> 1185094.8 | J6: =INDEX(Engine!$CZ$6:$CZ$58,$N6) -> 74254.742 | K6: =INDEX(Engine!$DA$6:$DA$58,$N6) -> 3981.4875 | L6: =INDEX(Engine!$T$6:$T$58,$N6) -> Site area / parking | M6: =INDEX(Engine!$DB$6:$DB$58,$N6) -> Only 6 ac used - rest resold. | N6: =MATCH(LARGE(Engine!$DC$6:$DC$58,A6),Engine!$DC$6:$DC$58,0) -> 48
A7: 2 | B7: =INDEX(Engine!$A$6:$A$58,$N7) -> Workforce / extended-stay RV park | C7: =INDEX(Engine!$B$6:$B$58,$N7) -> Income | D7: =INDEX(Engine!$S$6:$S$58,$N7) -> 234 | E7: =INDEX(Engine!$C$6:$C$58,$N7) -> site | F7: =INDEX(Engine!$CW$6:$CW$58,$N7) -> Build & hold / lease | G7: =INDEX(Engine!$CV$6:$CV$58,$N7) -> 660770.35 | H7: =INDEX(Engine!$CX$6:$CX$58,$N7) -> 561654.8 | I7: =INDEX(Engine!$CY$6:$CY$58,$N7) -> 360770.35 | J7: =INDEX(Engine!$CZ$6:$CZ$58,$N7) -> 33038.518 | K7: =INDEX(Engine!$DA$6:$DA$58,$N7) -> 2823.8049 | L7: =INDEX(Engine!$T$6:$T$58,$N7) -> Density | M7: =INDEX(Engine!$DB$6:$DB$58,$N7) | N7: =MATCH(LARGE(Engine!$DC$6:$DC$58,A7),Engine!$DC$6:$DC$58,0) -> 12
A8: 3 | B8: =INDEX(Engine!$A$6:$A$58,$N8) -> Supplier build-to-suit near major plants | C8: =INDEX(Engine!$B$6:$B$58,$N8) -> Income | D8: =INDEX(Engine!$S$6:$S$58,$N8) -> 239196.67 | E8: =INDEX(Engine!$C$6:$C$58,$N8) -> bldg SF | F8: =INDEX(Engine!$CW$6:$CW$58,$N8) -> Land / pad sale | G8: =INDEX(Engine!$CV$6:$CV$58,$N8) -> 493980.85 | H8: =INDEX(Engine!$CX$6:$CX$58,$N8) -> 419883.72 | I8: =INDEX(Engine!$CY$6:$CY$58,$N8) -> 193980.85 | J8: =INDEX(Engine!$CZ$6:$CZ$58,$N8) -> 24699.042 | K8: =INDEX(Engine!$DA$6:$DA$58,$N8) -> 2.065166 | L8: =INDEX(Engine!$T$6:$T$58,$N8) -> Site area / parking | M8: =INDEX(Engine!$DB$6:$DB$58,$N8) | N8: =MATCH(LARGE(Engine!$DC$6:$DC$58,A8),Engine!$DC$6:$DC$58,0) -> 41
A9: 4 | B9: =INDEX(Engine!$A$6:$A$58,$N9) -> Homesites (stick-built, for sale) | C9: =INDEX(Engine!$B$6:$B$58,$N9) -> For-Sale | D9: =INDEX(Engine!$S$6:$S$58,$N9) -> 24 | E9: =INDEX(Engine!$C$6:$C$58,$N9) -> lot / home | F9: =INDEX(Engine!$CW$6:$CW$58,$N9) -> Land / pad sale | G9: =INDEX(Engine!$CV$6:$CV$58,$N9) -> 441967.92 | H9: =INDEX(Engine!$CX$6:$CX$58,$N9) -> 375672.73 | I9: =INDEX(Engine!$CY$6:$CY$58,$N9) -> 141967.92 | J9: =INDEX(Engine!$CZ$6:$CZ$58,$N9) -> 22098.396 | K9: =INDEX(Engine!$DA$6:$DA$58,$N9) -> 18415.33 | L9: =INDEX(Engine!$T$6:$T$58,$N9) -> Septic lot size | M9: =INDEX(Engine!$DB$6:$DB$58,$N9) | N9: =MATCH(LARGE(Engine!$DC$6:$DC$58,A9),Engine!$DC$6:$DC$58,0) -> 1
A10: 5 | B10: =INDEX(Engine!$A$6:$A$58,$N10) -> Finished / entitled lots | C10: =INDEX(Engine!$B$6:$B$58,$N10) -> For-Sale | D10: =INDEX(Engine!$S$6:$S$58,$N10) -> 24 | E10: =INDEX(Engine!$C$6:$C$58,$N10) -> lot | F10: =INDEX(Engine!$CW$6:$CW$58,$N10) -> Land / pad sale | G10: =INDEX(Engine!$CV$6:$CV$58,$N10) -> 351753.61 | H10: =INDEX(Engine!$CX$6:$CX$58,$N10) -> 298990.57 | I10: =INDEX(Engine!$CY$6:$CY$58,$N10) -> 51753.61 | J10: =INDEX(Engine!$CZ$6:$CZ$58,$N10) -> 17587.68 | K10: =INDEX(Engine!$DA$6:$DA$58,$N10) -> 14656.4 | L10: =INDEX(Engine!$T$6:$T$58,$N10) -> Septic lot size | M10: =INDEX(Engine!$DB$6:$DB$58,$N10) | N10: =MATCH(LARGE(Engine!$DC$6:$DC$58,A10),Engine!$DC$6:$DC$58,0) -> 2
A11: 6 | B11: =INDEX(Engine!$A$6:$A$58,$N11) -> Manufactured home subdivision | C11: =INDEX(Engine!$B$6:$B$58,$N11) -> For-Sale | D11: =INDEX(Engine!$S$6:$S$58,$N11) -> 24 | E11: =INDEX(Engine!$C$6:$C$58,$N11) -> lot / home | F11: =INDEX(Engine!$CW$6:$CW$58,$N11) -> Build & sell | G11: =INDEX(Engine!$CV$6:$CV$58,$N11) -> 303520.56 | H11: =INDEX(Engine!$CX$6:$CX$58,$N11) -> 257992.48 | I11: =INDEX(Engine!$CY$6:$CY$58,$N11) -> 3520.5642 | J11: =INDEX(Engine!$CZ$6:$CZ$58,$N11) -> 15176.028 | K11: =INDEX(Engine!$DA$6:$DA$58,$N11) -> 12646.69 | L11: =INDEX(Engine!$T$6:$T$58,$N11) -> Septic lot size | M11: =INDEX(Engine!$DB$6:$DB$58,$N11) | N11: =MATCH(LARGE(Engine!$DC$6:$DC$58,A11),Engine!$DC$6:$DC$58,0) -> 5
A12: 7 | B12: =INDEX(Engine!$A$6:$A$58,$N12) -> Active-adult 55+ (for sale) | C12: =INDEX(Engine!$B$6:$B$58,$N12) -> For-Sale | D12: =INDEX(Engine!$S$6:$S$58,$N12) -> 24 | E12: =INDEX(Engine!$C$6:$C$58,$N12) -> lot / home | F12: =INDEX(Engine!$CW$6:$CW$58,$N12) -> Land / pad sale | G12: =INDEX(Engine!$CV$6:$CV$58,$N12) -> 289960.35 | H12: =INDEX(Engine!$CX$6:$CX$58,$N12) -> 246466.3 | I12: =INDEX(Engine!$CY$6:$CY$58,$N12) -> -10039.649 | J12: =INDEX(Engine!$CZ$6:$CZ$58,$N12) -> 14498.018 | K12: =INDEX(Engine!$DA$6:$DA$58,$N12) -> 12081.681 | L12: =INDEX(Engine!$T$6:$T$58,$N12) -> Septic lot size | M12: =INDEX(Engine!$DB$6:$DB$58,$N12) | N12: =MATCH(LARGE(Engine!$DC$6:$DC$58,A12),Engine!$DC$6:$DC$58,0) -> 3
A13: 8 | B13: =INDEX(Engine!$A$6:$A$58,$N13) -> Event venue / wedding barn | C13: =INDEX(Engine!$B$6:$B$58,$N13) -> Operator Pad | D13: =INDEX(Engine!$S$6:$S$58,$N13) -> 14.196 | E13: =INDEX(Engine!$C$6:$C$58,$N13) -> acre | F13: =INDEX(Engine!$CW$6:$CW$58,$N13) -> Land / pad sale | G13: =INDEX(Engine!$CV$6:$CV$58,$N13) -> 200241.01 | H13: =INDEX(Engine!$CX$6:$CX$58,$N13) -> 170204.86 | I13: =INDEX(Engine!$CY$6:$CY$58,$N13) -> -99758.993 | J13: =INDEX(Engine!$CZ$6:$CZ$58,$N13) -> 10012.05 | K13: =INDEX(Engine!$DA$6:$DA$58,$N13) -> 14105.453 | L13: =INDEX(Engine!$T$6:$T$58,$N13) -> Site area / parking | M13: =INDEX(Engine!$DB$6:$DB$58,$N13) | N13: =MATCH(LARGE(Engine!$DC$6:$DC$58,A13),Engine!$DC$6:$DC$58,0) -> 38
A14: 9 | B14: =INDEX(Engine!$A$6:$A$58,$N14) -> Entry-level for-sale homes | C14: =INDEX(Engine!$B$6:$B$58,$N14) -> For-Sale | D14: =INDEX(Engine!$S$6:$S$58,$N14) -> 24 | E14: =INDEX(Engine!$C$6:$C$58,$N14) -> lot / home | F14: =INDEX(Engine!$CW$6:$CW$58,$N14) -> Land / pad sale | G14: =INDEX(Engine!$CV$6:$CV$58,$N14) -> 199746.04 | H14: =INDEX(Engine!$CX$6:$CX$58,$N14) -> 169784.13 | I14: =INDEX(Engine!$CY$6:$CY$58,$N14) -> -100253.96 | J14: =INDEX(Engine!$CZ$6:$CZ$58,$N14) -> 9987.302 | K14: =INDEX(Engine!$DA$6:$DA$58,$N14) -> 8322.7517 | L14: =INDEX(Engine!$T$6:$T$58,$N14) -> Septic lot size | M14: =INDEX(Engine!$DB$6:$DB$58,$N14) | N14: =MATCH(LARGE(Engine!$DC$6:$DC$58,A14),Engine!$DC$6:$DC$58,0) -> 4
A15: 10 | B15: =INDEX(Engine!$A$6:$A$58,$N15) -> Private water / wastewater (package plant) site | C15: =INDEX(Engine!$B$6:$B$58,$N15) -> Land Play | D15: =INDEX(Engine!$S$6:$S$58,$N15) -> 5 | E15: =INDEX(Engine!$C$6:$C$58,$N15) -> acre | F15: =INDEX(Engine!$CW$6:$CW$58,$N15) -> Land / pad sale | G15: =INDEX(Engine!$CV$6:$CV$58,$N15) -> 116965.95 | H15: =INDEX(Engine!$CX$6:$CX$58,$N15) -> 99421.059 | I15: =INDEX(Engine!$CY$6:$CY$58,$N15) -> -183034.05 | J15: =INDEX(Engine!$CZ$6:$CZ$58,$N15) -> 5848.2976 | K15: =INDEX(Engine!$DA$6:$DA$58,$N15) -> 23393.19 | L15: =INDEX(Engine!$T$6:$T$58,$N15) -> Site area / parking | M15: =INDEX(Engine!$DB$6:$DB$58,$N15) -> Only 5 ac used - rest resold. | N15: =MATCH(LARGE(Engine!$DC$6:$DC$58,A15),Engine!$DC$6:$DC$58,0) -> 51
A16: 11 | B16: =INDEX(Engine!$A$6:$A$58,$N16) -> Powered land for data centers | C16: =INDEX(Engine!$B$6:$B$58,$N16) -> Land Play | D16: =INDEX(Engine!$S$6:$S$58,$N16) -> 0 | E16: =INDEX(Engine!$C$6:$C$58,$N16) -> acre | F16: =INDEX(Engine!$CW$6:$CW$58,$N16) -> None works | G16: =INDEX(Engine!$CV$6:$CV$58,$N16) -> 0 | H16: =INDEX(Engine!$CX$6:$CX$58,$N16) -> 0 | I16: =INDEX(Engine!$CY$6:$CY$58,$N16) -> -300000 | J16: =INDEX(Engine!$CZ$6:$CZ$58,$N16) -> 0 | K16: =INDEX(Engine!$DA$6:$DA$58,$N16) -> 0 | L16: =INDEX(Engine!$T$6:$T$58,$N16) -> Location fails | M16: =INDEX(Engine!$DB$6:$DB$58,$N16) -> Over 1 mi to substation. | N16: =MATCH(LARGE(Engine!$DC$6:$DC$58,A16),Engine!$DC$6:$DC$58,0) -> 53
A17: 12 | B17: =INDEX(Engine!$A$6:$A$58,$N17) -> Battery storage / solar land lease | C17: =INDEX(Engine!$B$6:$B$58,$N17) -> Land Play | D17: =INDEX(Engine!$S$6:$S$58,$N17) -> 0 | E17: =INDEX(Engine!$C$6:$C$58,$N17) -> acre | F17: =INDEX(Engine!$CW$6:$CW$58,$N17) -> None works | G17: =INDEX(Engine!$CV$6:$CV$58,$N17) -> 0 | H17: =INDEX(Engine!$CX$6:$CX$58,$N17) -> 0 | I17: =INDEX(Engine!$CY$6:$CY$58,$N17) -> -300000 | J17: =INDEX(Engine!$CZ$6:$CZ$58,$N17) -> 0 | K17: =INDEX(Engine!$DA$6:$DA$58,$N17) -> 0 | L17: =INDEX(Engine!$T$6:$T$58,$N17) -> Location fails | M17: =INDEX(Engine!$DB$6:$DB$58,$N17) -> Over 2 mi to substation. | N17: =MATCH(LARGE(Engine!$DC$6:$DC$58,A17),Engine!$DC$6:$DC$58,0) -> 52
... A58: 53 | B58: =INDEX(Engine!$A$6:$A$58,$N58) -> Townhomes | C58: =INDEX(Engine!$B$6:$B$58,$N58) -> For-Sale | D58: =INDEX(Engine!$S$6:$S$58,$N58) -> 0 | E58: =INDEX(Engine!$C$6:$C$58,$N58) -> unit | F58: =INDEX(Engine!$CW$6:$CW$58,$N58) -> None works | G58: =INDEX(Engine!$CV$6:$CV$58,$N58) -> 0 | H58: =INDEX(Engine!$CX$6:$CX$58,$N58) -> 0 | I58: =INDEX(Engine!$CY$6:$CY$58,$N58) -> -300000 | J58: =INDEX(Engine!$CZ$6:$CZ$58,$N58) -> 0 | K58: =INDEX(Engine!$DA$6:$DA$58,$N58) -> 0 | L58: =INDEX(Engine!$T$6:$T$58,$N58) -> Needs public sewer | M58: =INDEX(Engine!$DB$6:$DB$58,$N58) -> Nothing fits. | N58: =MATCH(LARGE(Engine!$DC$6:$DC$58,A58),Engine!$DC$6:$DC$58,0) -> 6
B60: Read with care: every number is a placeholder, and a high max offer means only that the math works. Check the location requirements (Use_Library) before believing any row.

Sheet Deal_View
A1: Deal View - one use in detail
A2: Pick a use. Everything below is read from the Engine row for that use, top to bottom, so you can audit each step.
B4: Use | C4: Multifamily - large garden (150+ units)
B5: Engine row | C5: =MATCH(C4,Engine!$A$6:$A$58,0) -> 14
B6: Location requirements | C6: =INDEX(Use_Library!$AS$5:$AS$57,$C$5) -> MF zoning; arterial frontage; employment within 20 min; sewer capacity letter
B9: Identity
B10: Engine | C10: =INDEX(Engine!$B$6:$B$58,$C$5) -> Income
B11: Capacity unit | C11: =INDEX(Engine!$C$6:$C$58,$C$5) -> unit
B13: Yield
B14: Usable acres (net - open space - detention) | C14: =INDEX(Engine!$D$6:$D$58,$C$5) -> 14.196
B15: Usable acres used by this use (market cap) | C15: =INDEX(Engine!$E$6:$E$58,$C$5) -> 14.196
B16: Share of parcel used | C16: =INDEX(Engine!$F$6:$F$58,$C$5) -> 1
B17: Net acres in use | C17: =INDEX(Engine!$G$6:$G$58,$C$5) -> 15.6
B18: Detention acres | C18: =INDEX(Engine!$H$6:$H$58,$C$5) -> 0.624
B19: Developed acres | C19: =INDEX(Engine!$I$6:$I$58,$C$5) -> 14.82
B20: Excess gross acres (resold as raw land) | C20: =INDEX(Engine!$J$6:$J$58,$C$5) -> 0
B21: Sewer requirement met (1/0) | C21: =INDEX(Engine!$K$6:$K$58,$C$5) -> 0
B22: Water requirement met (1/0) | C22: =INDEX(Engine!$L$6:$L$58,$C$5) -> 1
B23: Location test failures | C23: =INDEX(Engine!$M$6:$M$58,$C$5) -> Under 8,000 households in 3 mi.
B24: Location passes (1/0) | C24: =INDEX(Engine!$N$6:$N$58,$C$5) -> 0
B25: Parcel big enough (1/0) | C25: =INDEX(Engine!$O$6:$O$58,$C$5) -> 1
B26: Capacity by density | C26: =INDEX(Engine!$P$6:$P$58,$C$5) -> 374.4
B27: Capacity by site area | C27: =INDEX(Engine!$Q$6:$Q$58,$C$5) -> 515.3148
B28: Capacity by septic lot size | C28: =INDEX(Engine!$R$6:$R$58,$C$5) -> 1000000000
B29: CAPACITY (units / SF / acres) | C29: =INDEX(Engine!$S$6:$S$58,$C$5) -> 0
B30: Binding constraint | C30: =INDEX(Engine!$T$6:$T$58,$C$5) -> Location fails
B31: Anything fits (1/0) | C31: =INDEX(Engine!$U$6:$U$58,$C$5) -> 0
B32: Horizontal by us (1/0) | C32: =INDEX(Engine!$V$6:$V$58,$C$5) -> 0
B34: Quantities
B35: Internal road LF | C35: =INDEX(Engine!$W$6:$W$58,$C$5) -> 0
B36: Paving / hardscape SF | C36: =INDEX(Engine!$X$6:$X$58,$C$5) -> 0
B37: Water line LF | C37: =INDEX(Engine!$Y$6:$Y$58,$C$5) -> 0
B38: Water taps | C38: =INDEX(Engine!$Z$6:$Z$58,$C$5) -> 0
B39: Sewer line LF | C39: =INDEX(Engine!$AA$6:$AA$58,$C$5) -> 0
B40: Sewer taps | C40: =INDEX(Engine!$AB$6:$AB$58,$C$5) -> 0
B41: Septic systems | C41: =INDEX(Engine!$AC$6:$AC$58,$C$5) -> 0
B42: Private wells | C42: =INDEX(Engine!$AD$6:$AD$58,$C$5) -> 0
B43: Acres to clear | C43: =INDEX(Engine!$AE$6:$AE$58,$C$5) -> 0
B44: Acres to grade | C44: =INDEX(Engine!$AF$6:$AF$58,$C$5) -> 0
B45: Lots to plat | C45: =INDEX(Engine!$AG$6:$AG$58,$C$5) -> 0
B47: Horizontal budget
B48: 02-100 Survey | C48: =INDEX(Engine!$AH$6:$AH$58,$C$5) -> 0
B49: 02-110 Platting | C49: =INDEX(Engine!$AI$6:$AI$58,$C$5) -> 0
B50: 02-200 Civil engineering | C50: =INDEX(Engine!$AJ$6:$AJ$58,$C$5) -> 0
B51: 02-300 Geotech | C51: =INDEX(Engine!$AK$6:$AK$58,$C$5) -> 0
B52: 02-310 Septic evaluations | C52: =INDEX(Engine!$AL$6:$AL$58,$C$5) -> 0
B53: 02-400 Phase I | C53: =INDEX(Engine!$AM$6:$AM$58,$C$5) -> 0
B54: 02-500 Drainage study | C54: =INDEX(Engine!$AN$6:$AN$58,$C$5) -> 0
B55: Entitlement & zoning (use-specific) | C55: =INDEX(Engine!$AO$6:$AO$58,$C$5) -> 0
B56: 02-700 Legal & title | C56: =INDEX(Engine!$AP$6:$AP$58,$C$5) -> 0
B57: 03-100 Clearing | C57: =INDEX(Engine!$AQ$6:$AQ$58,$C$5) -> 0
B58: 03-200 Grading | C58: =INDEX(Engine!$AR$6:$AR$58,$C$5) -> 0
B59: 03-300 Roads / drives | C59: =INDEX(Engine!$AS$6:$AS$58,$C$5) -> 0
B60: 03-350 Paving / parking | C60: =INDEX(Engine!$AT$6:$AT$58,$C$5) -> 0
B61: 03-400 Detention | C61: =INDEX(Engine!$AU$6:$AU$58,$C$5) -> 0
B62: 03-500 SWPPP | C62: =INDEX(Engine!$AV$6:$AV$58,$C$5) -> 0
B63: 04-100 Water line | C63: =INDEX(Engine!$AW$6:$AW$58,$C$5) -> 0
B64: 04-110 Water taps | C64: =INDEX(Engine!$AX$6:$AX$58,$C$5) -> 0
B65: 04-200 Sewer line | C65: =INDEX(Engine!$AY$6:$AY$58,$C$5) -> 0
B66: 04-210 Sewer taps | C66: =INDEX(Engine!$AZ$6:$AZ$58,$C$5) -> 0
B67: 04-300 Septic systems | C67: =INDEX(Engine!$BA$6:$BA$58,$C$5) -> 0
B68: 04-310 Wells | C68: =INDEX(Engine!$BB$6:$BB$58,$C$5) -> 0
B69: 04-400 Electric | C69: =INDEX(Engine!$BC$6:$BC$58,$C$5) -> 0
B70: Horizontal subtotal | C70: =INDEX(Engine!$BD$6:$BD$58,$C$5) -> 0
B71: Horizontal contingency | C71: =INDEX(Engine!$BE$6:$BE$58,$C$5) -> 0
B72: HORIZONTAL TOTAL (ex land) | C72: =INDEX(Engine!$BF$6:$BF$58,$C$5) -> 0
B74: Vertical
B75: Vertical hard cost | C75: =INDEX(Engine!$BG$6:$BG$58,$C$5) -> 0
B76: Vertical soft + contingency | C76: =INDEX(Engine!$BH$6:$BH$58,$C$5) -> 0
B77: TI + leasing commissions | C77: =INDEX(Engine!$BI$6:$BI$58,$C$5) -> 0
B79: Land & financing factors
B80: Land cost factor (closing + carry) | C80: =INDEX(Engine!$BJ$6:$BJ$58,$C$5) -> 1.0616667
B81: Financing factor - no lease-up | C81: =INDEX(Engine!$BK$6:$BK$58,$C$5) -> 1.060125
B82: Financing factor - with lease-up | C82: =INDEX(Engine!$BL$6:$BL$58,$C$5) -> 1.104
B83: Excess land resale (net) | C83: =INDEX(Engine!$BM$6:$BM$58,$C$5) -> 0
B85: Build cost (exits 2 & 3)
B86: Build non-land cost (pre-financing) | C86: =INDEX(Engine!$BT$6:$BT$58,$C$5) -> 0
B87: Build cost per $1 of land | C87: =INDEX(Engine!$BU$6:$BU$58,$C$5) -> 1.17208
B89: Income (Income engine)
B90: Gross potential rent | C90: =INDEX(Engine!$BW$6:$BW$58,$C$5) -> 0
B91: Effective gross income | C91: =INDEX(Engine!$BX$6:$BX$58,$C$5) -> 0
B92: Operating expenses (ex tax, ex mgmt) | C92: =INDEX(Engine!$BY$6:$BY$58,$C$5) -> 0
B93: Property tax | C93: =INDEX(Engine!$BZ$6:$BZ$58,$C$5) -> 6575.3688
B94: Management | C94: =INDEX(Engine!$CA$6:$CA$58,$C$5) -> 0
B95: Expense recoveries | C95: =INDEX(Engine!$CB$6:$CB$58,$C$5) -> 328.76844
B96: NET OPERATING INCOME | C96: =INDEX(Engine!$CC$6:$CC$58,$C$5) -> -6246.6004
B97: Stabilized value (NOI / cap) | C97: =INDEX(Engine!$CD$6:$CD$58,$C$5) -> -113574.55
B98: Change in NOI per $1 of land | C98: =INDEX(Engine!$CE$6:$CE$58,$C$5) -> -0.020822001
B99: Yield on cost | C99: =INDEX(Engine!$CF$6:$CF$58,$C$5) -> -0.017765
B101: Hold financing (Income)
B102: Development loan | C102: =INDEX(Engine!$CR$6:$CR$58,$C$5) -> 207025
B103: Permanent loan (lesser of LTV, DSCR, debt yield) | C103: =INDEX(Engine!$CS$6:$CS$58,$C$5) -> 0
B104: DSCR on permanent loan | C104: =INDEX(Engine!$CT$6:$CT$58,$C$5) -> 0
B105: Cash out at refi (perm - dev loan) | C105: =INDEX(Engine!$CU$6:$CU$58,$C$5) -> -207025
B107: Exits
B108: Line | C108: Land / pad sale | D108: Build & sell | E108: Build & hold / lease
B109: Allowed for this use | C109: =IF(INDEX(Use_Library!$AJ$5:$AJ$57,$C$5)=1,"Yes","No") -> Yes | D109: =IF(INDEX(Use_Library!$AK$5:$AK$57,$C$5)=1,"Yes","No") -> Yes | E109: =IF(INDEX(Use_Library!$AL$5:$AL$57,$C$5)=1,"Yes","No") -> Yes
B110: Net revenue / value | C110: =INDEX(Engine!$BN$6:$BN$58,$C$5) -> 0 | D110: =INDEX(Engine!$CG$6:$CG$58,$C$5) -> 0 | E110: =INDEX(Engine!$CK$6:$CK$58,$C$5) -> 0
B111: Total cost at asking price | C111: =INDEX(Engine!$BQ$6:$BQ$58,$C$5) -> 337649.81 | D111: =INDEX(Engine!$BV$6:$BV$58,$C$5) -> 351624 | E111: =INDEX(Engine!$CN$6:$CN$58,$C$5) -> 351624
B112: Profit / value created at asking | C112: =INDEX(Engine!$BR$6:$BR$58,$C$5) -> -337649.81 | D112: =INDEX(Engine!$CI$6:$CI$58,$C$5) -> -351624 | E112: =INDEX(Engine!$CP$6:$CP$58,$C$5) -> -351624
...

Sheet Use_Library
A1: Use Library
A2: One row per use. Every economic value is a PLACEHOLDER for North Texas - replace with comps, bids and your own actuals. Add a use by adding a row (and extending the Engine tab).
A4: Use | B4: Category | C4: Engine | D4: Capacity unit | E4: Discrete units (Y/N) | F4: Max density (units / net ac; 0 = n/a) | G4: Site SF per unit (0 = n/a) | H4: Septic lot-size rule (Y/N) | I4: Requires public sewer (Y/N) | J4: Requires public water (Y/N) | K4: Horizontal work by us (Y/N) | L4: Min usable acres needed (0 = none) | M4: Max usable acres market supports (0 = no cap) | N4: Open space % of net | O4: Road / drive LF per unit | P4: Paving SF per unit | Q4: Utility taps per unit | R4: Septic systems per unit (if no sewer) | S4: Entitlement & zoning $ (fixed) | T4: Vertical cost per unit | U4: Lot sale price per unit (For-Sale) | V4: Finished sale price per unit (For-Sale) | W4: Rent per unit per year (Income) | X4: Other income % of rent | Y4: Stabilized vacancy | Z4: Opex per unit per year, excl. tax | AA4: Management % of EGI | AB4: Expense recovery % (NNN) | AC4: TI + leasing commissions per unit | AD4: Lease-up months | AE4: Exit / lease cap rate | AF4: Land / pad sale price per usable acre | AG4: Ground / land lease rent per acre per year | AH4: Development months | AI4: Required margin | AJ4: Exit allowed: Land / pad sale (1/0) | AK4: Exit allowed: Build & sell (1/0) | AL4: Exit allowed: Build & hold / lease (1/0) | AM4: Min road frontage LF | AN4: Min traffic count on frontage (VPD; 0 = none) | AO4: Min households within 3 mi (0 = none) | AP4: Max miles to highway interchange (0 = none) | AQ4: Corner lot required (Y/N) | AR4: Max miles to substation w/ capacity (0 = none) | AS4: Location requirements (land-search filters) | AT4: Notes
A5: Homesites (stick-built, for sale) | B5: Housing | C5: For-Sale | D5: lot / home | E5: Y | F5: 4 | G5: 0 | H5: Y | I5: N | J5: N | K5: Y | L5: 0 | M5: 0 | N5: 0.05 | O5: 50 | P5: 0 | Q5: 1 | R5: 1 | S5: 25000 | T5: 245000 | U5: 80000 | V5: 375000 | W5: 0 | X5: 0 | Y5: 0 | Z5: 0 | AA5: 0 | AB5: 0 | AC5: 0 | AD5: 0 | AE5: 0.07 | AF5: 0 | AG5: 0 | AH5: 12 | AI5: 0.15 | AJ5: 1 | AK5: 1 | AL5: 0 | AM5: 60 | AN5: 0 | AO5: 0 | AP5: 0 | AQ5: N | AR5: 0 | AS5: Within growth area; school district; < 30 min to job centers; no deed restriction on lot size | AT5: Placeholder values
A6: Finished / entitled lots | B6: Housing | C6: For-Sale | D6: lot | E6: Y | F6: 4 | G6: 0 | H6: Y | I6: N | J6: N | K6: Y | L6: 0 | M6: 0 | N6: 0.05 | O6: 50 | P6: 0 | Q6: 1 | R6: 1 | S6: 25000 | T6: 0 | U6: 75000 | V6: 0 | W6: 0 | X6: 0 | Y6: 0 | Z6: 0 | AA6: 0 | AB6: 0 | AC6: 0 | AD6: 0 | AE6: 0.07 | AF6: 0 | AG6: 0 | AH6: 12 | AI6: 0.15 | AJ6: 1 | AK6: 0 | AL6: 0 | AM6: 60 | AN6: 0 | AO6: 0 | AP6: 0 | AQ6: N | AR6: 0 | AS6: Builder demand in submarket; utilities within reach; platting allowed | AT6: Placeholder values
A7: Active-adult 55+ (for sale) | B7: Housing | C7: For-Sale | D7: lot / home | E7: Y | F7: 5 | G7: 0 | H7: Y | I7: N | J7: N | K7: Y | L7: 0 | M7: 0 | N7: 0.05 | O7: 45 | P7: 0 | Q7: 1 | R7: 1 | S7: 25000 | T7: 230000 | U7: 70000 | V7: 360000 | W7: 0 | X7: 0 | Y7: 0 | Z7: 0 | AA7: 0 | AB7: 0 | AC7: 0 | AD7: 0 | AE7: 0.07 | AF7: 0 | AG7: 0 | AH7: 12 | AI7: 0.15 | AJ7: 1 | AK7: 1 | AL7: 0 | AM7: 60 | AN7: 0 | AO7: 0 | AP7: 0 | AQ7: N | AR7: 0 | AS7: Near healthcare, retail and lakes/golf; 60+ population growth | AT7: Placeholder values
A8: Entry-level for-sale homes | B8: Housing | C8: For-Sale | D8: lot / home | E8: Y | F8: 5 | G8: 0 | H8: Y | I8: N | J8: N | K8: Y | L8: 0 | M8: 0 | N8: 0.05 | O8: 45 | P8: 0 | Q8: 1 | R8: 1 | S8: 25000 | T8: 210000 | U8: 65000 | V8: 310000 | W8: 0 | X8: 0 | Y8: 0 | Z8: 0 | AA8: 0 | AB8: 0 | AC8: 0 | AD8: 0 | AE8: 0.07 | AF8: 0 | AG8: 0 | AH8: 12 | AI8: 0.15 | AJ8: 1 | AK8: 1 | AL8: 0 | AM8: 60 | AN8: 0 | AO8: 0 | AP8: 0 | AQ8: N | AR8: 0 | AS8: Workforce demand (job growth); price-point gap vs. resale | AT8: Placeholder values
A9: Manufactured home subdivision | B9: Housing | C9: For-Sale | D9: lot / home | E9: Y | F9: 4 | G9: 0 | H9: Y | I9: N | J9: N | K9: Y | L9: 0 | M9: 0 | N9: 0.05 | O9: 50 | P9: 0 | Q9: 1 | R9: 1 | S9: 25000 | T9: 116500 | U9: 55000 | V9: 245000 | W9: 0 | X9: 0 | Y9: 0 | Z9: 0 | AA9: 0 | AB9: 0 | AC9: 0 | AD9: 0 | AE9: 0.07 | AF9: 0 | AG9: 0 | AH9: 12 | AI9: 0.15 | AJ9: 1 | AK9: 1 | AL9: 0 | AM9: 60 | AN9: 0 | AO9: 0 | AP9: 0 | AQ9: N | AR9: 0 | AS9: No deed restriction against MH; county (not city) jurisdiction or MH-friendly zoning | AT9: Vertical = Ridge Stone dealer cost ~$94K + set-up/foundation/skirting + flatwork (user-stated home cost; rest placeholder)
A10: Townhomes | B10: Housing | C10: For-Sale | D10: unit | E10: Y | F10: 10 | G10: 0 | H10: N | I10: Y | J10: Y | K10: Y | L10: 0 | M10: 0 | N10: 0.05 | O10: 25 | P10: 0 | Q10: 1 | R10: 0 | S10: 25000 | T10: 200000 | U10: 45000 | V10: 300000 | W10: 0 | X10: 0 | Y10: 0 | Z10: 0 | AA10: 0 | AB10: 0 | AC10: 0 | AD10: 0 | AE10: 0.07 | AF10: 0 | AG10: 0 | AH10: 12 | AI10: 0.15 | AJ10: 1 | AK10: 1 | AL10: 0 | AM10: 60 | AN10: 0 | AO10: 0 | AP10: 0 | AQ10: N | AR10: 0 | AS10: City water/sewer; zoning allows attached SF; near retail | AT10: Placeholder values
A11: Ranchette / acreage lots | B11: Housing | C11: For-Sale | D11: lot | E11: Y | F11: 0.2 | G11: 0 | H11: Y | I11: N | J11: N | K11: Y | L11: 0 | M11: 0 | N11: 0.05 | O11: 150 | P11: 0 | Q11: 1 | R11: 1 | S11: 10000 | T11: 0 | U11: 90000 | V11: 0 | W11: 0 | X11: 0 | Y11: 0 | Z11: 0 | AA11: 0 | AB11: 0 | AC11: 0 | AD11: 0 | AE11: 0.07 | AF11: 0 | AG11: 0 | AH11: 12 | AI11: 0.15 | AJ11: 1 | AK11: 0 | AL11: 0 | AM11: 60 | AN11: 0 | AO11: 0 | AP11: 0 | AQ11: N | AR11: 0 | AS11: Rural; good road frontage for flag-free lots; low flood exposure | AT11: Placeholder values
A12: Garage / car condos | B12: Storage | C12: For-Sale | D12: condo | E12: Y | F12: 0 | G12: 2900 | H12: N | I12: N | J12: N | K12: Y | L12: 0 | M12: 0 | N12: 0.05 | O12: 8 | P12: 900 | Q12: 0.1 | R12: 0.1 | S12: 25000 | T12: 85000 | U12: 0 | V12: 135000 | W12: 0 | X12: 0 | Y12: 0 | Z12: 0 | AA12: 0 | AB12: 0 | AC12: 0 | AD12: 0 | AE12: 0.07 | AF12: 0 | AG12: 0 | AH12: 12 | AI12: 0.15 | AJ12: 0 | AK12: 1 | AL12: 0 | AM12: 100 | AN12: 0 | AO12: 0 | AP12: 0 | AQ12: N | AR12: 0 | AS12: Affluent submarket; near lakes/airports; visible frontage | AT12: Placeholder values
A13: Contractor shop condos | B13: Business & Trades | C13: For-Sale | D13: condo (2,000 SF) | E13: Y | F13: 0 | G13: 5700 | H13: N | I13: N | J13: N | K13: Y | L13: 0 | M13: 6 | N13: 0.05 | O13: 10 | P13: 2500 | Q13: 0.2 | R13: 0.2 | S13: 25000 | T13: 190000 | U13: 0 | V13: 280000 | W13: 0 | X13: 0 | Y13: 0 | Z13: 0 | AA13: 0 | AB13: 0 | AC13: 0 | AD13: 0 | AE13: 0.07 | AF13: 0 | AG13: 0 | AH13: 12 | AI13: 0.15 | AJ13: 0 | AK13: 1 | AL13: 0 | AM13: 150 | AN13: 0 | AO13: 0 | AP13: 0 | AQ13: N | AR13: 0 | AS13: Arterial access; trades demand; light industrial / commercial zoning or county | AT13: Placeholder values
A14: Professional office condos | B14: Business & Trades | C14: For-Sale | D14: condo (1,500 SF) | E14: Y | F14: 0 | G14: 6000 | H14: N | I14: N | J14: Y | K14: Y | L14: 0 | M14: 4 | N14: 0.05 | O14: 8 | P14: 3000 | Q14: 0.25 | R14: 0.25 | S14: 25000 | T14: 300000 | U14: 0 | V14: 450000 | W14: 0 | X14: 0 | Y14: 0 | Z14: 0 | AA14: 0 | AB14: 0 | AC14: 0 | AD14: 0 | AE14: 0.07 | AF14: 0 | AG14: 0 | AH14: 12 | AI14: 0.15 | AJ14: 0 | AK14: 1 | AL14: 0 | AM14: 150 | AN14: 0 | AO14: 0 | AP14: 0 | AQ14: N | AR14: 0 | AS14: Near rooftops and medical/retail; commercial zoning | AT14: Placeholder values
A15: Manufactured home community (MHC) | B15: Housing | C15: Income | D15: pad | E15: Y | F15: 7 | G15: 0 | H15: Y | I15: N | J15: N | K15: Y | L15: 5 | M15: 0 | N15: 0.05 | O15: 40 | P15: 0 | Q15: 1 | R15: 1 | S15: 40000 | T15: 12000 | U15: 0 | V15: 0 | W15: 6600 | X15: 0.05 | Y15: 0.07 | Z15: 1200 | AA15: 0.05 | AB15: 0.15 | AC15: 0 | AD15: 24 | AE15: 0.065 | AF15: 40000 | AG15: 0 | AH15: 12 | AI15: 0.15 | AJ15: 1 | AK15: 1 | AL15: 1 | AM15: 60 | AN15: 0 | AO15: 0 | AP15: 0 | AQ15: N | AR15: 0 | AS15: County jurisdiction or MHC zoning; sewer or package plant for density; workforce job growth | AT15: Pad-only model. Park-owned homes = add home cost to vertical and home rent to rent (dealer-cost edge)
A16: Workforce / extended-stay RV park | B16: Housing | C16: Income | D16: site | E16: Y | F16: 15 | G16: 0 | H16: N | I16: N | J16: N | K16: Y | L16: 5 | M16: 0 | N16: 0.05 | O16: 30 | P16: 0 | Q16: 0.25 | R16: 0.25 | S16: 40000 | T16: 18000 | U16: 0 | V16: 0 | W16: 7800 | X16: 0.05 | Y16: 0.15 | Z16: 1800 | AA16: 0.08 | AB16: 0 | AC16: 0 | AD16: 12 | AE16: 0.085 | AF16: 40000 | AG16: 0 | AH16: 10 | AI16: 0.15 | AJ16: 1 | AK16: 1 | AL16: 1 | AM16: 60 | AN16: 0 | AO16: 0 | AP16: 0 | AQ16: N | AR16: 0 | AS16: Within 15 min of major construction/industrial employers (e.g. Sherman fabs); highway access | AT16: Placeholder values
... A57: Powered land for data centers | B57: Infrastructure | C57: Land Play | D57: acre | E57: N | F57: 0 | G57: 43560 | H57: N | I57: N | J57: N | K57: N | L57: 50 | M57: 0 | N57: 0.05 | O57: 0 | P57: 0 | Q57: 0 | R57: 0 | S57: 500000 | T57: 0 | U57: 0 | V57: 0 | W57: 0 | X57: 0 | Y57: 0 | Z57: 0 | AA57: 0 | AB57: 0 | AC57: 0 | AD57: 0 | AE57: 0.07 | AF57: 200000 | AG57: 0 | AH57: 24 | AI57: 0.25 | AJ57: 1 | AK57: 0 | AL57: 0 | AM57: 100 | AN57: 0 | AO57: 0 | AP57: 0 | AQ57: N | AR57: 1 | AS57: Transmission line / substation with available MW; fiber; water; 50+ ac | AT57: Entitlement = power/utility studies and agreements; the power commitment is the value

Sheet Engine
A1: Engine - every use run against this parcel
A2: One row per use, one column per calculation step, left to right. This tab IS the spec: each column header is a step Ryan codes. Do not edit - change inputs on Parcel, Assumptions, Use_Library.
A4: Identity | D4: Yield | W4: Quantities | AH4: Horizontal budget | BG4: Vertical | BJ4: Land & financing factors | BN4: Exit 1 - Land / pad sale | BT4: Build cost (exits 2 & 3) | BW4: Income (Income engine) | CG4: Exit 2 - Build & sell | CK4: Exit 3 - Build & hold / lease | CR4: Hold financing (Income) | CV4: Answer
A5: Use | B5: Engine | C5: Capacity unit | D5: Usable acres (net - open space - detention) | E5: Usable acres used by this use (market cap) | F5: Share of parcel used | G5: Net acres in use | H5: Detention acres | I5: Developed acres | J5: Excess gross acres (resold as raw land) | K5: Sewer requirement met (1/0) | L5: Water requirement met (1/0) | M5: Location test failures | N5: Location passes (1/0) | O5: Parcel big enough (1/0) | P5: Capacity by density | Q5: Capacity by site area | R5: Capacity by septic lot size | S5: CAPACITY (units / SF / acres) | T5: Binding constraint | U5: Anything fits (1/0) | V5: Horizontal by us (1/0) | W5: Internal road LF | X5: Paving / hardscape SF | Y5: Water line LF | Z5: Water taps | AA5: Sewer line LF | AB5: Sewer taps | AC5: Septic systems | AD5: Private wells | AE5: Acres to clear | AF5: Acres to grade | AG5: Lots to plat | AH5: 02-100 Survey | AI5: 02-110 Platting | AJ5: 02-200 Civil engineering | AK5: 02-300 Geotech | AL5: 02-310 Septic evaluations | AM5: 02-400 Phase I | AN5: 02-500 Drainage study | AO5: Entitlement & zoning (use-specific) | AP5: 02-700 Legal & title | AQ5: 03-100 Clearing | AR5: 03-200 Grading | AS5: 03-300 Roads / drives | AT5: 03-350 Paving / parking | AU5: 03-400 Detention | AV5: 03-500 SWPPP | AW5: 04-100 Water line | AX5: 04-110 Water taps | AY5: 04-200 Sewer line | AZ5: 04-210 Sewer taps | BA5: 04-300 Septic systems | BB5: 04-310 Wells | BC5: 04-400 Electric | BD5: Horizontal subtotal | BE5: Horizontal contingency | BF5: HORIZONTAL TOTAL (ex land) | BG5: Vertical hard cost | BH5: Vertical soft + contingency | BI5: TI + leasing commissions | BJ5: Land cost factor (closing + carry) | BK5: Financing factor - no lease-up | BL5: Financing factor - with lease-up | BM5: Excess land resale (net) | BN5: Exit 1 net revenue | BO5: Exit 1 non-land cost (no parking paving: buyer builds it) | BP5: Exit 1 cost per $1 of land | BQ5: Exit 1 total cost at asking | BR5: Exit 1 profit at asking | BS5: EXIT 1 MAX OFFER | BT5: Build non-land cost (pre-financing) | BU5: Build cost per $1 of land | BV5: Build total cost at asking | BW5: Gross potential rent | BX5: Effective gross income | BY5: Operating expenses (ex tax, ex mgmt) | BZ5: Property tax | CA5: Management | CB5: Expense recoveries | CC5: NET OPERATING INCOME | CD5: Stabilized value (NOI / cap) | CE5: Change in NOI per $1 of land | CF5: Yield on cost | CG5: Exit 2 net revenue | CH5: Change in exit 2 revenue per $1 of land | CI5: Exit 2 profit at asking | CJ5: EXIT 2 MAX OFFER | CK5: Exit 3 value | CL5: Exit 3 non-land cost | CM5: Exit 3 cost per $1 of land | CN5: Exit 3 total cost at asking | CO5: Change in exit 3 value per $1 of land | CP5: Exit 3 value created at asking | CQ5: EXIT 3 MAX OFFER | CR5: Development loan | CS5: Permanent loan (lesser of LTV, DSCR, debt yield) | CT5: DSCR on permanent loan | CU5: Cash out at refi (perm - dev loan) | CV5: BEST MAX OFFER | CW5: Best exit | CX5: Opening offer | CY5: Max offer minus asking | CZ5: Max offer per gross acre | DA5: Max offer per unit of capacity | DB5: Flags | DC5: Rank key
A6: =Use_Library!$A$5 -> Homesites (stick-built, for sale) | B6: =Use_Library!$C$5 -> For-Sale | C6: =Use_Library!$D$5 -> lot / home | D6: =MAX(0,Parcel!$C$26*(1-Use_Library!$N$5-Assumptions!$C$7)) -> 14.196 | E6: =IF(Use_Library!$M$5>0,MIN(D6,Use_Library!$M$5),D6) -> 14.196 | F6: =IF(D6=0,0,E6/D6) -> 1 | G6: =Parcel!$C$26*F6 -> 15.6 | H6: =G6*Assumptions!$C$7 -> 0.624 | I6: =G6*(1-Use_Library!$N$5) -> 14.82 | J6: =Parcel!$C$8*(1-F6) -> 0 | K6: =IF(AND(Use_Library!$I$5="Y",Parcel!$C$28=0),0,1) -> 1 | L6: =IF(AND(Use_Library!$J$5="Y",Parcel!$C$27=0),0,1) -> 1 | M6: =TRIM(IF(AND(Use_Library!$AN$5>0,Parcel!$C$19<Use_Library!$AN$5),"Traffic under "&TEXT(Use_Library!$AN$5,"#,##0")&" VPD. ","")&IF(AND(Use_Library!$AO$5>0,Parcel!$C$20<Use_Library!$AO$5),"Under "&TEXT(Use_Library!$AO$5,"#,##0")&" households in 3 mi. ","")&IF(AND(Use_Library!$AP$5>0,Parcel!$C$21>Use_Library!$AP$5),"Over "&Use_Library!$AP$5&" mi to highway. ","")&IF(AND(Use_Library!$AQ$5="Y",Parcel!$C$22<>"Y"),"Needs a corner. ","")&IF(AND(Use_Library!$AR$5>0,Parcel!$C$23>Use_Library!$AR$5),"Over "&Use_Library!$AR$5&" mi to substation. ","")) | N6: =IF(M6="",1,0) -> 1 | O6: =IF(D6>=Use_Library!$L$5,1,0) -> 1 | P6: =IF(Use_Library!$F$5>0,G6*Use_Library!$F$5,1000000000) -> 62.4 | Q6: =IF(Use_Library!$G$5>0,E6*43560/Use_Library!$G$5,1000000000) -> 1000000000 | R6: =IF(AND(Use_Library!$H$5="Y",Parcel!$C$28=0),E6*(1-Assumptions!$C$8)/IF(Parcel!$C$27=1,Assumptions!$C$9,Assumptions!$C$10),1000000000) -> 24.1332 | S6: =IF(K6*L6*O6*N6=0,0,IF(MIN(P6,Q6,R6)>=1000000000,E6,IF(Use_Library!$E$5="Y",INT(MIN(P6,Q6,R6)),MIN(P6,Q6,R6)))) -> 24 | T6: =IF(N6=0,"Location fails",IF(O6=0,"Too small - needs "&Use_Library!$L$5&" usable ac",IF(K6=0,"Needs public sewer",IF(L6=0,"Needs public water",IF(R6<=MIN(P6,Q6),"Septic lot size",IF(Q6<=P6,"Site area / parking","Density")))))) -> Septic lot size | U6: =IF(S6>0,1,0) -> 1 | V6: =IF(Use_Library!$K$5="Y",1,0)*U6 -> 1 | W6: =S6*Use_Library!$O$5*V6 -> 1200 | X6: =S6*Use_Library!$P$5*V6 -> 0 | Y6: =IF(Parcel!$C$27=1,W6+Parcel!$C$29,0)*V6 -> 1200 | Z6: =S6*Use_Library!$Q$5*Parcel!$C$27*V6 -> 24 | AA6: =IF(Parcel!$C$28=1,W6+Parcel!$C$30,0)*V6 -> 0 | AB6: =S6*Use_Library!$Q$5*Parcel!$C$28*V6 -> 0 | AC6: =IF(Parcel!$C$28=0,S6*Use_Library!$R$5,0)*V6 -> 24 | AD6: =IF(Parcel!$C$27=0,S6*Use_Library!$R$5,0)*V6 -> 0 | AE6: =I6*Parcel!$C$11*V6 -> 5.187 | AF6: =I6*V6 -> 14.82 | AG6: =IF(Use_Library!$C$5="For-Sale",IF(Use_Library!$E$5="Y",S6,1),1)*U6 -> 24 | AH6: =Cost_Library!$G$5*Parcel!$C$32*U6 -> 6500 | AI6: =AG6*Cost_Library!$G$6*Parcel!$C$32 -> 21600 | AJ6: =I6*Cost_Library!$G$7*Parcel!$C$32*V6 -> 74100 | AK6: =Cost_Library!$G$8*Parcel!$C$32*V6 -> 5000 | AL6: =AC6*Cost_Library!$G$9*Parcel!$C$32 -> 12000 | AM6: =Cost_Library!$G$10*U6 -> 2800 | AN6: =Cost_Library!$G$11*Parcel!$C$32*V6 -> 7500 | AO6: =Use_Library!$S$5*U6 -> 25000 | AP6: =Cost_Library!$G$12*U6 -> 10000 | AQ6: =AE6*Cost_Library!$G$13*Parcel!$C$32 -> 20748 | AR6: =AF6*Cost_Library!$G$14*Parcel!$C$32*Parcel!$C$33 -> 74100 | AS6: =W6*Cost_Library!$G$15*Parcel!$C$32 -> 180000 | AT6: =X6*Cost_Library!$G$16*Parcel!$C$32 -> 0 | AU6: =H6*Cost_Library!$G$17*Parcel!$C$32*V6 -> 34320 | AV6: =G6*Cost_Library!$G$18*Parcel!$C$32*V6 -> 10920 | AW6: =Y6*Cost_Library!$G$19*Parcel!$C$32 -> 60000 | AX6: =Z6*Cost_Library!$G$20 -> 60000 | AY6: =AA6*Cost_Library!$G$21*Parcel!$C$32 -> 0 | AZ6: =AB6*Cost_Library!$G$22 -> 0 | BA6: =AC6*Cost_Library!$G$23*Parcel!$C$32*Parcel!$C$34 -> 316800 | BB6: =AD6*Cost_Library!$G$24*Parcel!$C$32 -> 0 | BC6: =W6*Cost_Library!$G$25*Parcel!$C$32 -> 30000 | BD6: =SUM(AH6:BC6) -> 951388 | BE6: =BD6*Assumptions!$C$11 -> 95138.8 | BF6: =BD6+BE6 -> 1046526.8 | BG6: =S6*Use_Library!$T$5 -> 5880000 | BH6: =BG6*(Assumptions!$C$12+Assumptions!$C$13) -> 764400 | BI6: =S6*Use_Library!$AC$5 -> 0 | BJ6: =1+Assumptions!$C$14+Assumptions!$C$15*Use_Library!$AH$5/12 -> 1.045 | BK6: =1+Assumptions!$C$21*(Assumptions!$C$22*Use_Library!$AH$5/12*Assumptions!$C$24+Assumptions!$C$23) -> 1.038675 | BL6: =1+Assumptions!$C$21*(Assumptions!$C$22*(Use_Library!$AH$5/12*Assumptions!$C$24+IF(Use_Library!$C$5="Income",Use_Library!$AD$5,0)/12*Assumptions!$C$25)+Assumptions!$C$23) -> 1.038675 | BM6: =J6*Assumptions!$C$31*(1-Assumptions!$C$17)*U6 -> 0 | BN6: =IF(Use_Library!$AJ$5=1,IF(Use_Library!$C$5="For-Sale",S6*Use_Library!$U$5,E6*Use_Library!$AF$5)*(1-Assumptions!$C$17)+BM6,0)*U6 -> 1843200 | BO6: =(BD6-AT6)*(1+Assumptions!$C$11) -> 1046526.8 | BP6: =BJ6*BK6 -> 1.0854154 | BQ6: =(Parcel!$C$18*BJ6+BO6)*BK6 -> 1412625.8 | BR6: =BN6-BQ6 -> 430574.16 | BS6: =IF(AND(Use_Library!$AJ$5=1,U6=1),MAX(0,((1-Use_Library!$AI$5)*BN6-BO6*BK6)/BP6),0) -> 441967.92 | BT6: =BF6+BG6+BH6+BI6 -> 7690926.8 | BU6: =BJ6*BL6 -> 1.0854154 | BV6: =(Parcel!$C$18*BJ6+BT6)*BL6 -> 8313998 | BW6: =IF(Use_Library!$C$5="Income",S6*Use_Library!$W$5,0) -> 0 | BX6: =BW6*(1+Use_Library!$X$5)*(1-Use_Library!$Y$5) -> 0 | BY6: =IF(Use_Library!$C$5="Income",S6*Use_Library!$Z$5,0) -> 0 | BZ6: =IF(Use_Library!$C$5="Income",Assumptions!$C$19*Assumptions!$C$20*BV6,0) -> 0 | CA6: =BX6*Use_Library!$AA$5 -> 0 | CB6: =(BY6+BZ6)*Use_Library!$AB$5 -> 0 | CC6: =BX6-BY6-BZ6-CA6+CB6 -> 0 | CD6: =IF(AND(Use_Library!$C$5="Income",Use_Library!$AE$5>0),CC6/Use_Library!$AE$5,0) -> 0 | CE6: =IF(Use_Library!$C$5="Income",-Assumptions!$C$19*Assumptions!$C$20*(1-Use_Library!$AB$5)*BU6,0) -> 0 | CF6: =IF(BV6=0,0,CC6/BV6) -> 0 | CG6: =IF(Use_Library!$AK$5=1,IF(Use_Library!$C$5="Income",CD6*(1-Assumptions!$C$18),S6*Use_Library!$V$5*(1-Assumptions!$C$16))+BM6,0)*U6 -> 8460000 | CH6: =IF(AND(Use_Library!$AK$5=1,Use_Library!$C$5="Income",Use_Library!$AE$5>0),CE6/Use_Library!$AE$5*(1-Assumptions!$C$18),0) -> 0 | CI6: =CG6-BV6 -> 146001.99 | CJ6: =IF(AND(Use_Library!$AK$5=1,U6=1),MAX(0,Parcel!$C$18-((1-Use_Library!$AI$5)*CG6-BV6)/((1-Use_Library!$AI$5)*CH6-BU6)),0) -> 0 | CK6: =IF(Use_Library!$AL$5=1,IF(Use_Library!$C$5="Income",CD6,IF(Use_Library!$AE$5>0,E6*Use_Library!$AG$5/Use_Library!$AE$5,0))+BM6,0)*U6 -> 0 | CL6: =IF(Use_Library!$C$5="Income",BT6,BF6) -> 1046526.8 | CM6: =IF(Use_Library!$C$5="Income",BU6,BJ6*BK6) -> 1.0854154 | CN6: =IF(Use_Library!$C$5="Income",BV6,(Parcel!$C$18*BJ6+BF6)*BK6) -> 1412625.8 | CO6: =IF(AND(Use_Library!$AL$5=1,Use_Library!$C$5="Income",Use_Library!$AE$5>0),CE6/Use_Library!$AE$5,0) -> 0 | CP6: =CK6-CN6 -> -1412625.8 | CQ6: =IF(AND(Use_Library!$AL$5=1,U6=1),MAX(0,Parcel!$C$18-((1-Use_Library!$AI$5)*CK6-CN6)/((1-Use_Library!$AI$5)*CO6-CM6)),0) -> 0 | CR6: =IF(Use_Library!$C$5="Income",Assumptions!$C$21*(Parcel!$C$18*BJ6+BT6),0) -> 0 | CS6: =IF(AND(Use_Library!$C$5="Income",CC6>0),MIN(Assumptions!$C$26*CD6,PV(Assumptions!$C$29/12,Assumptions!$C$30*12,-CC6/Assumptions!$C$27/12),CC6/Assumptions!$C$28),0) -> 0 | CT6: =IF(CS6=0,0,CC6/(-PMT(Assumptions!$C$29/12,Assumptions!$C$30*12,CS6)*12)) -> 0 | CU6: =CS6-CR6 -> 0 | CV6: =MAX(BS6,CJ6,CQ6) -> 441967.92 | CW6: =IF(CV6<=0,"None works",IF(BS6=CV6,"Land / pad sale",IF(CJ6=CV6,"Build & sell","Build & hold / lease"))) -> Land / pad sale | CX6: =CV6*(1-Assumptions!$C$32) -> 375672.73 | CY6: =CV6-Parcel!$C$18 -> 141967.92 | CZ6: =IF(Parcel!$C$8=0,0,CV6/Parcel!$C$8) -> 22098.396 | DA6: =IF(S6=0,0,CV6/S6) -> 18415.33 | DB6: =TRIM(M6&" "&IF(AND(U6=0,N6=1),"Nothing fits. ","")&IF(Parcel!$C$12<Use_Library!$AM$5,"Frontage under "&Use_Library!$AM$5&" LF. ","")&IF(Parcel!$C$10>0.15,"Slope over 15%. ","")&IF(AND(U6=1,Use_Library!$M$5>0,D6>Use_Library!$M$5),"Only "&Use_Library!$M$5&" ac used - rest resold. ","")) | DC6: =CV6+ROW()/1000000 -> 441967.92
A7: =Use_Library!$A$6 -> Finished / entitled lots | B7: =Use_Library!$C$6 -> For-Sale | C7: =Use_Library!$D$6 -> lot | D7: =MAX(0,Parcel!$C$26*(1-Use_Library!$N$6-Assumptions!$C$7)) -> 14.196 | E7: =IF(Use_Library!$M$6>0,MIN(D7,Use_Library!$M$6),D7) -> 14.196 | F7: =IF(D7=0,0,E7/D7) -> 1 | G7: =Parcel!$C$26*F7 -> 15.6 | H7: =G7*Assumptions!$C$7 -> 0.624 | I7: =G7*(1-Use_Library!$N$6) -> 14.82 | J7: =Parcel!$C$8*(1-F7) -> 0 | K7: =IF(AND(Use_Library!$I$6="Y",Parcel!$C$28=0),0,1) -> 1 | L7: =IF(AND(Use_Library!$J$6="Y",Parcel!$C$27=0),0,1) -> 1 | M7: =TRIM(IF(AND(Use_Library!$AN$6>0,Parcel!$C$19<Use_Library!$AN$6),"Traffic under "&TEXT(Use_Library!$AN$6,"#,##0")&" VPD. ","")&IF(AND(Use_Library!$AO$6>0,Parcel!$C$20<Use_Library!$AO$6),"Under "&TEXT(Use_Library!$AO$6,"#,##0")&" households in 3 mi. ","")&IF(AND(Use_Library!$AP$6>0,Parcel!$C$21>Use_Library!$AP$6),"Over "&Use_Library!$AP$6&" mi to highway. ","")&IF(AND(Use_Library!$AQ$6="Y",Parcel!$C$22<>"Y"),"Needs a corner. ","")&IF(AND(Use_Library!$AR$6>0,Parcel!$C$23>Use_Library!$AR$6),"Over "&Use_Library!$AR$6&" mi to substation. ","")) | N7: =IF(M7="",1,0) -> 1 | O7: =IF(D7>=Use_Library!$L$6,1,0) -> 1 | P7: =IF(Use_Library!$F$6>0,G7*Use_Library!$F$6,1000000000) -> 62.4 | Q7: =IF(Use_Library!$G$6>0,E7*43560/Use_Library!$G$6,1000000000) -> 1000000000 | R7: =IF(AND(Use_Library!$H$6="Y",Parcel!$C$28=0),E7*(1-Assumptions!$C$8)/IF(Parcel!$C$27=1,Assumptions!$C$9,Assumptions!$C$10),1000000000) -> 24.1332 | S7: =IF(K7*L7*O7*N7=0,0,IF(MIN(P7,Q7,R7)>=1000000000,E7,IF(Use_Library!$E$6="Y",INT(MIN(P7,Q7,R7)),MIN(P7,Q7,R7)))) -> 24 | T7: =IF(N7=0,"Location fails",IF(O7=0,"Too small - needs "&Use_Library!$L$6&" usable ac",IF(K7=0,"Needs public sewer",IF(L7=0,"Needs public water",IF(R7<=MIN(P7,Q7),"Septic lot size",IF(Q7<=P7,"Site area / parking","Density")))))) -> Septic lot size | U7: =IF(S7>0,1,0) -> 1 | V7: =IF(Use_Library!$K$6="Y",1,0)*U7 -> 1 | W7: =S7*Use_Library!$O$6*V7 -> 1200 | X7: =S7*Use_Library!$P$6*V7 -> 0 | Y7: =IF(Parcel!$C$27=1,W7+Parcel!$C$29,0)*V7 -> 1200 | Z7: =S7*Use_Library!$Q$6*Parcel!$C$27*V7 -> 24 | AA7: =IF(Parcel!$C$28=1,W7+Parcel!$C$30,0)*V7 -> 0 | AB7: =S7*Use_Library!$Q$6*Parcel!$C$28*V7 -> 0 | AC7: =IF(Parcel!$C$28=0,S7*Use_Library!$R$6,0)*V7 -> 24 | AD7: =IF(Parcel!$C$27=0,S7*Use_Library!$R$6,0)*V7 -> 0 | AE7: =I7*Parcel!$C$11*V7 -> 5.187 | AF7: =I7*V7 -> 14.82 | AG7: =IF(Use_Library!$C$6="For-Sale",IF(Use_Library!$E$6="Y",S7,1),1)*U7 -> 24 | AH7: =Cost_Library!$G$5*Parcel!$C$32*U7 -> 6500 | AI7: =AG7*Cost_Library!$G$6*Parcel!$C$32 -> 21600 | AJ7: =I7*Cost_Library!$G$7*Parcel!$C$32*V7 -> 74100 | AK7: =Cost_Library!$G$8*Parcel!$C$32*V7 -> 5000 | AL7: =AC7*Cost_Library!$G$9*Parcel!$C$32 -> 12000 | AM7: =Cost_Library!$G$10*U7 -> 2800 | AN7: =Cost_Library!$G$11*Parcel!$C$32*V7 -> 7500 | AO7: =Use_Library!$S$6*U7 -> 25000 | AP7: =Cost_Library!$G$12*U7 -> 10000 | AQ7: =AE7*Cost_Library!$G$13*Parcel!$C$32 -> 20748 | AR7: =AF7*Cost_Library!$G$14*Parcel!$C$32*Parcel!$C$33 -> 74100 | AS7: =W7*Cost_Library!$G$15*Parcel!$C$32 -> 180000 | AT7: =X7*Cost_Library!$G$16*Parcel!$C$32 -> 0 | AU7: =H7*Cost_Library!$G$17*Parcel!$C$32*V7 -> 34320 | AV7: =G7*Cost_Library!$G$18*Parcel!$C$32*V7 -> 10920 | AW7: =Y7*Cost_Library!$G$19*Parcel!$C$32 -> 60000 | AX7: =Z7*Cost_Library!$G$20 -> 60000 | AY7: =AA7*Cost_Library!$G$21*Parcel!$C$32 -> 0 | AZ7: =AB7*Cost_Library!$G$22 -> 0 | BA7: =AC7*Cost_Library!$G$23*Parcel!$C$32*Parcel!$C$34 -> 316800 | BB7: =AD7*Cost_Library!$G$24*Parcel!$C$32 -> 0 | BC7: =W7*Cost_Library!$G$25*Parcel!$C$32 -> 30000 | BD7: =SUM(AH7:BC7) -> 951388 | BE7: =BD7*Assumptions!$C$11 -> 95138.8 | BF7: =BD7+BE7 -> 1046526.8 | BG7: =S7*Use_Library!$T$6 -> 0 | BH7: =BG7*(Assumptions!$C$12+Assumptions!$C$13) -> 0 | BI7: =S7*Use_Library!$AC$6 -> 0 | BJ7: =1+Assumptions!$C$14+Assumptions!$C$15*Use_Library!$AH$6/12 -> 1.045 | BK7: =1+Assumptions!$C$21*(Assumptions!$C$22*Use_Library!$AH$6/12*Assumptions!$C$24+Assumptions!$C$23) -> 1.038675 | BL7: =1+Assumptions!$C$21*(Assumptions!$C$22*(Use_Library!$AH$6/12*Assumptions!$C$24+IF(Use_Library!$C$6="Income",Use_Library!$AD$6,0)/12*Assumptions!$C$25)+Assumptions!$C$23) -> 1.038675 | BM7: =J7*Assumptions!$C$31*(1-Assumptions!$C$17)*U7 -> 0 | BN7: =IF(Use_Library!$AJ$6=1,IF(Use_Library!$C$6="For-Sale",S7*Use_Library!$U$6,E7*Use_Library!$AF$6)*(1-Assumptions!$C$17)+BM7,0)*U7 -> 1728000 | BO7: =(BD7-AT7)*(1+Assumptions!$C$11) -> 1046526.8 | BP7: =BJ7*BK7 -> 1.0854154 | BQ7: =(Parcel!$C$18*BJ7+BO7)*BK7 -> 1412625.8 | BR7: =BN7-BQ7 -> 315374.16 | BS7: =IF(AND(Use_Library!$AJ$6=1,U7=1),MAX(0,((1-Use_Library!$AI$6)*BN7-BO7*BK7)/BP7),0) -> 351753.61 | BT7: =BF7+BG7+BH7+BI7 -> 1046526.8 | BU7: =BJ7*BL7 -> 1.0854154 | BV7: =(Parcel!$C$18*BJ7+BT7)*BL7 -> 1412625.8 | BW7: =IF(Use_Library!$C$6="Income",S7*Use_Library!$W$6,0) -> 0 | BX7: =BW7*(1+Use_Library!$X$6)*(1-Use_Library!$Y$6) -> 0 | BY7: =IF(Use_Library!$C$6="Income",S7*Use_Library!$Z$6,0) -> 0 | BZ7: =IF(Use_Library!$C$6="Income",Assumptions!$C$19*Assumptions!$C$20*BV7,0) -> 0 | CA7: =BX7*Use_Library!$AA$6 -> 0 | CB7: =(BY7+BZ7)*Use_Library!$AB$6 -> 0 | CC7: =BX7-BY7-BZ7-CA7+CB7 -> 0 | CD7: =IF(AND(Use_Library!$C$6="Income",Use_Library!$AE$6>0),CC7/Use_Library!$AE$6,0) -> 0 | CE7: =IF(Use_Library!$C$6="Income",-Assumptions!$C$19*Assumptions!$C$20*(1-Use_Library!$AB$6)*BU7,0) -> 0 | CF7: =IF(BV7=0,0,CC7/BV7) -> 0 | CG7: =IF(Use_Library!$AK$6=1,IF(Use_Library!$C$6="Income",CD7*(1-Assumptions!$C$18),S7*Use_Library!$V$6*(1-Assumptions!$C$16))+BM7,0)*U7 -> 0 | CH7: =IF(AND(Use_Library!$AK$6=1,Use_Library!$C$6="Income",Use_Library!$AE$6>0),CE7/Use_Library!$AE$6*(1-Assumptions!$C$18),0) -> 0 | CI7: =CG7-BV7 -> -1412625.8 | CJ7: =IF(AND(Use_Library!$AK$6=1,U7=1),MAX(0,Parcel!$C$18-((1-Use_Library!$AI$6)*CG7-BV7)/((1-Use_Library!$AI$6)*CH7-BU7)),0) -> 0 | CK7: =IF(Use_Library!$AL$6=1,IF(Use_Library!$C$6="Income",CD7,IF(Use_Library!$AE$6>0,E7*Use_Library!$AG$6/Use_Library!$AE$6,0))+BM7,0)*U7 -> 0 | CL7: =IF(Use_Library!$C$6="Income",BT7,BF7) -> 1046526.8 | CM7: =IF(Use_Library!$C$6="Income",BU7,BJ7*BK7) -> 1.0854154 | CN7: =IF(Use_Library!$C$6="Income",BV7,(Parcel!$C$18*BJ7+BF7)*BK7) -> 1412625.8 | CO7: =IF(AND(Use_Library!$AL$6=1,Use_Library!$C$6="Income",Use_Library!$AE$6>0),CE7/Use_Library!$AE$6,0) -> 0 | CP7: =CK7-CN7 -> -1412625.8 | CQ7: =IF(AND(Use_Library!$AL$6=1,U7=1),MAX(0,Parcel!$C$18-((1-Use_Library!$AI$6)*CK7-CN7)/((1-Use_Library!$AI$6)*CO7-CM7)),0) -> 0 | CR7: =IF(Use_Library!$C$6="Income",Assumptions!$C$21*(Parcel!$C$18*BJ7+BT7),0) -> 0 | CS7: =IF(AND(Use_Library!$C$6="Income",CC7>0),MIN(Assumptions!$C$26*CD7,PV(Assumptions!$C$29/12,Assumptions!$C$30*12,-CC7/Assumptions!$C$27/12),CC7/Assumptions!$C$28),0) -> 0 | CT7: =IF(CS7=0,0,CC7/(-PMT(Assumptions!$C$29/12,Assumptions!$C$30*12,CS7)*12)) -> 0 | CU7: =CS7-CR7 -> 0 | CV7: =MAX(BS7,CJ7,CQ7) -> 351753.61 | CW7: =IF(CV7<=0,"None works",IF(BS7=CV7,"Land / pad sale",IF(CJ7=CV7,"Build & sell","Build & hold / lease"))) -> Land / pad sale | CX7: =CV7*(1-Assumptions!$C$32) -> 298990.57 | CY7: =CV7-Parcel!$C$18 -> 51753.61 | CZ7: =IF(Parcel!$C$8=0,0,CV7/Parcel!$C$8) -> 17587.68 | DA7: =IF(S7=0,0,CV7/S7) -> 14656.4 | DB7: =TRIM(M7&" "&IF(AND(U7=0,N7=1),"Nothing fits. ","")&IF(Parcel!$C$12<Use_Library!$AM$6,"Frontage under "&Use_Library!$AM$6&" LF. ","")&IF(Parcel!$C$10>0.15,"Slope over 15%. ","")&IF(AND(U7=1,Use_Library!$M$6>0,D7>Use_Library!$M$6),"Only "&Use_Library!$M$6&" ac used - rest resold. ","")) | DC7: =CV7+ROW()/1000000 -> 351753.61
A8: =Use_Library!$A$7 -> Active-adult 55+ (for sale) | B8: =Use_Library!$C$7 -> For-Sale | C8: =Use_Library!$D$7 -> lot / home | D8: =MAX(0,Parcel!$C$26*(1-Use_Library!$N$7-Assumptions!$C$7)) -> 14.196 | E8: =IF(Use_Library!$M$7>0,MIN(D8,Use_Library!$M$7),D8) -> 14.196 | F8: =IF(D8=0,0,E8/D8) -> 1 | G8: =Parcel!$C$26*F8 -> 15.6 | H8: =G8*Assumptions!$C$7 -> 0.624 | I8: =G8*(1-Use_Library!$N$7) -> 14.82 | J8: =Parcel!$C$8*(1-F8) -> 0 | K8: =IF(AND(Use_Library!$I$7="Y",Parcel!$C$28=0),0,1) -> 1 | L8: =IF(AND(Use_Library!$J$7="Y",Parcel!$C$27=0),0,1) -> 1 | M8: =TRIM(IF(AND(Use_Library!$AN$7>0,Parcel!$C$19<Use_Library!$AN$7),"Traffic under "&TEXT(Use_Library!$AN$7,"#,##0")&" VPD. ","")&IF(AND(Use_Library!$AO$7>0,Parcel!$C$20<Use_Library!$AO$7),"Under "&TEXT(Use_Library!$AO$7,"#,##0")&" households in 3 mi. ","")&IF(AND(Use_Library!$AP$7>0,Parcel!$C$21>Use_Library!$AP$7),"Over "&Use_Library!$AP$7&" mi to highway. ","")&IF(AND(Use_Library!$AQ$7="Y",Parcel!$C$22<>"Y"),"Needs a corner. ","")&IF(AND(Use_Library!$AR$7>0,Parcel!$C$23>Use_Library!$AR$7),"Over "&Use_Library!$AR$7&" mi to substation. ","")) | N8: =IF(M8="",1,0) -> 1 | O8: =IF(D8>=Use_Library!$L$7,1,0) -> 1 | P8: =IF(Use_Library!$F$7>0,G8*Use_Library!$F$7,1000000000) -> 78 | Q8: =IF(Use_Library!$G$7>0,E8*43560/Use_Library!$G$7,1000000000) -> 1000000000 | R8: =IF(AND(Use_Library!$H$7="Y",Parcel!$C$28=0),E8*(1-Assumptions!$C$8)/IF(Parcel!$C$27=1,Assumptions!$C$9,Assumptions!$C$10),1000000000) -> 24.1332 | S8: =IF(K8*L8*O8*N8=0,0,IF(MIN(P8,Q8,R8)>=1000000000,E8,IF(Use_Library!$E$7="Y",INT(MIN(P8,Q8,R8)),MIN(P8,Q8,R8)))) -> 24 | T8: =IF(N8=0,"Location fails",IF(O8=0,"Too small - needs "&Use_Library!$L$7&" usable ac",IF(K8=0,"Needs public sewer",IF(L8=0,"Needs public water",IF(R8<=MIN(P8,Q8),"Septic lot size",IF(Q8<=P8,"Site area / parking","Density")))))) -> Septic lot size | U8: =IF(S8>0,1,0) -> 1 | V8: =IF(Use_Library!$K$7="Y",1,0)*U8 -> 1 | W8: =S8*Use_Library!$O$7*V8 -> 1080 | X8: =S8*Use_Library!$P$7*V8 -> 0 | Y8: =IF(Parcel!$C$27=1,W8+Parcel!$C$29,0)*V8 -> 1080 | Z8: =S8*Use_Library!$Q$7*Parcel!$C$27*V8 -> 24 | AA8: =IF(Parcel!$C$28=1,W8+Parcel!$C$30,0)*V8 -> 0 | AB8: =S8*Use_Library!$Q$7*Parcel!$C$28*V8 -> 0 | AC8: =IF(Parcel!$C$28=0,S8*Use_Library!$R$7,0)*V8 -> 24 | AD8: =IF(Parcel!$C$27=0,S8*Use_Library!$R$7,0)*V8 -> 0 | AE8: =I8*Parcel!$C$11*V8 -> 5.187 | AF8: =I8*V8 -> 14.82 | AG8: =IF(Use_Library!$C$7="For-Sale",IF(Use_Library!$E$7="Y",S8,1),1)*U8 -> 24 | AH8: =Cost_Library!$G$5*Parcel!$C$32*U8 -> 6500 | AI8: =AG8*Cost_Library!$G$6*Parcel!$C$32 -> 21600 | AJ8: =I8*Cost_Library!$G$7*Parcel!$C$32*V8 -> 74100 | AK8: =Cost_Library!$G$8*Parcel!$C$32*V8 -> 5000 | AL8: =AC8*Cost_Library!$G$9*Parcel!$C$32 -> 12000 | AM8: =Cost_Library!$G$10*U8 -> 2800 | AN8: =Cost_Library!$G$11*Parcel!$C$32*V8 -> 7500 | AO8: =Use_Library!$S$7*U8 -> 25000 | AP8: =Cost_Library!$G$12*U8 -> 10000 | AQ8: =AE8*Cost_Library!$G$13*Parcel!$C$32 -> 20748 | AR8: =AF8*Cost_Library!$G$14*Parcel!$C$32*Parcel!$C$33 -> 74100 | AS8: =W8*Cost_Library!$G$15*Parcel!$C$32 -> 162000 | AT8: =X8*Cost_Library!$G$16*Parcel!$C$32 -> 0 | AU8: =H8*Cost_Library!$G$17*Parcel!$C$32*V8 -> 34320 | AV8: =G8*Cost_Library!$G$18*Parcel!$C$32*V8 -> 10920 | AW8: =Y8*Cost_Library!$G$19*Parcel!$C$32 -> 54000 | AX8: =Z8*Cost_Library!$G$20 -> 60000 | AY8: =AA8*Cost_Library!$G$21*Parcel!$C$32 -> 0 | AZ8: =AB8*Cost_Library!$G$22 -> 0 | BA8: =AC8*Cost_Library!$G$23*Parcel!$C$32*Parcel!$C$34 -> 316800 | BB8: =AD8*Cost_Library!$G$24*Parcel!$C$32 -> 0 | BC8: =W8*Cost_Library!$G$25*Parcel!$C$32 -> 27000 | BD8: =SUM(AH8:BC8) -> 924388 | BE8: =BD8*Assumptions!$C$11 -> 92438.8 | BF8: =BD8+BE8 -> 1016826.8 | BG8: =S8*Use_Library!$T$7 -> 5520000 | BH8: =BG8*(Assumptions!$C$12+Assumptions!$C$13) -> 717600 | BI8: =S8*Use_Library!$AC$7 -> 0 | BJ8: =1+Assumptions!$C$14+Assumptions!$C$15*Use_Library!$AH$7/12 -> 1.045 | BK8: =1+Assumptions!$C$21*(Assumptions!$C$22*Use_Library!$AH$7/12*Assumptions!$C$24+Assumptions!$C$23) -> 1.038675 | BL8: =1+Assumptions!$C$21*(Assumptions!$C$22*(Use_Library!$AH$7/12*Assumptions!$C$24+IF(Use_Library!$C$7="Income",Use_Library!$AD$7,0)/12*Assumptions!$C$25)+Assumptions!$C$23) -> 1.038675 | BM8: =J8*Assumptions!$C$31*(1-Assumptions!$C$17)*U8 -> 0 | BN8: =IF(Use_Library!$AJ$7=1,IF(Use_Library!$C$7="For-Sale",S8*Use_Library!$U$7,E8*Use_Library!$AF$7)*(1-Assumptions!$C$17)+BM8,0)*U8 -> 1612800 | BO8: =(BD8-AT8)*(1+Assumptions!$C$11) -> 1016826.8 | BP8: =BJ8*BK8 -> 1.0854154 | BQ8: =(Parcel!$C$18*BJ8+BO8)*BK8 -> 1381777.2 | BR8: =BN8-BQ8 -> 231022.81 | BS8: =IF(AND(Use_Library!$AJ$7=1,U8=1),MAX(0,((1-Use_Library!$AI$7)*BN8-BO8*BK8)/BP8),0) -> 289960.35 | BT8: =BF8+BG8+BH8+BI8 -> 7254426.8 | BU8: =BJ8*BL8 -> 1.0854154 | BV8: =(Parcel!$C$18*BJ8+BT8)*BL8 -> 7860616.4 | BW8: =IF(Use_Library!$C$7="Income",S8*Use_Library!$W$7,0) -> 0 | BX8: =BW8*(1+Use_Library!$X$7)*(1-Use_Library!$Y$7) -> 0 | BY8: =IF(Use_Library!$C$7="Income",S8*Use_Library!$Z$7,0) -> 0 | BZ8: =IF(Use_Library!$C$7="Income",Assumptions!$C$19*Assumptions!$C$20*BV8,0) -> 0 | CA8: =BX8*Use_Library!$AA$7 -> 0 | CB8: =(BY8+BZ8)*Use_Library!$AB$7 -> 0 | CC8: =BX8-BY8-BZ8-CA8+CB8 -> 0 | CD8: =IF(AND(Use_Library!$C$7="Income",Use_Library!$AE$7>0),CC8/Use_Library!$AE$7,0) -> 0 | CE8: =IF(Use_Library!$C$7="Income",-Assumptions!$C$19*Assumptions!$C$20*(1-Use_Library!$AB$7)*BU8,0) -> 0 | CF8: =IF(BV8=0,0,CC8/BV8) -> 0 | CG8: =IF(Use_Library!$AK$7=1,IF(Use_Library!$C$7="Income",CD8*(1-Assumptions!$C$18),S8*Use_Library!$V$7*(1-Assumptions!$C$16))+BM8,0)*U8 -> 8121600 | CH8: =IF(AND(Use_Library!$AK$7=1,Use_Library!$C$7="Income",Use_Library!$AE$7>0),CE8/Use_Library!$AE$7*(1-Assumptions!$C$18),0) -> 0 | CI8: =CG8-BV8 -> 260983.63 | CJ8: =IF(AND(Use_Library!$AK$7=1,U8=1),MAX(0,Parcel!$C$18-((1-Use_Library!$AI$7)*CG8-BV8)/((1-Use_Library!$AI$7)*CH8-BU8)),0) -> 0 | CK8: =IF(Use_Library!$AL$7=1,IF(Use_Library!$C$7="Income",CD8,IF(Use_Library!$AE$7>0,E8*Use_Library!$AG$7/Use_Library!$AE$7,0))+BM8,0)*U8 -> 0 | CL8: =IF(Use_Library!$C$7="Income",BT8,BF8) -> 1016826.8 | CM8: =IF(Use_Library!$C$7="Income",BU8,BJ8*BK8) -> 1.0854154 | CN8: =IF(Use_Library!$C$7="Income",BV8,(Parcel!$C$18*BJ8+BF8)*BK8) -> 1381777.2 | CO8: =IF(AND(Use_Library!$AL$7=1,Use_Library!$C$7="Income",Use_Library!$AE$7>0),CE8/Use_Library!$AE$7,0) -> 0 | CP8: =CK8-CN8 -> -1381777.2 | CQ8: =IF(AND(Use_Library!$AL$7=1,U8=1),MAX(0,Parcel!$C$18-((1-Use_Library!$AI$7)*CK8-CN8)/((1-Use_Library!$AI$7)*CO8-CM8)),0) -> 0 | CR8: =IF(Use_Library!$C$7="Income",Assumptions!$C$21*(Parcel!$C$18*BJ8+BT8),0) -> 0 | CS8: =IF(AND(Use_Library!$C$7="Income",CC8>0),MIN(Assumptions!$C$26*CD8,PV(Assumptions!$C$29/12,Assumptions!$C$30*12,-CC8/Assumptions!$C$27/12),CC8/Assumptions!$C$28),0) -> 0 | CT8: =IF(CS8=0,0,CC8/(-PMT(Assumptions!$C$29/12,Assumptions!$C$30*12,CS8)*12)) -> 0 | CU8: =CS8-CR8 -> 0 | CV8: =MAX(BS8,CJ8,CQ8) -> 289960.35 | CW8: =IF(CV8<=0,"None works",IF(BS8=CV8,"Land / pad sale",IF(CJ8=CV8,"Build & sell","Build & hold / lease"))) -> Land / pad sale | CX8: =CV8*(1-Assumptions!$C$32) -> 246466.3 | CY8: =CV8-Parcel!$C$18 -> -10039.649 | CZ8: =IF(Parcel!$C$8=0,0,CV8/Parcel!$C$8) -> 14498.018 | DA8: =IF(S8=0,0,CV8/S8) -> 12081.681 | DB8: =TRIM(M8&" "&IF(AND(U8=0,N8=1),"Nothing fits. ","")&IF(Parcel!$C$12<Use_Library!$AM$7,"Frontage under "&Use_Library!$AM$7&" LF. ","")&IF(Parcel!$C$10>0.15,"Slope over 15%. ","")&IF(AND(U8=1,Use_Library!$M$7>0,D8>Use_Library!$M$7),"Only "&Use_Library!$M$7&" ac used - rest resold. ","")) | DC8: =CV8+ROW()/1000000 -> 289960.35
A9: =Use_Library!$A$8 -> Entry-level for-sale homes | B9: =Use_Library!$C$8 -> For-Sale | C9: =Use_Library!$D$8 -> lot / home | D9: =MAX(0,Parcel!$C$26*(1-Use_Library!$N$8-Assumptions!$C$7)) -> 14.196 | E9: =IF(Use_Library!$M$8>0,MIN(D9,Use_Library!$M$8),D9) -> 14.196 | F9: =IF(D9=0,0,E9/D9) -> 1 | G9: =Parcel!$C$26*F9 -> 15.6 | H9: =G9*Assumptions!$C$7 -> 0.624 | I9: =G9*(1-Use_Library!$N$8) -> 14.82 | J9: =Parcel!$C$8*(1-F9) -> 0 | K9: =IF(AND(Use_Library!$I$8="Y",Parcel!$C$28=0),0,1) -> 1 | L9: =IF(AND(Use_Library!$J$8="Y",Parcel!$C$27=0),0,1) -> 1 | M9: =TRIM(IF(AND(Use_Library!$AN$8>0,Parcel!$C$19<Use_Library!$AN$8),"Traffic under "&TEXT(Use_Library!$AN$8,"#,##0")&" VPD. ","")&IF(AND(Use_Library!$AO$8>0,Parcel!$C$20<Use_Library!$AO$8),"Under "&TEXT(Use_Library!$AO$8,"#,##0")&" households in 3 mi. ","")&IF(AND(Use_Library!$AP$8>0,Parcel!$C$21>Use_Library!$AP$8),"Over "&Use_Library!$AP$8&" mi to highway. ","")&IF(AND(Use_Library!$AQ$8="Y",Parcel!$C$22<>"Y"),"Needs a corner. ","")&IF(AND(Use_Library!$AR$8>0,Parcel!$C$23>Use_Library!$AR$8),"Over "&Use_Library!$AR$8&" mi to substation. ","")) | N9: =IF(M9="",1,0) -> 1 | O9: =IF(D9>=Use_Library!$L$8,1,0) -> 1 | P9: =IF(Use_Library!$F$8>0,G9*Use_Library!$F$8,1000000000) -> 78 | Q9: =IF(Use_Library!$G$8>0,E9*43560/Use_Library!$G$8,1000000000) -> 1000000000 | R9: =IF(AND(Use_Library!$H$8="Y",Parcel!$C$28=0),E9*(1-Assumptions!$C$8)/IF(Parcel!$C$27=1,Assumptions!$C$9,Assumptions!$C$10),1000000000) -> 24.1332 | S9: =IF(K9*L9*O9*N9=0,0,IF(MIN(P9,Q9,R9)>=1000000000,E9,IF(Use_Library!$E$8="Y",INT(MIN(P9,Q9,R9)),MIN(P9,Q9,R9)))) -> 24 | T9: =IF(N9=0,"Location fails",IF(O9=0,"Too small - needs "&Use_Library!$L$8&" usable ac",IF(K9=0,"Needs public sewer",IF(L9=0,"Needs public water",IF(R9<=MIN(P9,Q9),"Septic lot size",IF(Q9<=P9,"Site area / parking","Density")))))) -> Septic lot size | U9: =IF(S9>0,1,0) -> 1 | V9: =IF(Use_Library!$K$8="Y",1,0)*U9 -> 1 | W9: =S9*Use_Library!$O$8*V9 -> 1080 | X9: =S9*Use_Library!$P$8*V9 -> 0 | Y9: =IF(Parcel!$C$27=1,W9+Parcel!$C$29,0)*V9 -> 1080 | Z9: =S9*Use_Library!$Q$8*Parcel!$C$27*V9 -> 24 | AA9: =IF(Parcel!$C$28=1,W9+Parcel!$C$30,0)*V9 -> 0 | AB9: =S9*Use_Library!$Q$8*Parcel!$C$28*V9 -> 0 | AC9: =IF(Parcel!$C$28=0,S9*Use_Library!$R$8,0)*V9 -> 24 | AD9: =IF(Parcel!$C$27=0,S9*Use_Library!$R$8,0)*V9 -> 0 | AE9: =I9*Parcel!$C$11*V9 -> 5.187 | AF9: =I9*V9 -> 14.82 | AG9: =IF(Use_Library!$C$8="For-Sale",IF(Use_Library!$E$8="Y",S9,1),1)*U9 -> 24 | AH9: =Cost_Library!$G$5*Parcel!$C$32*U9 -> 6500 | AI9: =AG9*Cost_Library!$G$6*Parcel!$C$32 -> 21600 | AJ9: =I9*Cost_Library!$G$7*Parcel!$C$32*V9 -> 74100 | AK9: =Cost_Library!$G$8*Parcel!$C$32*V9 -> 5000 | AL9: =AC9*Cost_Library!$G$9*Parcel!$C$32 -> 12000 | AM9: =Cost_Library!$G$10*U9 -> 2800 | AN9: =Cost_Library!$G$11*Parcel!$C$32*V9 -> 7500 | AO9: =Use_Library!$S$8*U9 -> 25000 | AP9: =Cost_Library!$G$12*U9 -> 10000 | AQ9: =AE9*Cost_Library!$G$13*Parcel!$C$32 -> 20748 | AR9: =AF9*Cost_Library!$G$14*Parcel!$C$32*Parcel!$C$33 -> 74100 | AS9: =W9*Cost_Library!$G$15*Parcel!$C$32 -> 162000 | AT9: =X9*Cost_Library!$G$16*Parcel!$C$32 -> 0 | AU9: =H9*Cost_Library!$G$17*Parcel!$C$32*V9 -> 34320 | AV9: =G9*Cost_Library!$G$18*Parcel!$C$32*V9 -> 10920 | AW9: =Y9*Cost_Library!$G$19*Parcel!$C$32 -> 54000 | AX9: =Z9*Cost_Library!$G$20 -> 60000 | AY9: =AA9*Cost_Library!$G$21*Parcel!$C$32 -> 0 | AZ9: =AB9*Cost_Library!$G$22 -> 0 | BA9: =AC9*Cost_Library!$G$23*Parcel!$C$32*Parcel!$C$34 -> 316800 | BB9: =AD9*Cost_Library!$G$24*Parcel!$C$32 -> 0 | BC9: =W9*Cost_Library!$G$25*Parcel!$C$32 -> 27000 | BD9: =SUM(AH9:BC9) -> 924388 | BE9: =BD9*Assumptions!$C$11 -> 92438.8 | BF9: =BD9+BE9 -> 1016826.8 | BG9: =S9*Use_Library!$T$8 -> 5040000 | BH9: =BG9*(Assumptions!$C$12+Assumptions!$C$13) -> 655200 | BI9: =S9*Use_Library!$AC$8 -> 0 | BJ9: =1+Assumptions!$C$14+Assumptions!$C$15*Use_Library!$AH$8/12 -> 1.045 | BK9: =1+Assumptions!$C$21*(Assumptions!$C$22*Use_Library!$AH$8/12*Assumptions!$C$24+Assumptions!$C$23) -> 1.038675 | BL9: =1+Assumptions!$C$21*(Assumptions!$C$22*(Use_Library!$AH$8/12*Assumptions!$C$24+IF(Use_Library!$C$8="Income",Use_Library!$AD$8,0)/12*Assumptions!$C$25)+Assumptions!$C$23) -> 1.038675 | BM9: =J9*Assumptions!$C$31*(1-Assumptions!$C$17)*U9 -> 0 | BN9: =IF(Use_Library!$AJ$8=1,IF(Use_Library!$C$8="For-Sale",S9*Use_Library!$U$8,E9*Use_Library!$AF$8)*(1-Assumptions!$C$17)+BM9,0)*U9 -> 1497600 | BO9: =(BD9-AT9)*(1+Assumptions!$C$11) -> 1016826.8 | BP9: =BJ9*BK9 -> 1.0854154 | BQ9: =(Parcel!$C$18*BJ9+BO9)*BK9 -> 1381777.2 | BR9: =BN9-BQ9 -> 115822.81 | BS9: =IF(AND(Use_Library!$AJ$8=1,U9=1),MAX(0,((1-Use_Library!$AI$8)*BN9-BO9*BK9)/BP9),0) -> 199746.04 | BT9: =BF9+BG9+BH9+BI9 -> 6712026.8 | BU9: =BJ9*BL9 -> 1.0854154 | BV9: =(Parcel!$C$18*BJ9+BT9)*BL9 -> 7297239 | BW9: =IF(Use_Library!$C$8="Income",S9*Use_Library!$W$8,0) -> 0 | BX9: =BW9*(1+Use_Library!$X$8)*(1-Use_Library!$Y$8) -> 0 | BY9: =IF(Use_Library!$C$8="Income",S9*Use_Library!$Z$8,0) -> 0 | BZ9: =IF(Use_Library!$C$8="Income",Assumptions!$C$19*Assumptions!$C$20*BV9,0) -> 0 | CA9: =BX9*Use_Library!$AA$8 -> 0 | CB9: =(BY9+BZ9)*Use_Library!$AB$8 -> 0 | CC9: =BX9-BY9-BZ9-CA9+CB9 -> 0 | CD9: =IF(AND(Use_Library!$C$8="Income",Use_Library!$AE$8>0),CC9/Use_Library!$AE$8,0) -> 0 | CE9: =IF(Use_Library!$C$8="Income",-Assumptions!$C$19*Assumptions!$C$20*(1-Use_Library!$AB$8)*BU9,0) -> 0 | CF9: =IF(BV9=0,0,CC9/BV9) -> 0 | CG9: =IF(Use_Library!$AK$8=1,IF(Use_Library!$C$8="Income",CD9*(1-Assumptions!$C$18),S9*Use_Library!$V$8*(1-Assumptions!$C$16))+BM9,0)*U9 -> 6993600 | CH9: =IF(AND(Use_Library!$AK$8=1,Use_Library!$C$8="Income",Use_Library!$AE$8>0),CE9/Use_Library!$AE$8*(1-Assumptions!$C$18),0) -> 0 | CI9: =CG9-BV9 -> -303639.05 | CJ9: =IF(AND(Use_Library!$AK$8=1,U9=1),MAX(0,Parcel!$C$18-((1-Use_Library!$AI$8)*CG9-BV9)/((1-Use_Library!$AI$8)*CH9-BU9)),0) -> 0 | CK9: =IF(Use_Library!$AL$8=1,IF(Use_Library!$C$8="Income",CD9,IF(Use_Library!$AE$8>0,E9*Use_Library!$AG$8/Use_Library!$AE$8,0))+BM9,0)*U9 -> 0 | CL9: =IF(Use_Library!$C$8="Income",BT9,BF9) -> 1016826.8 | CM9: =IF(Use_Library!$C$8="Income",BU9,BJ9*BK9) -> 1.0854154 | CN9: =IF(Use_Library!$C$8="Income",BV9,(Parcel!$C$18*BJ9+BF9)*BK9) -> 1381777.2 | CO9: =IF(AND(Use_Library!$AL$8=1,Use_Library!$C$8="Income",Use_Library!$AE$8>0),CE9/Use_Library!$AE$8,0) -> 0 | CP9: =CK9-CN9 -> -1381777.2 | CQ9: =IF(AND(Use_Library!$AL$8=1,U9=1),MAX(0,Parcel!$C$18-((1-Use_Library!$AI$8)*CK9-CN9)/((1-Use_Library!$AI$8)*CO9-CM9)),0) -> 0 | CR9: =IF(Use_Library!$C$8="Income",Assumptions!$C$21*(Parcel!$C$18*BJ9+BT9),0) -> 0 | CS9: =IF(AND(Use_Library!$C$8="Income",CC9>0),MIN(Assumptions!$C$26*CD9,PV(Assumptions!$C$29/12,Assumptions!$C$30*12,-CC9/Assumptions!$C$27/12),CC9/Assumptions!$C$28),0) -> 0 | CT9: =IF(CS9=0,0,CC9/(-PMT(Assumptions!$C$29/12,Assumptions!$C$30*12,CS9)*12)) -> 0 | CU9: =CS9-CR9 -> 0 | CV9: =MAX(BS9,CJ9,CQ9) -> 199746.04 | CW9: =IF(CV9<=0,"None works",IF(BS9=CV9,"Land / pad sale",IF(CJ9=CV9,"Build & sell","Build & hold / lease"))) -> Land / pad sale | CX9: =CV9*(1-Assumptions!$C$32) -> 169784.13 | CY9: =CV9-Parcel!$C$18 -> -100253.96 | CZ9: =IF(Parcel!$C$8=0,0,CV9/Parcel!$C$8) -> 9987.302 | DA9: =IF(S9=0,0,CV9/S9) -> 8322.7517 | DB9: =TRIM(M9&" "&IF(AND(U9=0,N9=1),"Nothing fits. ","")&IF(Parcel!$C$12<Use_Library!$AM$8,"Frontage under "&Use_Library!$AM$8&" LF. ","")&IF(Parcel!$C$10>0.15,"Slope over 15%. ","")&IF(AND(U9=1,Use_Library!$M$8>0,D9>Use_Library!$M$8),"Only "&Use_Library!$M$8&" ac used - rest resold. ","")) | DC9: =CV9+ROW()/1000000 -> 199746.04
A10: =Use_Library!$A$9 -> Manufactured home subdivision | B10: =Use_Library!$C$9 -> For-Sale | C10: =Use_Library!$D$9 -> lot / home | D10: =MAX(0,Parcel!$C$26*(1-Use_Library!$N$9-Assumptions!$C$7)) -> 14.196 | E10: =IF(Use_Library!$M$9>0,MIN(D10,Use_Library!$M$9),D10) -> 14.196 | F10: =IF(D10=0,0,E10/D10) -> 1 | G10: =Parcel!$C$26*F10 -> 15.6 | H10: =G10*Assumptions!$C$7 -> 0.624 | I10: =G10*(1-Use_Library!$N$9) -> 14.82 | J10: =Parcel!$C$8*(1-F10) -> 0 | K10: =IF(AND(Use_Library!$I$9="Y",Parcel!$C$28=0),0,1) -> 1 | L10: =IF(AND(Use_Library!$J$9="Y",Parcel!$C$27=0),0,1) -> 1 | M10: =TRIM(IF(AND(Use_Library!$AN$9>0,Parcel!$C$19<Use_Library!$AN$9),"Traffic under "&TEXT(Use_Library!$AN$9,"#,##0")&" VPD. ","")&IF(AND(Use_Library!$AO$9>0,Parcel!$C$20<Use_Library!$AO$9),"Under "&TEXT(Use_Library!$AO$9,"#,##0")&" households in 3 mi. ","")&IF(AND(Use_Library!$AP$9>0,Parcel!$C$21>Use_Library!$AP$9),"Over "&Use_Library!$AP$9&" mi to highway. ","")&IF(AND(Use_Library!$AQ$9="Y",Parcel!$C$22<>"Y"),"Needs a corner. ","")&IF(AND(Use_Library!$AR$9>0,Parcel!$C$23>Use_Library!$AR$9),"Over "&Use_Library!$AR$9&" mi to substation. ","")) | N10: =IF(M10="",1,0) -> 1 | O10: =IF(D10>=Use_Library!$L$9,1,0) -> 1 | P10: =IF(Use_Library!$F$9>0,G10*Use_Library!$F$9,1000000000) -> 62.4 | Q10: =IF(Use_Library!$G$9>0,E10*43560/Use_Library!$G$9,1000000000) -> 1000000000 | R10: =IF(AND(Use_Library!$H$9="Y",Parcel!$C$28=0),E10*(1-Assumptions!$C$8)/IF(Parcel!$C$27=1,Assumptions!$C$9,Assumptions!$C$10),1000000000) -> 24.1332 | S10: =IF(K10*L10*O10*N10=0,0,IF(MIN(P10,Q10,R10)>=1000000000,E10,IF(Use_Library!$E$9="Y",INT(MIN(P10,Q10,R10)),MIN(P10,Q10,R10)))) -> 24 | T10: =IF(N10=0,"Location fails",IF(O10=0,"Too small - needs "&Use_Library!$L$9&" usable ac",IF(K10=0,"Needs public sewer",IF(L10=0,"Needs public water",IF(R10<=MIN(P10,Q10),"Septic lot size",IF(Q10<=P10,"Site area / parking","Density")))))) -> Septic lot size | U10: =IF(S10>0,1,0) -> 1 | V10: =IF(Use_Library!$K$9="Y",1,0)*U10 -> 1 | W10: =S10*Use_Library!$O$9*V10 -> 1200 | X10: =S10*Use_Library!$P$9*V10 -> 0 | Y10: =IF(Parcel!$C$27=1,W10+Parcel!$C$29,0)*V10 -> 1200 | Z10: =S10*Use_Library!$Q$9*Parcel!$C$27*V10 -> 24 | AA10: =IF(Parcel!$C$28=1,W10+Parcel!$C$30,0)*V10 -> 0 | AB10: =S10*Use_Library!$Q$9*Parcel!$C$28*V10 -> 0 | AC10: =IF(Parcel!$C$28=0,S10*Use_Library!$R$9,0)*V10 -> 24 | AD10: =IF(Parcel!$C$27=0,S10*Use_Library!$R$9,0)*V10 -> 0 | AE10: =I10*Parcel!$C$11*V10 -> 5.187 | AF10: =I10*V10 -> 14.82 | AG10: =IF(Use_Library!$C$9="For-Sale",IF(Use_Library!$E$9="Y",S10,1),1)*U10 -> 24 | AH10: =Cost_Library!$G$5*Parcel!$C$32*U10 -> 6500 | AI10: =AG10*Cost_Library!$G$6*Parcel!$C$32 -> 21600 | AJ10: =I10*Cost_Library!$G$7*Parcel!$C$32*V10 -> 74100 | AK10: =Cost_Library!$G$8*Parcel!$C$32*V10 -> 5000 | AL10: =AC10*Cost_Library!$G$9*Parcel!$C$32 -> 12000 | AM10: =Cost_Library!$G$10*U10 -> 2800 | AN10: =Cost_Library!$G$11*Parcel!$C$32*V10 -> 7500 | AO10: =Use_Library!$S$9*U10 -> 25000 | AP10: =Cost_Library!$G$12*U10 -> 10000 | AQ10: =AE10*Cost_Library!$G$13*Parcel!$C$32 -> 20748 | AR10: =AF10*Cost_Library!$G$14*Parcel!$C$32*Parcel!$C$33 -> 74100 | AS10: =W10*Cost_Library!$G$15*Parcel!$C$32 -> 180000 | AT10: =X10*Cost_Library!$G$16*Parcel!$C$32 -> 0 | AU10: =H10*Cost_Library!$G$17*Parcel!$C$32*V10 -> 34320 | AV10: =G10*Cost_Library!$G$18*Parcel!$C$32*V10 -> 10920 | AW10: =Y10*Cost_Library!$G$19*Parcel!$C$32 -> 60000 | AX10: =Z10*Cost_Library!$G$20 -> 60000 | AY10: =AA10*Cost_Library!$G$21*Parcel!$C$32 -> 0 | AZ10: =AB10*Cost_Library!$G$22 -> 0 | BA10: =AC10*Cost_Library!$G$23*Parcel!$C$32*Parcel!$C$34 -> 316800 | BB10: =AD10*Cost_Library!$G$24*Parcel!$C$32 -> 0 | BC10: =W10*Cost_Library!$G$25*Parcel!$C$32 -> 30000 | BD10: =SUM(AH10:BC10) -> 951388 | BE10: =BD10*Assumptions!$C$11 -> 95138.8 | BF10: =BD10+BE10 -> 1046526.8 | BG10: =S10*Use_Library!$T$9 -> 2796000 | BH10: =BG10*(Assumptions!$C$12+Assumptions!$C$13) -> 363480 | BI10: =S10*Use_Library!$AC$9 -> 0 | BJ10: =1+Assumptions!$C$14+Assumptions!$C$15*Use_Library!$AH$9/12 -> 1.045 | BK10: =1+Assumptions!$C$21*(Assumptions!$C$22*Use_Library!$AH$9/12*Assumptions!$C$24+Assumptions!$C$23) -> 1.038675 | BL10: =1+Assumptions!$C$21*(Assumptions!$C$22*(Use_Library!$AH$9/12*Assumptions!$C$24+IF(Use_Library!$C$9="Income",Use_Library!$AD$9,0)/12*Assumptions!$C$25)+Assumptions!$C$23) -> 1.038675 | BM10: =J10*Assumptions!$C$31*(1-Assumptions!$C$17)*U10 -> 0 | BN10: =IF(Use_Library!$AJ$9=1,IF(Use_Library!$C$9="For-Sale",S10*Use_Library!$U$9,E10*Use_Library!$AF$9)*(1-Assumptions!$C$17)+BM10,0)*U10 -> 1267200 | BO10: =(BD10-AT10)*(1+Assumptions!$C$11) -> 1046526.8 | BP10: =BJ10*BK10 -> 1.0854154 | BQ10: =(Parcel!$C$18*BJ10+BO10)*BK10 -> 1412625.8 | BR10: =BN10-BQ10 -> -145425.84 | BS10: =IF(AND(Use_Library!$AJ$9=1,U10=1),MAX(0,((1-Use_Library!$AI$9)*BN10-BO10*BK10)/BP10),0) -> 0 | BT10: =BF10+BG10+BH10+BI10 -> 4206006.8 | BU10: =BJ10*BL10 -> 1.0854154 | BV10: =(Parcel!$C$18*BJ10+BT10)*BL10 -> 4694298.7 | BW10: =IF(Use_Library!$C$9="Income",S10*Use_Library!$W$9,0) -> 0 | BX10: =BW10*(1+Use_Library!$X$9)*(1-Use_Library!$Y$9) -> 0 | BY10: =IF(Use_Library!$C$9="Income",S10*Use_Library!$Z$9,0) -> 0 | BZ10: =IF(Use_Library!$C$9="Income",Assumptions!$C$19*Assumptions!$C$20*BV10,0) -> 0 | CA10: =BX10*Use_Library!$AA$9 -> 0 | CB10: =(BY10+BZ10)*Use_Library!$AB$9 -> 0 | CC10: =BX10-BY10-BZ10-CA10+CB10 -> 0 | CD10: =IF(AND(Use_Library!$C$9="Income",Use_Library!$AE$9>0),CC10/Use_Library!$AE$9,0) -> 0 | CE10: =IF(Use_Library!$C$9="Income",-Assumptions!$C$19*Assumptions!$C$20*(1-Use_Library!$AB$9)*BU10,0) -> 0 | CF10: =IF(BV10=0,0,CC10/BV10) -> 0 | CG10: =IF(Use_Library!$AK$9=1,IF(Use_Library!$C$9="Income",CD10*(1-Assumptions!$C$18),S10*Use_Library!$V$9*(1-Assumptions!$C$16))+BM10,0)*U10 -> 5527200 | CH10: =IF(AND(Use_Library!$AK$9=1,Use_Library!$C$9="Income",Use_Library!$AE$9>0),CE10/Use_Library!$AE$9*(1-Assumptions!$C$18),0) -> 0 | CI10: =CG10-BV10 -> 832901.27 | CJ10: =IF(AND(Use_Library!$AK$9=1,U10=1),MAX(0,Parcel!$C$18-((1-Use_Library!$AI$9)*CG10-BV10)/((1-Use_Library!$AI$9)*CH10-BU10)),0) -> 303520.56 | CK10: =IF(Use_Library!$AL$9=1,IF(Use_Library!$C$9="Income",CD10,IF(Use_Library!$AE$9>0,E10*Use_Library!$AG$9/Use_Library!$AE$9,0))+BM10,0)*U10 -> 0 | CL10: =IF(Use_Library!$C$9="Income",BT10,BF10) -> 1046526.8 | CM10: =IF(Use_Library!$C$9="Income",BU10,BJ10*BK10) -> 1.0854154 | CN10: =IF(Use_Library!$C$9="Income",BV10,(Parcel!$C$18*BJ10+BF10)*BK10) -> 1412625.8 | CO10: =IF(AND(Use_Library!$AL$9=1,Use_Library!$C$9="Income",Use_Library!$AE$9>0),CE10/Use_Library!$AE$9,0) -> 0 | CP10: =CK10-CN10 -> -1412625.8 | CQ10: =IF(AND(Use_Library!$AL$9=1,U10=1),MAX(0,Parcel!$C$18-((1-Use_Library!$AI$9)*CK10-CN10)/((1-Use_Library!$AI$9)*CO10-CM10)),0) -> 0 | CR10: =IF(Use_Library!$C$9="Income",Assumptions!$C$21*(Parcel!$C$18*BJ10+BT10),0) -> 0 | CS10: =IF(AND(Use_Library!$C$9="Income",CC10>0),MIN(Assumptions!$C$26*CD10,PV(Assumptions!$C$29/12,Assumptions!$C$30*12,-CC10/Assumptions!$C$27/12),CC10/Assumptions!$C$28),0) -> 0 | CT10: =IF(CS10=0,0,CC10/(-PMT(Assumptions!$C$29/12,Assumptions!$C$30*12,CS10)*12)) -> 0 | CU10: =CS10-CR10 -> 0 | CV10: =MAX(BS10,CJ10,CQ10) -> 303520.56 | CW10: =IF(CV10<=0,"None works",IF(BS10=CV10,"Land / pad sale",IF(CJ10=CV10,"Build & sell","Build & hold / lease"))) -> Build & sell | CX10: =CV10*(1-Assumptions!$C$32) -> 257992.48 | CY10: =CV10-Parcel!$C$18 -> 3520.5642 | CZ10: =IF(Parcel!$C$8=0,0,CV10/Parcel!$C$8) -> 15176.028 | DA10: =IF(S10=0,0,CV10/S10) -> 12646.69 | DB10: =TRIM(M10&" "&IF(AND(U10=0,N10=1),"Nothing fits. ","")&IF(Parcel!$C$12<Use_Library!$AM$9,"Frontage under "&Use_Library!$AM$9&" LF. ","")&IF(Parcel!$C$10>0.15,"Slope over 15%. ","")&IF(AND(U10=1,Use_Library!$M$9>0,D10>Use_Library!$M$9),"Only "&Use_Library!$M$9&" ac used - rest resold. ","")) | DC10: =CV10+ROW()/1000000 -> 303520.56
A11: =Use_Library!$A$10 -> Townhomes | B11: =Use_Library!$C$10 -> For-Sale | C11: =Use_Library!$D$10 -> unit | D11: =MAX(0,Parcel!$C$26*(1-Use_Library!$N$10-Assumptions!$C$7)) -> 14.196 | E11: =IF(Use_Library!$M$10>0,MIN(D11,Use_Library!$M$10),D11) -> 14.196 | F11: =IF(D11=0,0,E11/D11) -> 1 | G11: =Parcel!$C$26*F11 -> 15.6 | H11: =G11*Assumptions!$C$7 -> 0.624 | I11: =G11*(1-Use_Library!$N$10) -> 14.82 | J11: =Parcel!$C$8*(1-F11) -> 0 | K11: =IF(AND(Use_Library!$I$10="Y",Parcel!$C$28=0),0,1) -> 0 | L11: =IF(AND(Use_Library!$J$10="Y",Parcel!$C$27=0),0,1) -> 1 | M11: =TRIM(IF(AND(Use_Library!$AN$10>0,Parcel!$C$19<Use_Library!$AN$10),"Traffic under "&TEXT(Use_Library!$AN$10,"#,##0")&" VPD. ","")&IF(AND(Use_Library!$AO$10>0,Parcel!$C$20<Use_Library!$AO$10),"Under "&TEXT(Use_Library!$AO$10,"#,##0")&" households in 3 mi. ","")&IF(AND(Use_Library!$AP$10>0,Parcel!$C$21>Use_Library!$AP$10),"Over "&Use_Library!$AP$10&" mi to highway. ","")&IF(AND(Use_Library!$AQ$10="Y",Parcel!$C$22<>"Y"),"Needs a corner. ","")&IF(AND(Use_Library!$AR$10>0,Parcel!$C$23>Use_Library!$AR$10),"Over "&Use_Library!$AR$10&" mi to substation. ","")) | N11: =IF(M11="",1,0) -> 1 | O11: =IF(D11>=Use_Library!$L$10,1,0) -> 1 | P11: =IF(Use_Library!$F$10>0,G11*Use_Library!$F$10,1000000000) -> 156 | Q11: =IF(Use_Library!$G$10>0,E11*43560/Use_Library!$G$10,1000000000) -> 1000000000 | R11: =IF(AND(Use_Library!$H$10="Y",Parcel!$C$28=0),E11*(1-Assumptions!$C$8)/IF(Parcel!$C$27=1,Assumptions!$C$9,Assumptions!$C$10),1000000000) -> 1000000000 | S11: =IF(K11*L11*O11*N11=0,0,IF(MIN(P11,Q11,R11)>=1000000000,E11,IF(Use_Library!$E$10="Y",INT(MIN(P11,Q11,R11)),MIN(P11,Q11,R11)))) -> 0 | T11: =IF(N11=0,"Location fails",IF(O11=0,"Too small - needs "&Use_Library!$L$10&" usable ac",IF(K11=0,"Needs public sewer",IF(L11=0,"Needs public water",IF(R11<=MIN(P11,Q11),"Septic lot size",IF(Q11<=P11,"Site area / parking","Density")))))) -> Needs public sewer | U11: =IF(S11>0,1,0) -> 0 | V11: =IF(Use_Library!$K$10="Y",1,0)*U11 -> 0 | W11: =S11*Use_Library!$O$10*V11 -> 0 | X11: =S11*Use_Library!$P$10*V11 -> 0 | Y11: =IF(Parcel!$C$27=1,W11+Parcel!$C$29,0)*V11 -> 0 | Z11: =S11*Use_Library!$Q$10*Parcel!$C$27*V11 -> 0 | AA11: =IF(Parcel!$C$28=1,W11+Parcel!$C$30,0)*V11 -> 0 | AB11: =S11*Use_Library!$Q$10*Parcel!$C$28*V11 -> 0 | AC11: =IF(Parcel!$C$28=0,S11*Use_Library!$R$10,0)*V11 -> 0 | AD11: =IF(Parcel!$C$27=0,S11*Use_Library!$R$10,0)*V11 -> 0 | AE11: =I11*Parcel!$C$11*V11 -> 0 | AF11: =I11*V11 -> 0 | AG11: =IF(Use_Library!$C$10="For-Sale",IF(Use_Library!$E$10="Y",S11,1),1)*U11 -> 0 | AH11: =Cost_Library!$G$5*Parcel!$C$32*U11 -> 0 | AI11: =AG11*Cost_Library!$G$6*Parcel!$C$32 -> 0 | AJ11: =I11*Cost_Library!$G$7*Parcel!$C$32*V11 -> 0 | AK11: =Cost_Library!$G$8*Parcel!$C$32*V11 -> 0 | AL11: =AC11*Cost_Library!$G$9*Parcel!$C$32 -> 0 | AM11: =Cost_Library!$G$10*U11 -> 0 | AN11: =Cost_Library!$G$11*Parcel!$C$32*V11 -> 0 | AO11: =Use_Library!$S$10*U11 -> 0 | AP11: =Cost_Library!$G$12*U11 -> 0 | AQ11: =AE11*Cost_Library!$G$13*Parcel!$C$32 -> 0 | AR11: =AF11*Cost_Library!$G$14*Parcel!$C$32*Parcel!$C$33 -> 0 | AS11: =W11*Cost_Library!$G$15*Parcel!$C$32 -> 0 | AT11: =X11*Cost_Library!$G$16*Parcel!$C$32 -> 0 | AU11: =H11*Cost_Library!$G$17*Parcel!$C$32*V11 -> 0 | AV11: =G11*Cost_Library!$G$18*Parcel!$C$32*V11 -> 0 | AW11: =Y11*Cost_Library!$G$19*Parcel!$C$32 -> 0 | AX11: =Z11*Cost_Library!$G$20 -> 0 | AY11: =AA11*Cost_Library!$G$21*Parcel!$C$32 -> 0 | AZ11: =AB11*Cost_Library!$G$22 -> 0 | BA11: =AC11*Cost_Library!$G$23*Parcel!$C$32*Parcel!$C$34 -> 0 | BB11: =AD11*Cost_Library!$G$24*Parcel!$C$32 -> 0 | BC11: =W11*Cost_Library!$G$25*Parcel!$C$32 -> 0 | BD11: =SUM(AH11:BC11) -> 0 | BE11: =BD11*Assumptions!$C$11 -> 0 | BF11: =BD11+BE11 -> 0 | BG11: =S11*Use_Library!$T$10 -> 0 | BH11: =BG11*(Assumptions!$C$12+Assumptions!$C$13) -> 0 | BI11: =S11*Use_Library!$AC$10 -> 0 | BJ11: =1+Assumptions!$C$14+Assumptions!$C$15*Use_Library!$AH$10/12 -> 1.045 | BK11: =1+Assumptions!$C$21*(Assumptions!$C$22*Use_Library!$AH$10/12*Assumptions!$C$24+Assumptions!$C$23) -> 1.038675 | BL11: =1+Assumptions!$C$21*(Assumptions!$C$22*(Use_Library!$AH$10/12*Assumptions!$C$24+IF(Use_Library!$C$10="Income",Use_Library!$AD$10,0)/12*Assumptions!$C$25)+Assumptions!$C$23) -> 1.038675 | BM11: =J11*Assumptions!$C$31*(1-Assumptions!$C$17)*U11 -> 0 | BN11: =IF(Use_Library!$AJ$10=1,IF(Use_Library!$C$10="For-Sale",S11*Use_Library!$U$10,E11*Use_Library!$AF$10)*(1-Assumptions!$C$17)+BM11,0)*U11 -> 0 | BO11: =(BD11-AT11)*(1+Assumptions!$C$11) -> 0 | BP11: =BJ11*BK11 -> 1.0854154 | BQ11: =(Parcel!$C$18*BJ11+BO11)*BK11 -> 325624.61 | BR11: =BN11-BQ11 -> -325624.61 | BS11: =IF(AND(Use_Library!$AJ$10=1,U11=1),MAX(0,((1-Use_Library!$AI$10)*BN11-BO11*BK11)/BP11),0) -> 0 | BT11: =BF11+BG11+BH11+BI11 -> 0 | BU11: =BJ11*BL11 -> 1.0854154 | BV11: =(Parcel!$C$18*BJ11+BT11)*BL11 -> 325624.61 | BW11: =IF(Use_Library!$C$10="Income",S11*Use_Library!$W$10,0) -> 0 | BX11: =BW11*(1+Use_Library!$X$10)*(1-Use_Library!$Y$10) -> 0 | BY11: =IF(Use_Library!$C$10="Income",S11*Use_Library!$Z$10,0) -> 0 | BZ11: =IF(Use_Library!$C$10="Income",Assumptions!$C$19*Assumptions!$C$20*BV11,0) -> 0 | CA11: =BX11*Use_Library!$AA$10 -> 0 | CB11: =(BY11+BZ11)*Use_Library!$AB$10 -> 0 | CC11: =BX11-BY11-BZ11-CA11+CB11 -> 0 | CD11: =IF(AND(Use_Library!$C$10="Income",Use_Library!$AE$10>0),CC11/Use_Library!$AE$10,0) -> 0 | CE11: =IF(Use_Library!$C$10="Income",-Assumptions!$C$19*Assumptions!$C$20*(1-Use_Library!$AB$10)*BU11,0) -> 0 | CF11: =IF(BV11=0,0,CC11/BV11) -> 0 | CG11: =IF(Use_Library!$AK$10=1,IF(Use_Library!$C$10="Income",CD11*(1-Assumptions!$C$18),S11*Use_Library!$V$10*(1-Assumptions!$C$16))+BM11,0)*U11 -> 0 | CH11: =IF(AND(Use_Library!$AK$10=1,Use_Library!$C$10="Income",Use_Library!$AE$10>0),CE11/Use_Library!$AE$10*(1-Assumptions!$C$18),0) -> 0 | CI11: =CG11-BV11 -> -325624.61 | CJ11: =IF(AND(Use_Library!$AK$10=1,U11=1),MAX(0,Parcel!$C$18-((1-Use_Library!$AI$10)*CG11-BV11)/((1-Use_Library!$AI$10)*CH11-BU11)),0) -> 0 | CK11: =IF(Use_Library!$AL$10=1,IF(Use_Library!$C$10="Income",CD11,IF(Use_Library!$AE$10>0,E11*Use_Library!$AG$10/Use_Library!$AE$10,0))+BM11,0)*U11 -> 0 | CL11: =IF(Use_Library!$C$10="Income",BT11,BF11) -> 0 | CM11: =IF(Use_Library!$C$10="Income",BU11,BJ11*BK11) -> 1.0854154 | CN11: =IF(Use_Library!$C$10="Income",BV11,(Parcel!$C$18*BJ11+BF11)*BK11) -> 325624.61 | CO11: =IF(AND(Use_Library!$AL$10=1,Use_Library!$C$10="Income",Use_Library!$AE$10>0),CE11/Use_Library!$AE$10,0) -> 0 | CP11: =CK11-CN11 -> -325624.61 | CQ11: =IF(AND(Use_Library!$AL$10=1,U11=1),MAX(0,Parcel!$C$18-((1-Use_Library!$AI$10)*CK11-CN11)/((1-Use_Library!$AI$10)*CO11-CM11)),0) -> 0 | CR11: =IF(Use_Library!$C$10="Income",Assumptions!$C$21*(Parcel!$C$18*BJ11+BT11),0) -> 0 | CS11: =IF(AND(Use_Library!$C$10="Income",CC11>0),MIN(Assumptions!$C$26*CD11,PV(Assumptions!$C$29/12,Assumptions!$C$30*12,-CC11/Assumptions!$C$27/12),CC11/Assumptions!$C$28),0) -> 0 | CT11: =IF(CS11=0,0,CC11/(-PMT(Assumptions!$C$29/12,Assumptions!$C$30*12,CS11)*12)) -> 0 | CU11: =CS11-CR11 -> 0 | CV11: =MAX(BS11,CJ11,CQ11) -> 0 | CW11: =IF(CV11<=0,"None works",IF(BS11=CV11,"Land / pad sale",IF(CJ11=CV11,"Build & sell","Build & hold / lease"))) -> None works | CX11: =CV11*(1-Assumptions!$C$32) -> 0 | CY11: =CV11-Parcel!$C$18 -> -300000 | CZ11: =IF(Parcel!$C$8=0,0,CV11/Parcel!$C$8) -> 0 | DA11: =IF(S11=0,0,CV11/S11) -> 0 | DB11: =TRIM(M11&" "&IF(AND(U11=0,N11=1),"Nothing fits. ","")&IF(Parcel!$C$12<Use_Library!$AM$10,"Frontage under "&Use_Library!$AM$10&" LF. ","")&IF(Parcel!$C$10>0.15,"Slope over 15%. ","")&IF(AND(U11=1,Use_Library!$M$10>0,D11>Use_Library!$M$10),"Only "&Use_Library!$M$10&" ac used - rest resold. ","")) -> Nothing fits. | DC11: =CV11+ROW()/1000000 -> 1.1e-05
A12: =Use_Library!$A$11 -> Ranchette / acreage lots | B12: =Use_Library!$C$11 -> For-Sale | C12: =Use_Library!$D$11 -> lot | D12: =MAX(0,Parcel!$C$26*(1-Use_Library!$N$11-Assumptions!$C$7)) -> 14.196 | E12: =IF(Use_Library!$M$11>0,MIN(D12,Use_Library!$M$11),D12) -> 14.196 | F12: =IF(D12=0,0,E12/D12) -> 1 | G12: =Parcel!$C$26*F12 -> 15.6 | H12: =G12*Assumptions!$C$7 -> 0.624 | I12: =G12*(1-Use_Library!$N$11) -> 14.82 | J12: =Parcel!$C$8*(1-F12) -> 0 | K12: =IF(AND(Use_Library!$I$11="Y",Parcel!$C$28=0),0,1) -> 1 | L12: =IF(AND(Use_Library!$J$11="Y",Parcel!$C$27=0),0,1) -> 1 | M12: =TRIM(IF(AND(Use_Library!$AN$11>0,Parcel!$C$19<Use_Library!$AN$11),"Traffic under "&TEXT(Use_Library!$AN$11,"#,##0")&" VPD. ","")&IF(AND(Use_Library!$AO$11>0,Parcel!$C$20<Use_Library!$AO$11),"Under "&TEXT(Use_Library!$AO$11,"#,##0")&" households in 3 mi. ","")&IF(AND(Use_Library!$AP$11>0,Parcel!$C$21>Use_Library!$AP$11),"Over "&Use_Library!$AP$11&" mi to highway. ","")&IF(AND(Use_Library!$AQ$11="Y",Parcel!$C$22<>"Y"),"Needs a corner. ","")&IF(AND(Use_Library!$AR$11>0,Parcel!$C$23>Use_Library!$AR$11),"Over "&Use_Library!$AR$11&" mi to substation. ","")) | N12: =IF(M12="",1,0) -> 1 | O12: =IF(D12>=Use_Library!$L$11,1,0) -> 1 | P12: =IF(Use_Library!$F$11>0,G12*Use_Library!$F$11,1000000000) -> 3.12 | Q12: =IF(Use_Library!$G$11>0,E12*43560/Use_Library!$G$11,1000000000) -> 1000000000 | R12: =IF(AND(Use_Library!$H$11="Y",Parcel!$C$28=0),E12*(1-Assumptions!$C$8)/IF(Parcel!$C$27=1,Assumptions!$C$9,Assumptions!$C$10),1000000000) -> 24.1332 | S12: =IF(K12*L12*O12*N12=0,0,IF(MIN(P12,Q12,R12)>=1000000000,E12,IF(Use_Library!$E$11="Y",INT(MIN(P12,Q12,R12)),MIN(P12,Q12,R12)))) -> 3 | T12: =IF(N12=0,"Location fails",IF(O12=0,"Too small - needs "&Use_Library!$L$11&" usable ac",IF(K12=0,"Needs public sewer",IF(L12=0,"Needs public water",IF(R12<=MIN(P12,Q12),"Septic lot size",IF(Q12<=P12,"Site area / parking","Density")))))) -> Density | U12: =IF(S12>0,1,0) -> 1 | V12: =IF(Use_Library!$K$11="Y",1,0)*U12 -> 1 | W12: =S12*Use_Library!$O$11*V12 -> 450 | X12: =S12*Use_Library!$P$11*V12 -> 0 | Y12: =IF(Parcel!$C$27=1,W12+Parcel!$C$29,0)*V12 -> 450 | Z12: =S12*Use_Library!$Q$11*Parcel!$C$27*V12 -> 3 | AA12: =IF(Parcel!$C$28=1,W12+Parcel!$C$30,0)*V12 -> 0 | AB12: =S12*Use_Library!$Q$11*Parcel!$C$28*V12 -> 0 | AC12: =IF(Parcel!$C$28=0,S12*Use_Library!$R$11,0)*V12 -> 3 | AD12: =IF(Parcel!$C$27=0,S12*Use_Library!$R$11,0)*V12 -> 0 | AE12: =I12*Parcel!$C$11*V12 -> 5.187 | AF12: =I12*V12 -> 14.82 | AG12: =IF(Use_Library!$C$11="For-Sale",IF(Use_Library!$E$11="Y",S12,1),1)*U12 -> 3 | AH12: =Cost_Library!$G$5*Parcel!$C$32*U12 -> 6500 | AI12: =AG12*Cost_Library!$G$6*Parcel!$C$32 -> 2700 | AJ12: =I12*Cost_Library!$G$7*Parcel!$C$32*V12 -> 74100 | AK12: =Cost_Library!$G$8*Parcel!$C$32*V12 -> 5000 | AL12: =AC12*Cost_Library!$G$9*Parcel!$C$32 -> 1500 | AM12: =Cost_Library!$G$10*U12 -> 2800 | AN12: =Cost_Library!$G$11*Parcel!$C$32*V12 -> 7500 | AO12: =Use_Library!$S$11*U12 -> 10000 | AP12: =Cost_Library!$G$12*U12 -> 10000 | AQ12: =AE12*Cost_Library!$G$13*Parcel!$C$32 -> 20748 | AR12: =AF12*Cost_Library!$G$14*Parcel!$C$32*Parcel!$C$33 -> 74100 | AS12: =W12*Cost_Library!$G$15*Parcel!$C$32 -> 67500 | AT12: =X12*Cost_Library!$G$16*Parcel!$C$32 -> 0 | AU12: =H12*Cost_Library!$G$17*Parcel!$C$32*V12 -> 34320 | AV12: =G12*Cost_Library!$G$18*Parcel!$C$32*V12 -> 10920 | AW12: =Y12*Cost_Library!$G$19*Parcel!$C$32 -> 22500 | AX12: =Z12*Cost_Library!$G$20 -> 7500 | AY12: =AA12*Cost_Library!$G$21*Parcel!$C$32 -> 0 | AZ12: =AB12*Cost_Library!$G$22 -> 0 | BA12: =AC12*Cost_Library!$G$23*Parcel!$C$32*Parcel!$C$34 -> 39600 | BB12: =AD12*Cost_Library!$G$24*Parcel!$C$32 -> 0 | BC12: =W12*Cost_Library!$G$25*Parcel!$C$32 -> 11250 | BD12: =SUM(AH12:BC12) -> 408538 | BE12: =BD12*Assumptions!$C$11 -> 40853.8 | BF12: =BD12+BE12 -> 449391.8 | BG12: =S12*Use_Library!$T$11 -> 0 | BH12: =BG12*(Assumptions!$C$12+Assumptions!$C$13) -> 0 | BI12: =S12*Use_Library!$AC$11 -> 0 | BJ12: =1+Assumptions!$C$14+Assumptions!$C$15*Use_Library!$AH$11/12 -> 1.045 | BK12: =1+Assumptions!$C$21*(Assumptions!$C$22*Use_Library!$AH$11/12*Assumptions!$C$24+Assumptions!$C$23) -> 1.038675 | BL12: =1+Assumptions!$C$21*(Assumptions!$C$22*(Use_Library!$AH$11/12*Assumptions!$C$24+IF(Use_Library!$C$11="Income",Use_Library!$AD$11,0)/12*Assumptions!$C$25)+Assumptions!$C$23) -> 1.038675 | BM12: =J12*Assumptions!$C$31*(1-Assumptions!$C$17)*U12 -> 0 | BN12: =IF(Use_Library!$AJ$11=1,IF(Use_Library!$C$11="For-Sale",S12*Use_Library!$U$11,E12*Use_Library!$AF$11)*(1-Assumptions!$C$17)+BM12,0)*U12 -> 259200 | BO12: =(BD12-AT12)*(1+Assumptions!$C$11) -> 449391.8 | BP12: =BJ12*BK12 -> 1.0854154 | BQ12: =(Parcel!$C$18*BJ12+BO12)*BK12 -> 792396.64 | BR12: =BN12-BQ12 -> -533196.64 | BS12: =IF(AND(Use_Library!$AJ$11=1,U12=1),MAX(0,((1-Use_Library!$AI$11)*BN12-BO12*BK12)/BP12),0) -> 0 | BT12: =BF12+BG12+BH12+BI12 -> 449391.8 | BU12: =BJ12*BL12 -> 1.0854154 | BV12: =(Parcel!$C$18*BJ12+BT12)*BL12 -> 792396.64 | BW12: =IF(Use_Library!$C$11="Income",S12*Use_Library!$W$11,0) -> 0 | BX12: =BW12*(1+Use_Library!$X$11)*(1-Use_Library!$Y$11) -> 0 | BY12: =IF(Use_Library!$C$11="Income",S12*Use_Library!$Z$11,0) -> 0 | BZ12: =IF(Use_Library!$C$11="Income",Assumptions!$C$19*Assumptions!$C$20*BV12,0) -> 0 | CA12: =BX12*Use_Library!$AA$11 -> 0 | CB12: =(BY12+BZ12)*Use_Library!$AB$11 -> 0 | CC12: =BX12-BY12-BZ12-CA12+CB12 -> 0 | CD12: =IF(AND(Use_Library!$C$11="Income",Use_Library!$AE$11>0),CC12/Use_Library!$AE$11,0) -> 0 | CE12: =IF(Use_Library!$C$11="Income",-Assumptions!$C$19*Assumptions!$C$20*(1-Use_Library!$AB$11)*BU12,0) -> 0 | CF12: =IF(BV12=0,0,CC12/BV12) -> 0 | CG12: =IF(Use_Library!$AK$11=1,IF(Use_Library!$C$11="Income",CD12*(1-Assumptions!$C$18),S12*Use_Library!$V$11*(1-Assumptions!$C$16))+BM12,0)*U12 -> 0 | CH12: =IF(AND(Use_Library!$AK$11=1,Use_Library!$C$11="Income",Use_Library!$AE$11>0),CE12/Use_Library!$AE$11*(1-Assumptions!$C$18),0) -> 0 | CI12: =CG12-BV12 -> -792396.64 | CJ12: =IF(AND(Use_Library!$AK$11=1,U12=1),MAX(0,Parcel!$C$18-((1-Use_Library!$AI$11)*CG12-BV12)/((1-Use_Library!$AI$11)*CH12-BU12)),0) -> 0 | CK12: =IF(Use_Library!$AL$11=1,IF(Use_Library!$C$11="Income",CD12,IF(Use_Library!$AE$11>0,E12*Use_Library!$AG$11/Use_Library!$AE$11,0))+BM12,0)*U12 -> 0 | CL12: =IF(Use_Library!$C$11="Income",BT12,BF12) -> 449391.8 | CM12: =IF(Use_Library!$C$11="Income",BU12,BJ12*BK12) -> 1.0854154 | CN12: =IF(Use_Library!$C$11="Income",BV12,(Parcel!$C$18*BJ12+BF12)*BK12) -> 792396.64 | CO12: =IF(AND(Use_Library!$AL$11=1,Use_Library!$C$11="Income",Use_Library!$AE$11>0),CE12/Use_Library!$AE$11,0) -> 0 | CP12: =CK12-CN12 -> -792396.64 | CQ12: =IF(AND(Use_Library!$AL$11=1,U12=1),MAX(0,Parcel!$C$18-((1-Use_Library!$AI$11)*CK12-CN12)/((1-Use_Library!$AI$11)*CO12-CM12)),0) -> 0 | CR12: =IF(Use_Library!$C$11="Income",Assumptions!$C$21*(Parcel!$C$18*BJ12+BT12),0) -> 0 | CS12: =IF(AND(Use_Library!$C$11="Income",CC12>0),MIN(Assumptions!$C$26*CD12,PV(Assumptions!$C$29/12,Assumptions!$C$30*12,-CC12/Assumptions!$C$27/12),CC12/Assumptions!$C$28),0) -> 0 | CT12: =IF(CS12=0,0,CC12/(-PMT(Assumptions!$C$29/12,Assumptions!$C$30*12,CS12)*12)) -> 0 | CU12: =CS12-CR12 -> 0 | CV12: =MAX(BS12,CJ12,CQ12) -> 0 | CW12: =IF(CV12<=0,"None works",IF(BS12=CV12,"Land / pad sale",IF(CJ12=CV12,"Build & sell","Build & hold / lease"))) -> None works | CX12: =CV12*(1-Assumptions!$C$32) -> 0 | CY12: =CV12-Parcel!$C$18 -> -300000 | CZ12: =IF(Parcel!$C$8=0,0,CV12/Parcel!$C$8) -> 0 | DA12: =IF(S12=0,0,CV12/S12) -> 0 | DB12: =TRIM(M12&" "&IF(AND(U12=0,N12=1),"Nothing fits. ","")&IF(Parcel!$C$12<Use_Library!$AM$11,"Frontage under "&Use_Library!$AM$11&" LF. ","")&IF(Parcel!$C$10>0.15,"Slope over 15%. ","")&IF(AND(U12=1,Use_Library!$M$11>0,D12>Use_Library!$M$11),"Only "&Use_Library!$M$11&" ac used - rest resold. ","")) | DC12: =CV12+ROW()/1000000 -> 1.2e-05
A13: =Use_Library!$A$12 -> Garage / car condos | B13: =Use_Library!$C$12 -> For-Sale | C13: =Use_Library!$D$12 -> condo | D13: =MAX(0,Parcel!$C$26*(1-Use_Library!$N$12-Assumptions!$C$7)) -> 14.196 | E13: =IF(Use_Library!$M$12>0,MIN(D13,Use_Library!$M$12),D13) -> 14.196 | F13: =IF(D13=0,0,E13/D13) -> 1 | G13: =Parcel!$C$26*F13 -> 15.6 | H13: =G13*Assumptions!$C$7 -> 0.624 | I13: =G13*(1-Use_Library!$N$12) -> 14.82 | J13: =Parcel!$C$8*(1-F13) -> 0 | K13: =IF(AND(Use_Library!$I$12="Y",Parcel!$C$28=0),0,1) -> 1 | L13: =IF(AND(Use_Library!$J$12="Y",Parcel!$C$27=0),0,1) -> 1 | M13: =TRIM(IF(AND(Use_Library!$AN$12>0,Parcel!$C$19<Use_Library!$AN$12),"Traffic under "&TEXT(Use_Library!$AN$12,"#,##0")&" VPD. ","")&IF(AND(Use_Library!$AO$12>0,Parcel!$C$20<Use_Library!$AO$12),"Under "&TEXT(Use_Library!$AO$12,"#,##0")&" households in 3 mi. ","")&IF(AND(Use_Library!$AP$12>0,Parcel!$C$21>Use_Library!$AP$12),"Over "&Use_Library!$AP$12&" mi to highway. ","")&IF(AND(Use_Library!$AQ$12="Y",Parcel!$C$22<>"Y"),"Needs a corner. ","")&IF(AND(Use_Library!$AR$12>0,Parcel!$C$23>Use_Library!$AR$12),"Over "&Use_Library!$AR$12&" mi to substation. ","")) | N13: =IF(M13="",1,0) -> 1 | O13: =IF(D13>=Use_Library!$L$12,1,0) -> 1 | P13: =IF(Use_Library!$F$12>0,G13*Use_Library!$F$12,1000000000) -> 1000000000 | Q13: =IF(Use_Library!$G$12>0,E13*43560/Use_Library!$G$12,1000000000) -> 213.23371 | R13: =IF(AND(Use_Library!$H$12="Y",Parcel!$C$28=0),E13*(1-Assumptions!$C$8)/IF(Parcel!$C$27=1,Assumptions!$C$9,Assumptions!$C$10),1000000000) -> 1000000000 | S13: =IF(K13*L13*O13*N13=0,0,IF(MIN(P13,Q13,R13)>=1000000000,E13,IF(Use_Library!$E$12="Y",INT(MIN(P13,Q13,R13)),MIN(P13,Q13,R13)))) -> 213 | T13: =IF(N13=0,"Location fails",IF(O13=0,"Too small - needs "&Use_Library!$L$12&" usable ac",IF(K13=0,"Needs public sewer",IF(L13=0,"Needs public water",IF(R13<=MIN(P13,Q13),"Septic lot size",IF(Q13<=P13,"Site area / parking","Density")))))) -> Site area / parking | U13: =IF(S13>0,1,0) -> 1 | V13: =IF(Use_Library!$K$12="Y",1,0)*U13 -> 1 | W13: =S13*Use_Library!$O$12*V13 -> 1704 | X13: =S13*Use_Library!$P$12*V13 -> 191700 | Y13: =IF(Parcel!$C$27=1,W13+Parcel!$C$29,0)*V13 -> 1704 | Z13: =S13*Use_Library!$Q$12*Parcel!$C$27*V13 -> 21.3 | AA13: =IF(Parcel!$C$28=1,W13+Parcel!$C$30,0)*V13 -> 0 | AB13: =S13*Use_Library!$Q$12*Parcel!$C$28*V13 -> 0 | AC13: =IF(Parcel!$C$28=0,S13*Use_Library!$R$12,0)*V13 -> 21.3 | AD13: =IF(Parcel!$C$27=0,S13*Use_Library!$R$12,0)*V13 -> 0 | AE13: =I13*Parcel!$C$11*V13 -> 5.187 | AF13: =I13*V13 -> 14.82 | AG13: =IF(Use_Library!$C$12="For-Sale",IF(Use_Library!$E$12="Y",S13,1),1)*U13 -> 213 | AH13: =Cost_Library!$G$5*Parcel!$C$32*U13 -> 6500 | AI13: =AG13*Cost_Library!$G$6*Parcel!$C$32 -> 191700 | AJ13: =I13*Cost_Library!$G$7*Parcel!$C$32*V13 -> 74100 | AK13: =Cost_Library!$G$8*Parcel!$C$32*V13 -> 5000 | AL13: =AC13*Cost_Library!$G$9*Parcel!$C$32 -> 10650 | AM13: =Cost_Library!$G$10*U13 -> 2800 | AN13: =Cost_Library!$G$11*Parcel!$C$32*V13 -> 7500 | AO13: =Use_Library!$S$12*U13 -> 25000 | AP13: =Cost_Library!$G$12*U13 -> 10000 | AQ13: =AE13*Cost_Library!$G$13*Parcel!$C$32 -> 20748 | AR13: =AF13*Cost_Library!$G$14*Parcel!$C$32*Parcel!$C$33 -> 74100 | AS13: =W13*Cost_Library!$G$15*Parcel!$C$32 -> 255600 | AT13: =X13*Cost_Library!$G$16*Parcel!$C$32 -> 1150200 | AU13: =H13*Cost_Library!$G$17*Parcel!$C$32*V13 -> 34320 | AV13: =G13*Cost_Library!$G$18*Parcel!$C$32*V13 -> 10920 | AW13: =Y13*Cost_Library!$G$19*Parcel!$C$32 -> 85200 | AX13: =Z13*Cost_Library!$G$20 -> 53250 | AY13: =AA13*Cost_Library!$G$21*Parcel!$C$32 -> 0 | AZ13: =AB13*Cost_Library!$G$22 -> 0 | BA13: =AC13*Cost_Library!$G$23*Parcel!$C$32*Parcel!$C$34 -> 281160 | BB13: =AD13*Cost_Library!$G$24*Parcel!$C$32 -> 0 | BC13: =W13*Cost_Library!$G$25*Parcel!$C$32 -> 42600 | BD13: =SUM(AH13:BC13) -> 2341348 | BE13: =BD13*Assumptions!$C$11 -> 234134.8 | BF13: =BD13+BE13 -> 2575482.8 | BG13: =S13*Use_Library!$T$12 -> 18105000 | BH13: =BG13*(Assumptions!$C$12+Assumptions!$C$13) -> 2353650 | BI13: =S13*Use_Library!$AC$12 -> 0 | BJ13: =1+Assumptions!$C$14+Assumptions!$C$15*Use_Library!$AH$12/12 -> 1.045 | BK13: =1+Assumptions!$C$21*(Assumptions!$C$22*Use_Library!$AH$12/12*Assumptions!$C$24+Assumptions!$C$23) -> 1.038675 | BL13: =1+Assumptions!$C$21*(Assumptions!$C$22*(Use_Library!$AH$12/12*Assumptions!$C$24+IF(Use_Library!$C$12="Income",Use_Library!$AD$12,0)/12*Assumptions!$C$25)+Assumptions!$C$23) -> 1.038675 | BM13: =J13*Assumptions!$C$31*(1-Assumptions!$C$17)*U13 -> 0 | BN13: =IF(Use_Library!$AJ$12=1,IF(Use_Library!$C$12="For-Sale",S13*Use_Library!$U$12,E13*Use_Library!$AF$12)*(1-Assumptions!$C$17)+BM13,0)*U13 -> 0 | BO13: =(BD13-AT13)*(1+Assumptions!$C$11) -> 1310262.8 | BP13: =BJ13*BK13 -> 1.0854154 | BQ13: =(Parcel!$C$18*BJ13+BO13)*BK13 -> 1686561.8 | BR13: =BN13-BQ13 -> -1686561.8 | BS13: =IF(AND(Use_Library!$AJ$12=1,U13=1),MAX(0,((1-Use_Library!$AI$12)*BN13-BO13*BK13)/BP13),0) -> 0 | BT13: =BF13+BG13+BH13+BI13 -> 23034133 | BU13: =BJ13*BL13 -> 1.0854154 | BV13: =(Parcel!$C$18*BJ13+BT13)*BL13 -> 24250602 | BW13: =IF(Use_Library!$C$12="Income",S13*Use_Library!$W$12,0) -> 0 | BX13: =BW13*(1+Use_Library!$X$12)*(1-Use_Library!$Y$12) -> 0 | BY13: =IF(Use_Library!$C$12="Income",S13*Use_Library!$Z$12,0) -> 0 | BZ13: =IF(Use_Library!$C$12="Income",Assumptions!$C$19*Assumptions!$C$20*BV13,0) -> 0 | CA13: =BX13*Use_Library!$AA$12 -> 0 | CB13: =(BY13+BZ13)*Use_Library!$AB$12 -> 0 | CC13: =BX13-BY13-BZ13-CA13+CB13 -> 0 | CD13: =IF(AND(Use_Library!$C$12="Income",Use_Library!$AE$12>0),CC13/Use_Library!$AE$12,0) -> 0 | CE13: =IF(Use_Library!$C$12="Income",-Assumptions!$C$19*Assumptions!$C$20*(1-Use_Library!$AB$12)*BU13,0) -> 0 | CF13: =IF(BV13=0,0,CC13/BV13) -> 0 | CG13: =IF(Use_Library!$AK$12=1,IF(Use_Library!$C$12="Income",CD13*(1-Assumptions!$C$18),S13*Use_Library!$V$12*(1-Assumptions!$C$16))+BM13,0)*U13 -> 27029700 | CH13: =IF(AND(Use_Library!$AK$12=1,Use_Library!$C$12="Income",Use_Library!$AE$12>0),CE13/Use_Library!$AE$12*(1-Assumptions!$C$18),0) -> 0 | CI13: =CG13-BV13 -> 2779097.5 | CJ13: =IF(AND(Use_Library!$AK$12=1,U13=1),MAX(0,Parcel!$C$18-((1-Use_Library!$AI$12)*CG13-BV13)/((1-Use_Library!$AI$12)*CH13-BU13)),0) -> 0 | CK13: =IF(Use_Library!$AL$12=1,IF(Use_Library!$C$12="Income",CD13,IF(Use_Library!$AE$12>0,E13*Use_Library!$AG$12/Use_Library!$AE$12,0))+BM13,0)*U13 -> 0 | CL13: =IF(Use_Library!$C$12="Income",BT13,BF13) -> 2575482.8 | CM13: =IF(Use_Library!$C$12="Income",BU13,BJ13*BK13) -> 1.0854154 | CN13: =IF(Use_Library!$C$12="Income",BV13,(Parcel!$C$18*BJ13+BF13)*BK13) -> 3000714.2 | CO13: =IF(AND(Use_Library!$AL$12=1,Use_Library!$C$12="Income",Use_Library!$AE$12>0),CE13/Use_Library!$AE$12,0) -> 0 | CP13: =CK13-CN13 -> -3000714.2 | CQ13: =IF(AND(Use_Library!$AL$12=1,U13=1),MAX(0,Parcel!$C$18-((1-Use_Library!$AI$12)*CK13-CN13)/((1-Use_Library!$AI$12)*CO13-CM13)),0) -> 0 | CR13: =IF(Use_Library!$C$12="Income",Assumptions!$C$21*(Parcel!$C$18*BJ13+BT13),0) -> 0 | CS13: =IF(AND(Use_Library!$C$12="Income",CC13>0),MIN(Assumptions!$C$26*CD13,PV(Assumptions!$C$29/12,Assumptions!$C$30*12,-CC13/Assumptions!$C$27/12),CC13/Assumptions!$C$28),0) -> 0 | CT13: =IF(CS13=0,0,CC13/(-PMT(Assumptions!$C$29/12,Assumptions!$C$30*12,CS13)*12)) -> 0 | CU13: =CS13-CR13 -> 0 | CV13: =MAX(BS13,CJ13,CQ13) -> 0 | CW13: =IF(CV13<=0,"None works",IF(BS13=CV13,"Land / pad sale",IF(CJ13=CV13,"Build & sell","Build & hold / lease"))) -> None works | CX13: =CV13*(1-Assumptions!$C$32) -> 0 | CY13: =CV13-Parcel!$C$18 -> -300000 | CZ13: =IF(Parcel!$C$8=0,0,CV13/Parcel!$C$8) -> 0 | DA13: =IF(S13=0,0,CV13/S13) -> 0 | DB13: =TRIM(M13&" "&IF(AND(U13=0,N13=1),"Nothing fits. ","")&IF(Parcel!$C$12<Use_Library!$AM$12,"Frontage under "&Use_Library!$AM$12&" LF. ","")&IF(Parcel!$C$10>0.15,"Slope over 15%. ","")&IF(AND(U13=1,Use_Library!$M$12>0,D13>Use_Library!$M$12),"Only "&Use_Library!$M$12&" ac used - rest resold. ","")) | DC13: =CV13+ROW()/1000000 -> 1.3e-05
A14: =Use_Library!$A$13 -> Contractor shop condos | B14: =Use_Library!$C$13 -> For-Sale | C14: =Use_Library!$D$13 -> condo (2,000 SF) | D14: =MAX(0,Parcel!$C$26*(1-Use_Library!$N$13-Assumptions!$C$7)) -> 14.196 | E14: =IF(Use_Library!$M$13>0,MIN(D14,Use_Library!$M$13),D14) -> 6 | F14: =IF(D14=0,0,E14/D14) -> 0.42265427 | G14: =Parcel!$C$26*F14 -> 6.5934066 | H14: =G14*Assumptions!$C$7 -> 0.26373626 | I14: =G14*(1-Use_Library!$N$13) -> 6.2637363 | J14: =Parcel!$C$8*(1-F14) -> 11.546915 | K14: =IF(AND(Use_Library!$I$13="Y",Parcel!$C$28=0),0,1) -> 1 | L14: =IF(AND(Use_Library!$J$13="Y",Parcel!$C$27=0),0,1) -> 1 | M14: =TRIM(IF(AND(Use_Library!$AN$13>0,Parcel!$C$19<Use_Library!$AN$13),"Traffic under "&TEXT(Use_Library!$AN$13,"#,##0")&" VPD. ","")&IF(AND(Use_Library!$AO$13>0,Parcel!$C$20<Use_Library!$AO$13),"Under "&TEXT(Use_Library!$AO$13,"#,##0")&" households in 3 mi. ","")&IF(AND(Use_Library!$AP$13>0,Parcel!$C$21>Use_Library!$AP$13),"Over "&Use_Library!$AP$13&" mi to highway. ","")&IF(AND(Use_Library!$AQ$13="Y",Parcel!$C$22<>"Y"),"Needs a corner. ","")&IF(AND(Use_Library!$AR$13>0,Parcel!$C$23>Use_Library!$AR$13),"Over "&Use_Library!$AR$13&" mi to substation. ","")) | N14: =IF(M14="",1,0) -> 1 | O14: =IF(D14>=Use_Library!$L$13,1,0) -> 1 | P14: =IF(Use_Library!$F$13>0,G14*Use_Library!$F$13,1000000000) -> 1000000000 | Q14: =IF(Use_Library!$G$13>0,E14*43560/Use_Library!$G$13,1000000000) -> 45.852632 | R14: =IF(AND(Use_Library!$H$13="Y",Parcel!$C$28=0),E14*(1-Assumptions!$C$8)/IF(Parcel!$C$27=1,Assumptions!$C$9,Assumptions!$C$10),1000000000) -> 1000000000 | S14: =IF(K14*L14*O14*N14=0,0,IF(MIN(P14,Q14,R14)>=1000000000,E14,IF(Use_Library!$E$13="Y",INT(MIN(P14,Q14,R14)),MIN(P14,Q14,R14)))) -> 45 | T14: =IF(N14=0,"Location fails",IF(O14=0,"Too small - needs "&Use_Library!$L$13&" usable ac",IF(K14=0,"Needs public sewer",IF(L14=0,"Needs public water",IF(R14<=MIN(P14,Q14),"Septic lot size",IF(Q14<=P14,"Site area / parking","Density")))))) -> Site area / parking | U14: =IF(S14>0,1,0) -> 1 | V14: =IF(Use_Library!$K$13="Y",1,0)*U14 -> 1 | W14: =S14*Use_Library!$O$13*V14 -> 450 | X14: =S14*Use_Library!$P$13*V14 -> 112500 | Y14: =IF(Parcel!$C$27=1,W14+Parcel!$C$29,0)*V14 -> 450 | Z14: =S14*Use_Library!$Q$13*Parcel!$C$27*V14 -> 9 | AA14: =IF(Parcel!$C$28=1,W14+Parcel!$C$30,0)*V14 -> 0 | AB14: =S14*Use_Library!$Q$13*Parcel!$C$28*V14 -> 0 | AC14: =IF(Parcel!$C$28=0,S14*Use_Library!$R$13,0)*V14 -> 9 | AD14: =IF(Parcel!$C$27=0,S14*Use_Library!$R$13,0)*V14 -> 0 | AE14: =I14*Parcel!$C$11*V14 -> 2.1923077 | AF14: =I14*V14 -> 6.2637363 | AG14: =IF(Use_Library!$C$13="For-Sale",IF(Use_Library!$E$13="Y",S14,1),1)*U14 -> 45 | AH14: =Cost_Library!$G$5*Parcel!$C$32*U14 -> 6500 | AI14: =AG14*Cost_Library!$G$6*Parcel!$C$32 -> 40500 | AJ14: =I14*Cost_Library!$G$7*Parcel!$C$32*V14 -> 31318.681 | AK14: =Cost_Library!$G$8*Parcel!$C$32*V14 -> 5000 | AL14: =AC14*Cost_Library!$G$9*Parcel!$C$32 -> 4500 | AM14: =Cost_Library!$G$10*U14 -> 2800 | AN14: =Cost_Library!$G$11*Parcel!$C$32*V14 -> 7500 | AO14: =Use_Library!$S$13*U14 -> 25000 | AP14: =Cost_Library!$G$12*U14 -> 10000 | AQ14: =AE14*Cost_Library!$G$13*Parcel!$C$32 -> 8769.2308 | AR14: =AF14*Cost_Library!$G$14*Parcel!$C$32*Parcel!$C$33 -> 31318.681 | AS14: =W14*Cost_Library!$G$15*Parcel!$C$32 -> 67500 | AT14: =X14*Cost_Library!$G$16*Parcel!$C$32 -> 675000 | AU14: =H14*Cost_Library!$G$17*Parcel!$C$32*V14 -> 14505.495 | AV14: =G14*Cost_Library!$G$18*Parcel!$C$32*V14 -> 4615.3846 | AW14: =Y14*Cost_Library!$G$19*Parcel!$C$32 -> 22500 | AX14: =Z14*Cost_Library!$G$20 -> 22500 | AY14: =AA14*Cost_Library!$G$21*Parcel!$C$32 -> 0 | AZ14: =AB14*Cost_Library!$G$22 -> 0 | BA14: =AC14*Cost_Library!$G$23*Parcel!$C$32*Parcel!$C$34 -> 118800 | BB14: =AD14*Cost_Library!$G$24*Parcel!$C$32 -> 0 | BC14: =W14*Cost_Library!$G$25*Parcel!$C$32 -> 11250 | BD14: =SUM(AH14:BC14) -> 1109877.5 | BE14: =BD14*Assumptions!$C$11 -> 110987.75 | BF14: =BD14+BE14 -> 1220865.2 | BG14: =S14*Use_Library!$T$13 -> 8550000 | BH14: =BG14*(Assumptions!$C$12+Assumptions!$C$13) -> 1111500 | BI14: =S14*Use_Library!$AC$13 -> 0 | BJ14: =1+Assumptions!$C$14+Assumptions!$C$15*Use_Library!$AH$13/12 -> 1.045 | BK14: =1+Assumptions!$C$21*(Assumptions!$C$22*Use_Library!$AH$13/12*Assumptions!$C$24+Assumptions!$C$23) -> 1.038675 | BL14: =1+Assumptions!$C$21*(Assumptions!$C$22*(Use_Library!$AH$13/12*Assumptions!$C$24+IF(Use_Library!$C$13="Income",Use_Library!$AD$13,0)/12*Assumptions!$C$25)+Assumptions!$C$23) -> 1.038675 | BM14: =J14*Assumptions!$C$31*(1-Assumptions!$C$17)*U14 -> 133020.46 | BN14: =IF(Use_Library!$AJ$13=1,IF(Use_Library!$C$13="For-Sale",S14*Use_Library!$U$13,E14*Use_Library!$AF$13)*(1-Assumptions!$C$17)+BM14,0)*U14 -> 0 | BO14: =(BD14-AT14)*(1+Assumptions!$C$11) -> 478365.22 | BP14: =BJ14*BK14 -> 1.0854154 | BQ14: =(Parcel!$C$18*BJ14+BO14)*BK14 -> 822490.61 | BR14: =BN14-BQ14 -> -822490.61 | BS14: =IF(AND(Use_Library!$AJ$13=1,U14=1),MAX(0,((1-Use_Library!$AI$13)*BN14-BO14*BK14)/BP14),0) -> 0 | BT14: =BF14+BG14+BH14+BI14 -> 10882365 | BU14: =BJ14*BL14 -> 1.0854154 | BV14: =(Parcel!$C$18*BJ14+BT14)*BL14 -> 11628865 | BW14: =IF(Use_Library!$C$13="Income",S14*Use_Library!$W$13,0) -> 0 | BX14: =BW14*(1+Use_Library!$X$13)*(1-Use_Library!$Y$13) -> 0 | BY14: =IF(Use_Library!$C$13="Income",S14*Use_Library!$Z$13,0) -> 0 | BZ14: =IF(Use_Library!$C$13="Income",Assumptions!$C$19*Assumptions!$C$20*BV14,0) -> 0 | CA14: =BX14*Use_Library!$AA$13 -> 0 | CB14: =(BY14+BZ14)*Use_Library!$AB$13 -> 0 | CC14: =BX14-BY14-BZ14-CA14+CB14 -> 0 | CD14: =IF(AND(Use_Library!$C$13="Income",Use_Library!$AE$13>0),CC14/Use_Library!$AE$13,0) -> 0 | CE14: =IF(Use_Library!$C$13="Income",-Assumptions!$C$19*Assumptions!$C$20*(1-Use_Library!$AB$13)*BU14,0) -> 0 | CF14: =IF(BV14=0,0,CC14/BV14) -> 0 | CG14: =IF(Use_Library!$AK$13=1,IF(Use_Library!$C$13="Income",CD14*(1-Assumptions!$C$18),S14*Use_Library!$V$13*(1-Assumptions!$C$16))+BM14,0)*U14 -> 11977020 | CH14: =IF(AND(Use_Library!$AK$13=1,Use_Library!$C$13="Income",Use_Library!$AE$13>0),CE14/Use_Library!$AE$13*(1-Assumptions!$C$18),0) -> 0 | CI14: =CG14-BV14 -> 348155.15 | CJ14: =IF(AND(Use_Library!$AK$13=1,U14=1),MAX(0,Parcel!$C$18-((1-Use_Library!$AI$13)*CG14-BV14)/((1-Use_Library!$AI$13)*CH14-BU14)),0) -> 0 | CK14: =IF(Use_Library!$AL$13=1,IF(Use_Library!$C$13="Income",CD14,IF(Use_Library!$AE$13>0,E14*Use_Library!$AG$13/Use_Library!$AE$13,0))+BM14,0)*U14 -> 0 | CL14: =IF(Use_Library!$C$13="Income",BT14,BF14) -> 1220865.2 | CM14: =IF(Use_Library!$C$13="Income",BU14,BJ14*BK14) -> 1.0854154 | CN14: =IF(Use_Library!$C$13="Income",BV14,(Parcel!$C$18*BJ14+BF14)*BK14) -> 1593706.8 | CO14: =IF(AND(Use_Library!$AL$13=1,Use_Library!$C$13="Income",Use_Library!$AE$13>0),CE14/Use_Library!$AE$13,0) -> 0 | CP14: =CK14-CN14 -> -1593706.8 | CQ14: =IF(AND(Use_Library!$AL$13=1,U14=1),MAX(0,Parcel!$C$18-((1-Use_Library!$AI$13)*CK14-CN14)/((1-Use_Library!$AI$13)*CO14-CM14)),0) -> 0 | CR14: =IF(Use_Library!$C$13="Income",Assumptions!$C$21*(Parcel!$C$18*BJ14+BT14),0) -> 0 | CS14: =IF(AND(Use_Library!$C$13="Income",CC14>0),MIN(Assumptions!$C$26*CD14,PV(Assumptions!$C$29/12,Assumptions!$C$30*12,-CC14/Assumptions!$C$27/12),CC14/Assumptions!$C$28),0) -> 0 | CT14: =IF(CS14=0,0,CC14/(-PMT(Assumptions!$C$29/12,Assumptions!$C$30*12,CS14)*12)) -> 0 | CU14: =CS14-CR14 -> 0 | CV14: =MAX(BS14,CJ14,CQ14) -> 0 | CW14: =IF(CV14<=0,"None works",IF(BS14=CV14,"Land / pad sale",IF(CJ14=CV14,"Build & sell","Build & hold / lease"))) -> None works | CX14: =CV14*(1-Assumptions!$C$32) -> 0 | CY14: =CV14-Parcel!$C$18 -> -300000 | CZ14: =IF(Parcel!$C$8=0,0,CV14/Parcel!$C$8) -> 0 | DA14: =IF(S14=0,0,CV14/S14) -> 0 | DB14: =TRIM(M14&" "&IF(AND(U14=0,N14=1),"Nothing fits. ","")&IF(Parcel!$C$12<Use_Library!$AM$13,"Frontage under "&Use_Library!$AM$13&" LF. ","")&IF(Parcel!$C$10>0.15,"Slope over 15%. ","")&IF(AND(U14=1,Use_Library!$M$13>0,D14>Use_Library!$M$13),"Only "&Use_Library!$M$13&" ac used - rest resold. ","")) -> Only 6 ac used - rest resold. | DC14: =CV14+ROW()/1000000 -> 1.4e-05
A15: =Use_Library!$A$14 -> Professional office condos | B15: =Use_Library!$C$14 -> For-Sale | C15: =Use_Library!$D$14 -> condo (1,500 SF) | D15: =MAX(0,Parcel!$C$26*(1-Use_Library!$N$14-Assumptions!$C$7)) -> 14.196 | E15: =IF(Use_Library!$M$14>0,MIN(D15,Use_Library!$M$14),D15) -> 4 | F15: =IF(D15=0,0,E15/D15) -> 0.28176951 | G15: =Parcel!$C$26*F15 -> 4.3956044 | H15: =G15*Assumptions!$C$7 -> 0.17582418 | I15: =G15*(1-Use_Library!$N$14) -> 4.1758242 | J15: =Parcel!$C$8*(1-F15) -> 14.36461 | K15: =IF(AND(Use_Library!$I$14="Y",Parcel!$C$28=0),0,1) -> 1 | L15: =IF(AND(Use_Library!$J$14="Y",Parcel!$C$27=0),0,1) -> 1 | M15: =TRIM(IF(AND(Use_Library!$AN$14>0,Parcel!$C$19<Use_Library!$AN$14),"Traffic under "&TEXT(Use_Library!$AN$14,"#,##0")&" VPD. ","")&IF(AND(Use_Library!$AO$14>0,Parcel!$C$20<Use_Library!$AO$14),"Under "&TEXT(Use_Library!$AO$14,"#,##0")&" households in 3 mi. ","")&IF(AND(Use_Library!$AP$14>0,Parcel!$C$21>Use_Library!$AP$14),"Over "&Use_Library!$AP$14&" mi to highway. ","")&IF(AND(Use_Library!$AQ$14="Y",Parcel!$C$22<>"Y"),"Needs a corner. ","")&IF(AND(Use_Library!$AR$14>0,Parcel!$C$23>Use_Library!$AR$14),"Over "&Use_Library!$AR$14&" mi to substation. ","")) | N15: =IF(M15="",1,0) -> 1 | O15: =IF(D15>=Use_Library!$L$14,1,0) -> 1 | P15: =IF(Use_Library!$F$14>0,G15*Use_Library!$F$14,1000000000) -> 1000000000 | Q15: =IF(Use_Library!$G$14>0,E15*43560/Use_Library!$G$14,1000000000) -> 29.04 | R15: =IF(AND(Use_Library!$H$14="Y",Parcel!$C$28=0),E15*(1-Assumptions!$C$8)/IF(Parcel!$C$27=1,Assumptions!$C$9,Assumptions!$C$10),1000000000) -> 1000000000 | S15: =IF(K15*L15*O15*N15=0,0,IF(MIN(P15,Q15,R15)>=1000000000,E15,IF(Use_Library!$E$14="Y",INT(MIN(P15,Q15,R15)),MIN(P15,Q15,R15)))) -> 29 | T15: =IF(N15=0,"Location fails",IF(O15=0,"Too small - needs "&Use_Library!$L$14&" usable ac",IF(K15=0,"Needs public sewer",IF(L15=0,"Needs public water",IF(R15<=MIN(P15,Q15),"Septic lot size",IF(Q15<=P15,"Site area / parking","Density")))))) -> Site area / parking | U15: =IF(S15>0,1,0) -> 1 | V15: =IF(Use_Library!$K$14="Y",1,0)*U15 -> 1 | W15: =S15*Use_Library!$O$14*V15 -> 232 | X15: =S15*Use_Library!$P$14*V15 -> 87000 | Y15: =IF(Parcel!$C$27=1,W15+Parcel!$C$29,0)*V15 -> 232 | Z15: =S15*Use_Library!$Q$14*Parcel!$C$27*V15 -> 7.25 | AA15: =IF(Parcel!$C$28=1,W15+Parcel!$C$30,0)*V15 -> 0 | AB15: =S15*Use_Library!$Q$14*Parcel!$C$28*V15 -> 0 | AC15: =IF(Parcel!$C$28=0,S15*Use_Library!$R$14,0)*V15 -> 7.25 | AD15: =IF(Parcel!$C$27=0,S15*Use_Library!$R$14,0)*V15 -> 0 | AE15: =I15*Parcel!$C$11*V15 -> 1.4615385 | AF15: =I15*V15 -> 4.1758242 | AG15: =IF(Use_Library!$C$14="For-Sale",IF(Use_Library!$E$14="Y",S15,1),1)*U15 -> 29 | AH15: =Cost_Library!$G$5*Parcel!$C$32*U15 -> 6500 | AI15: =AG15*Cost_Library!$G$6*Parcel!$C$32 -> 26100 | AJ15: =I15*Cost_Library!$G$7*Parcel!$C$32*V15 -> 20879.121 | AK15: =Cost_Library!$G$8*Parcel!$C$32*V15 -> 5000 | AL15: =AC15*Cost_Library!$G$9*Parcel!$C$32 -> 3625 | AM15: =Cost_Library!$G$10*U15 -> 2800 | AN15: =Cost_Library!$G$11*Parcel!$C$32*V15 -> 7500 | AO15: =Use_Library!$S$14*U15 -> 25000 | AP15: =Cost_Library!$G$12*U15 -> 10000 | AQ15: =AE15*Cost_Library!$G$13*Parcel!$C$32 -> 5846.1538 | AR15: =AF15*Cost_Library!$G$14*Parcel!$C$32*Parcel!$C$33 -> 20879.121 | AS15: =W15*Cost_Library!$G$15*Parcel!$C$32 -> 34800 | AT15: =X15*Cost_Library!$G$16*Parcel!$C$32 -> 522000 | AU15: =H15*Cost_Library!$G$17*Parcel!$C$32*V15 -> 9670.3297 | AV15: =G15*Cost_Library!$G$18*Parcel!$C$32*V15 -> 3076.9231 | AW15: =Y15*Cost_Library!$G$19*Parcel!$C$32 -> 11600 | AX15: =Z15*Cost_Library!$G$20 -> 18125 | AY15: =AA15*Cost_Library!$G$21*Parcel!$C$32 -> 0 | AZ15: =AB15*Cost_Library!$G$22 -> 0 | BA15: =AC15*Cost_Library!$G$23*Parcel!$C$32*Parcel!$C$34 -> 95700 | BB15: =AD15*Cost_Library!$G$24*Parcel!$C$32 -> 0 | BC15: =W15*Cost_Library!$G$25*Parcel!$C$32 -> 5800 | BD15: =SUM(AH15:BC15) -> 834901.65 | BE15: =BD15*Assumptions!$C$11 -> 83490.165 | BF15: =BD15+BE15 -> 918391.81 | BG15: =S15*Use_Library!$T$14 -> 8700000 | BH15: =BG15*(Assumptions!$C$12+Assumptions!$C$13) -> 1131000 | BI15: =S15*Use_Library!$AC$14 -> 0 | BJ15: =1+Assumptions!$C$14+Assumptions!$C$15*Use_Library!$AH$14/12 -> 1.045 | BK15: =1+Assumptions!$C$21*(Assumptions!$C$22*Use_Library!$AH$14/12*Assumptions!$C$24+Assumptions!$C$23) -> 1.038675 | BL15: =1+Assumptions!$C$21*(Assumptions!$C$22*(Use_Library!$AH$14/12*Assumptions!$C$24+IF(Use_Library!$C$14="Income",Use_Library!$AD$14,0)/12*Assumptions!$C$25)+Assumptions!$C$23) -> 1.038675 | BM15: =J15*Assumptions!$C$31*(1-Assumptions!$C$17)*U15 -> 165480.3 | BN15: =IF(Use_Library!$AJ$14=1,IF(Use_Library!$C$14="For-Sale",S15*Use_Library!$U$14,E15*Use_Library!$AF$14)*(1-Assumptions!$C$17)+BM15,0)*U15 -> 0 | BO15: =(BD15-AT15)*(1+Assumptions!$C$11) -> 344191.81 | BP15: =BJ15*BK15 -> 1.0854154 | BQ15: =(Parcel!$C$18*BJ15+BO15)*BK15 -> 683128.04 | BR15: =BN15-BQ15 -> -683128.04 | BS15: =IF(AND(Use_Library!$AJ$14=1,U15=1),MAX(0,((1-Use_Library!$AI$14)*BN15-BO15*BK15)/BP15),0) -> 0 | BT15: =BF15+BG15+BH15+BI15 -> 10749392 | BU15: =BJ15*BL15 -> 1.0854154 | BV15: =(Parcel!$C$18*BJ15+BT15)*BL15 -> 11490749 | BW15: =IF(Use_Library!$C$14="Income",S15*Use_Library!$W$14,0) -> 0 | BX15: =BW15*(1+Use_Library!$X$14)*(1-Use_Library!$Y$14) -> 0 | BY15: =IF(Use_Library!$C$14="Income",S15*Use_Library!$Z$14,0) -> 0 | BZ15: =IF(Use_Library!$C$14="Income",Assumptions!$C$19*Assumptions!$C$20*BV15,0) -> 0 | CA15: =BX15*Use_Library!$AA$14 -> 0 | CB15: =(BY15+BZ15)*Use_Library!$AB$14 -> 0 | CC15: =BX15-BY15-BZ15-CA15+CB15 -> 0 | CD15: =IF(AND(Use_Library!$C$14="Income",Use_Library!$AE$14>0),CC15/Use_Library!$AE$14,0) -> 0 | CE15: =IF(Use_Library!$C$14="Income",-Assumptions!$C$19*Assumptions!$C$20*(1-Use_Library!$AB$14)*BU15,0) -> 0 | CF15: =IF(BV15=0,0,CC15/BV15) -> 0 | CG15: =IF(Use_Library!$AK$14=1,IF(Use_Library!$C$14="Income",CD15*(1-Assumptions!$C$18),S15*Use_Library!$V$14*(1-Assumptions!$C$16))+BM15,0)*U15 -> 12432480 | CH15: =IF(AND(Use_Library!$AK$14=1,Use_Library!$C$14="Income",Use_Library!$AE$14>0),CE15/Use_Library!$AE$14*(1-Assumptions!$C$18),0) -> 0 | CI15: =CG15-BV15 -> 941731.15 | CJ15: =IF(AND(Use_Library!$AK$14=1,U15=1),MAX(0,Parcel!$C$18-((1-Use_Library!$AI$14)*CG15-BV15)/((1-Use_Library!$AI$14)*CH15-BU15)),0) -> 0 | CK15: =IF(Use_Library!$AL$14=1,IF(Use_Library!$C$14="Income",CD15,IF(Use_Library!$AE$14>0,E15*Use_Library!$AG$14/Use_Library!$AE$14,0))+BM15,0)*U15 -> 0 | CL15: =IF(Use_Library!$C$14="Income",BT15,BF15) -> 918391.81 | CM15: =IF(Use_Library!$C$14="Income",BU15,BJ15*BK15) -> 1.0854154 | CN15: =IF(Use_Library!$C$14="Income",BV15,(Parcel!$C$18*BJ15+BF15)*BK15) -> 1279535.2 | CO15: =IF(AND(Use_Library!$AL$14=1,Use_Library!$C$14="Income",Use_Library!$AE$14>0),CE15/Use_Library!$AE$14,0) -> 0 | CP15: =CK15-CN15 -> -1279535.2 | CQ15: =IF(AND(Use_Library!$AL$14=1,U15=1),MAX(0,Parcel!$C$18-((1-Use_Library!$AI$14)*CK15-CN15)/((1-Use_Library!$AI$14)*CO15-CM15)),0) -> 0 | CR15: =IF(Use_Library!$C$14="Income",Assumptions!$C$21*(Parcel!$C$18*BJ15+BT15),0) -> 0 | CS15: =IF(AND(Use_Library!$C$14="Income",CC15>0),MIN(Assumptions!$C$26*CD15,PV(Assumptions!$C$29/12,Assumptions!$C$30*12,-CC15/Assumptions!$C$27/12),CC15/Assumptions!$C$28),0) -> 0 | CT15: =IF(CS15=0,0,CC15/(-PMT(Assumptions!$C$29/12,Assumptions!$C$30*12,CS15)*12)) -> 0 | CU15: =CS15-CR15 -> 0 | CV15: =MAX(BS15,CJ15,CQ15) -> 0 | CW15: =IF(CV15<=0,"None works",IF(BS15=CV15,"Land / pad sale",IF(CJ15=CV15,"Build & sell","Build & hold / lease"))) -> None works | CX15: =CV15*(1-Assumptions!$C$32) -> 0 | CY15: =CV15-Parcel!$C$18 -> -300000 | CZ15: =IF(Parcel!$C$8=0,0,CV15/Parcel!$C$8) -> 0 | DA15: =IF(S15=0,0,CV15/S15) -> 0 | DB15: =TRIM(M15&" "&IF(AND(U15=0,N15=1),"Nothing fits. ","")&IF(Parcel!$C$12<Use_Library!$AM$14,"Frontage under "&Use_Library!$AM$14&" LF. ","")&IF(Parcel!$C$10>0.15,"Slope over 15%. ","")&IF(AND(U15=1,Use_Library!$M$14>0,D15>Use_Library!$M$14),"Only "&Use_Library!$M$14&" ac used - rest resold. ","")) -> Only 4 ac used - rest resold. | DC15: =CV15+ROW()/1000000 -> 1.5e-05
A16: =Use_Library!$A$15 -> Manufactured home community (MHC) | B16: =Use_Library!$C$15 -> Income | C16: =Use_Library!$D$15 -> pad | D16: =MAX(0,Parcel!$C$26*(1-Use_Library!$N$15-Assumptions!$C$7)) -> 14.196 | E16: =IF(Use_Library!$M$15>0,MIN(D16,Use_Library!$M$15),D16) -> 14.196 | F16: =IF(D16=0,0,E16/D16) -> 1 | G16: =Parcel!$C$26*F16 -> 15.6 | H16: =G16*Assumptions!$C$7 -> 0.624 | I16: =G16*(1-Use_Library!$N$15) -> 14.82 | J16: =Parcel!$C$8*(1-F16) -> 0 | K16: =IF(AND(Use_Library!$I$15="Y",Parcel!$C$28=0),0,1) -> 1 | L16: =IF(AND(Use_Library!$J$15="Y",Parcel!$C$27=0),0,1) -> 1 | M16: =TRIM(IF(AND(Use_Library!$AN$15>0,Parcel!$C$19<Use_Library!$AN$15),"Traffic under "&TEXT(Use_Library!$AN$15,"#,##0")&" VPD. ","")&IF(AND(Use_Library!$AO$15>0,Parcel!$C$20<Use_Library!$AO$15),"Under "&TEXT(Use_Library!$AO$15,"#,##0")&" households in 3 mi. ","")&IF(AND(Use_Library!$AP$15>0,Parcel!$C$21>Use_Library!$AP$15),"Over "&Use_Library!$AP$15&" mi to highway. ","")&IF(AND(Use_Library!$AQ$15="Y",Parcel!$C$22<>"Y"),"Needs a corner. ","")&IF(AND(Use_Library!$AR$15>0,Parcel!$C$23>Use_Library!$AR$15),"Over "&Use_Library!$AR$15&" mi to substation. ","")) | N16: =IF(M16="",1,0) -> 1 | O16: =IF(D16>=Use_Library!$L$15,1,0) -> 1 | P16: =IF(Use_Library!$F$15>0,G16*Use_Library!$F$15,1000000000) -> 109.2 | Q16: =IF(Use_Library!$G$15>0,E16*43560/Use_Library!$G$15,1000000000) -> 1000000000 | R16: =IF(AND(Use_Library!$H$15="Y",Parcel!$C$28=0),E16*(1-Assumptions!$C$8)/IF(Parcel!$C$27=1,Assumptions!$C$9,Assumptions!$C$10),1000000000) -> 24.1332 | S16: =IF(K16*L16*O16*N16=0,0,IF(MIN(P16,Q16,R16)>=1000000000,E16,IF(Use_Library!$E$15="Y",INT(MIN(P16,Q16,R16)),MIN(P16,Q16,R16)))) -> 24 | T16: =IF(N16=0,"Location fails",IF(O16=0,"Too small - needs "&Use_Library!$L$15&" usable ac",IF(K16=0,"Needs public sewer",IF(L16=0,"Needs public water",IF(R16<=MIN(P16,Q16),"Septic lot size",IF(Q16<=P16,"Site area / parking","Density")))))) -> Septic lot size | U16: =IF(S16>0,1,0) -> 1 | V16: =IF(Use_Library!$K$15="Y",1,0)*U16 -> 1 | W16: =S16*Use_Library!$O$15*V16 -> 960 | X16: =S16*Use_Library!$P$15*V16 -> 0 | Y16: =IF(Parcel!$C$27=1,W16+Parcel!$C$29,0)*V16 -> 960 | Z16: =S16*Use_Library!$Q$15*Parcel!$C$27*V16 -> 24 | AA16: =IF(Parcel!$C$28=1,W16+Parcel!$C$30,0)*V16 -> 0 | AB16: =S16*Use_Library!$Q$15*Parcel!$C$28*V16 -> 0 | AC16: =IF(Parcel!$C$28=0,S16*Use_Library!$R$15,0)*V16 -> 24 | AD16: =IF(Parcel!$C$27=0,S16*Use_Library!$R$15,0)*V16 -> 0 | AE16: =I16*Parcel!$C$11*V16 -> 5.187 | AF16: =I16*V16 -> 14.82 | AG16: =IF(Use_Library!$C$15="For-Sale",IF(Use_Library!$E$15="Y",S16,1),1)*U16 -> 1 | AH16: =Cost_Library!$G$5*Parcel!$C$32*U16 -> 6500 | AI16: =AG16*Cost_Library!$G$6*Parcel!$C$32 -> 900 | AJ16: =I16*Cost_Library!$G$7*Parcel!$C$32*V16 -> 74100 | AK16: =Cost_Library!$G$8*Parcel!$C$32*V16 -> 5000 | AL16: =AC16*Cost_Library!$G$9*Parcel!$C$32 -> 12000 | AM16: =Cost_Library!$G$10*U16 -> 2800 | AN16: =Cost_Library!$G$11*Parcel!$C$32*V16 -> 7500 | AO16: =Use_Library!$S$15*U16 -> 40000 | AP16: =Cost_Library!$G$12*U16 -> 10000 | AQ16: =AE16*Cost_Library!$G$13*Parcel!$C$32 -> 20748 | AR16: =AF16*Cost_Library!$G$14*Parcel!$C$32*Parcel!$C$33 -> 74100 | AS16: =W16*Cost_Library!$G$15*Parcel!$C$32 -> 144000 | AT16: =X16*Cost_Library!$G$16*Parcel!$C$32 -> 0 | AU16: =H16*Cost_Library!$G$17*Parcel!$C$32*V16 -> 34320 | AV16: =G16*Cost_Library!$G$18*Parcel!$C$32*V16 -> 10920 | AW16: =Y16*Cost_Library!$G$19*Parcel!$C$32 -> 48000 | AX16: =Z16*Cost_Library!$G$20 -> 60000 | AY16: =AA16*Cost_Library!$G$21*Parcel!$C$32 -> 0 | AZ16: =AB16*Cost_Library!$G$22 -> 0 | BA16: =AC16*Cost_Library!$G$23*Parcel!$C$32*Parcel!$C$34 -> 316800 | BB16: =AD16*Cost_Library!$G$24*Parcel!$C$32 -> 0 | BC16: =W16*Cost_Library!$G$25*Parcel!$C$32 -> 24000 | BD16: =SUM(AH16:BC16) -> 891688 | BE16: =BD16*Assumptions!$C$11 -> 89168.8 | BF16: =BD16+BE16 -> 980856.8 | BG16: =S16*Use_Library!$T$15 -> 288000 | BH16: =BG16*(Assumptions!$C$12+Assumptions!$C$13) -> 37440 | BI16: =S16*Use_Library!$AC$15 -> 0 | BJ16: =1+Assumptions!$C$14+Assumptions!$C$15*Use_Library!$AH$15/12 -> 1.045 | BK16: =1+Assumptions!$C$21*(Assumptions!$C$22*Use_Library!$AH$15/12*Assumptions!$C$24+Assumptions!$C$23) -> 1.038675 | BL16: =1+Assumptions!$C$21*(Assumptions!$C$22*(Use_Library!$AH$15/12*Assumptions!$C$24+IF(Use_Library!$C$15="Income",Use_Library!$AD$15,0)/12*Assumptions!$C$25)+Assumptions!$C$23) -> 1.097175 | BM16: =J16*Assumptions!$C$31*(1-Assumptions!$C$17)*U16 -> 0 | BN16: =IF(Use_Library!$AJ$15=1,IF(Use_Library!$C$15="For-Sale",S16*Use_Library!$U$15,E16*Use_Library!$AF$15)*(1-Assumptions!$C$17)+BM16,0)*U16 -> 545126.4 | BO16: =(BD16-AT16)*(1+Assumptions!$C$11) -> 980856.8 | BP16: =BJ16*BK16 -> 1.0854154 | BQ16: =(Parcel!$C$18*BJ16+BO16)*BK16 -> 1344416 | BR16: =BN16-BQ16 -> -799289.65 | BS16: =IF(AND(Use_Library!$AJ$15=1,U16=1),MAX(0,((1-Use_Library!$AI$15)*BN16-BO16*BK16)/BP16),0) -> 0 | BT16: =BF16+BG16+BH16+BI16 -> 1306296.8 | BU16: =BJ16*BL16 -> 1.1465479 | BV16: =(Parcel!$C$18*BJ16+BT16)*BL16 -> 1777200.6 | BW16: =IF(Use_Library!$C$15="Income",S16*Use_Library!$W$15,0) -> 158400 | BX16: =BW16*(1+Use_Library!$X$15)*(1-Use_Library!$Y$15) -> 154677.6 | BY16: =IF(Use_Library!$C$15="Income",S16*Use_Library!$Z$15,0) -> 28800 | BZ16: =IF(Use_Library!$C$15="Income",Assumptions!$C$19*Assumptions!$C$20*BV16,0) -> 33233.65 | CA16: =BX16*Use_Library!$AA$15 -> 7733.88 | CB16: =(BY16+BZ16)*Use_Library!$AB$15 -> 9305.0476 | CC16: =BX16-BY16-BZ16-CA16+CB16 -> 94215.117 | CD16: =IF(AND(Use_Library!$C$15="Income",Use_Library!$AE$15>0),CC16/Use_Library!$AE$15,0) -> 1449463.3 | CE16: =IF(Use_Library!$C$15="Income",-Assumptions!$C$19*Assumptions!$C$20*(1-Use_Library!$AB$15)*BU16,0) -> -0.018224378 | CF16: =IF(BV16=0,0,CC16/BV16) -> 0.053013216 | CG16: =IF(Use_Library!$AK$15=1,IF(Use_Library!$C$15="Income",CD16*(1-Assumptions!$C$18),S16*Use_Library!$V$15*(1-Assumptions!$C$16))+BM16,0)*U16 -> 1420474.1 | CH16: =IF(AND(Use_Library!$AK$15=1,Use_Library!$C$15="Income",Use_Library!$AE$15>0),CE16/Use_Library!$AE$15*(1-Assumptions!$C$18),0) -> -0.27476755 | CI16: =CG16-BV16 -> -356726.48 | CJ16: =IF(AND(Use_Library!$AK$15=1,U16=1),MAX(0,Parcel!$C$18-((1-Use_Library!$AI$15)*CG16-BV16)/((1-Use_Library!$AI$15)*CH16-BU16)),0) -> 0 | CK16: =IF(Use_Library!$AL$15=1,IF(Use_Library!$C$15="Income",CD16,IF(Use_Library!$AE$15>0,E16*Use_Library!$AG$15/Use_Library!$AE$15,0))+BM16,0)*U16 -> 1449463.3 | CL16: =IF(Use_Library!$C$15="Income",BT16,BF16) -> 1306296.8 | CM16: =IF(Use_Library!$C$15="Income",BU16,BJ16*BK16) -> 1.1465479 | CN16: =IF(Use_Library!$C$15="Income",BV16,(Parcel!$C$18*BJ16+BF16)*BK16) -> 1777200.6 | CO16: =IF(AND(Use_Library!$AL$15=1,Use_Library!$C$15="Income",Use_Library!$AE$15>0),CE16/Use_Library!$AE$15,0) -> -0.28037505 | CP16: =CK16-CN16 -> -327737.21 | CQ16: =IF(AND(Use_Library!$AL$15=1,U16=1),MAX(0,Parcel!$C$18-((1-Use_Library!$AI$15)*CK16-CN16)/((1-Use_Library!$AI$15)*CO16-CM16)),0) -> 0 | CR16: =IF(Use_Library!$C$15="Income",Assumptions!$C$21*(Parcel!$C$18*BJ16+BT16),0) -> 1052867.9 | CS16: =IF(AND(Use_Library!$C$15="Income",CC16>0),MIN(Assumptions!$C$26*CD16,PV(Assumptions!$C$29/12,Assumptions!$C$30*12,-CC16/Assumptions!$C$27/12),CC16/Assumptions!$C$28),0) -> 963455.31 | CT16: =IF(CS16=0,0,CC16/(-PMT(Assumptions!$C$29/12,Assumptions!$C$30*12,CS16)*12)) -> 1.25 | CU16: =CS16-CR16 -> -89412.615 | CV16: =MAX(BS16,CJ16,CQ16) -> 0 | CW16: =IF(CV16<=0,"None works",IF(BS16=CV16,"Land / pad sale",IF(CJ16=CV16,"Build & sell","Build & hold / lease"))) -> None works | CX16: =CV16*(1-Assumptions!$C$32) -> 0 | CY16: =CV16-Parcel!$C$18 -> -300000 | CZ16: =IF(Parcel!$C$8=0,0,CV16/Parcel!$C$8) -> 0 | DA16: =IF(S16=0,0,CV16/S16) -> 0 | DB16: =TRIM(M16&" "&IF(AND(U16=0,N16=1),"Nothing fits. ","")&IF(Parcel!$C$12<Use_Library!$AM$15,"Frontage under "&Use_Library!$AM$15&" LF. ","")&IF(Parcel!$C$10>0.15,"Slope over 15%. ","")&IF(AND(U16=1,Use_Library!$M$15>0,D16>Use_Library!$M$15),"Only "&Use_Library!$M$15&" ac used - rest resold. ","")) | DC16: =CV16+ROW()/1000000 -> 1.6e-05
A17: =Use_Library!$A$16 -> Workforce / extended-stay RV park | B17: =Use_Library!$C$16 -> Income | C17: =Use_Library!$D$16 -> site | D17: =MAX(0,Parcel!$C$26*(1-Use_Library!$N$16-Assumptions!$C$7)) -> 14.196 | E17: =IF(Use_Library!$M$16>0,MIN(D17,Use_Library!$M$16),D17) -> 14.196 | F17: =IF(D17=0,0,E17/D17) -> 1 | G17: =Parcel!$C$26*F17 -> 15.6 | H17: =G17*Assumptions!$C$7 -> 0.624 | I17: =G17*(1-Use_Library!$N$16) -> 14.82 | J17: =Parcel!$C$8*(1-F17) -> 0 | K17: =IF(AND(Use_Library!$I$16="Y",Parcel!$C$28=0),0,1) -> 1 | L17: =IF(AND(Use_Library!$J$16="Y",Parcel!$C$27=0),0,1) -> 1 | M17: =TRIM(IF(AND(Use_Library!$AN$16>0,Parcel!$C$19<Use_Library!$AN$16),"Traffic under "&TEXT(Use_Library!$AN$16,"#,##0")&" VPD. ","")&IF(AND(Use_Library!$AO$16>0,Parcel!$C$20<Use_Library!$AO$16),"Under "&TEXT(Use_Library!$AO$16,"#,##0")&" households in 3 mi. ","")&IF(AND(Use_Library!$AP$16>0,Parcel!$C$21>Use_Library!$AP$16),"Over "&Use_Library!$AP$16&" mi to highway. ","")&IF(AND(Use_Library!$AQ$16="Y",Parcel!$C$22<>"Y"),"Needs a corner. ","")&IF(AND(Use_Library!$AR$16>0,Parcel!$C$23>Use_Library!$AR$16),"Over "&Use_Library!$AR$16&" mi to substation. ","")) | N17: =IF(M17="",1,0) -> 1 | O17: =IF(D17>=Use_Library!$L$16,1,0) -> 1 | P17: =IF(Use_Library!$F$16>0,G17*Use_Library!$F$16,1000000000) -> 234 | Q17: =IF(Use_Library!$G$16>0,E17*43560/Use_Library!$G$16,1000000000) -> 1000000000 | R17: =IF(AND(Use_Library!$H$16="Y",Parcel!$C$28=0),E17*(1-Assumptions!$C$8)/IF(Parcel!$C$27=1,Assumptions!$C$9,Assumptions!$C$10),1000000000) -> 1000000000 | S17: =IF(K17*L17*O17*N17=0,0,IF(MIN(P17,Q17,R17)>=1000000000,E17,IF(Use_Library!$E$16="Y",INT(MIN(P17,Q17,R17)),MIN(P17,Q17,R17)))) -> 234 | T17: =IF(N17=0,"Location fails",IF(O17=0,"Too small - needs "&Use_Library!$L$16&" usable ac",IF(K17=0,"Needs public sewer",IF(L17=0,"Needs public water",IF(R17<=MIN(P17,Q17),"Septic lot size",IF(Q17<=P17,"Site area / parking","Density")))))) -> Density | U17: =IF(S17>0,1,0) -> 1 | V17: =IF(Use_Library!$K$16="Y",1,0)*U17 -> 1 | W17: =S17*Use_Library!$O$16*V17 -> 7020 | X17: =S17*Use_Library!$P$16*V17 -> 0 | Y17: =IF(Parcel!$C$27=1,W17+Parcel!$C$29,0)*V17 -> 7020 | Z17: =S17*Use_Library!$Q$16*Parcel!$C$27*V17 -> 58.5 | AA17: =IF(Parcel!$C$28=1,W17+Parcel!$C$30,0)*V17 -> 0 | AB17: =S17*Use_Library!$Q$16*Parcel!$C$28*V17 -> 0 | AC17: =IF(Parcel!$C$28=0,S17*Use_Library!$R$16,0)*V17 -> 58.5 | AD17: =IF(Parcel!$C$27=0,S17*Use_Library!$R$16,0)*V17 -> 0 | AE17: =I17*Parcel!$C$11*V17 -> 5.187 | AF17: =I17*V17 -> 14.82 | AG17: =IF(Use_Library!$C$16="For-Sale",IF(Use_Library!$E$16="Y",S17,1),1)*U17 -> 1 | AH17: =Cost_Library!$G$5*Parcel!$C$32*U17 -> 6500 | AI17: =AG17*Cost_Library!$G$6*Parcel!$C$32 -> 900 | AJ17: =I17*Cost_Library!$G$7*Parcel!$C$32*V17 -> 74100 | AK17: =Cost_Library!$G$8*Parcel!$C$32*V17 -> 5000 | AL17: =AC17*Cost_Library!$G$9*Parcel!$C$32 -> 29250 | AM17: =Cost_Library!$G$10*U17 -> 2800 | AN17: =Cost_Library!$G$11*Parcel!$C$32*V17 -> 7500 | AO17: =Use_Library!$S$16*U17 -> 40000 | AP17: =Cost_Library!$G$12*U17 -> 10000 | AQ17: =AE17*Cost_Library!$G$13*Parcel!$C$32 -> 20748 | AR17: =AF17*Cost_Library!$G$14*Parcel!$C$32*Parcel!$C$33 -> 74100 | AS17: =W17*Cost_Library!$G$15*Parcel!$C$32 -> 1053000 | AT17: =X17*Cost_Library!$G$16*Parcel!$C$32 -> 0 | AU17: =H17*Cost_Library!$G$17*Parcel!$C$32*V17 -> 34320 | AV17: =G17*Cost_Library!$G$18*Parcel!$C$32*V17 -> 10920 | AW17: =Y17*Cost_Library!$G$19*Parcel!$C$32 -> 351000 | AX17: =Z17*Cost_Library!$G$20 -> 146250 | AY17: =AA17*Cost_Library!$G$21*Parcel!$C$32 -> 0 | AZ17: =AB17*Cost_Library!$G$22 -> 0 | BA17: =AC17*Cost_Library!$G$23*Parcel!$C$32*Parcel!$C$34 -> 772200 | BB17: =AD17*Cost_Library!$G$24*Parcel!$C$32 -> 0 | BC17: =W17*Cost_Library!$G$25*Parcel!$C$32 -> 175500 | BD17: =SUM(AH17:BC17) -> 2814088 | BE17: =BD17*Assumptions!$C$11 -> 281408.8 | BF17: =BD17+BE17 -> 3095496.8 | BG17: =S17*Use_Library!$T$16 -> 4212000 | BH17: =BG17*(Assumptions!$C$12+Assumptions!$C$13) -> 547560 | BI17: =S17*Use_Library!$AC$16 -> 0 | BJ17: =1+Assumptions!$C$14+Assumptions!$C$15*Use_Library!$AH$16/12 -> 1.0408333 | BK17: =1+Assumptions!$C$21*(Assumptions!$C$22*Use_Library!$AH$16/12*Assumptions!$C$24+Assumptions!$C$23) -> 1.0333125 | BL17: =1+Assumptions!$C$21*(Assumptions!$C$22*(Use_Library!$AH$16/12*Assumptions!$C$24+IF(Use_Library!$C$16="Income",Use_Library!$AD$16,0)/12*Assumptions!$C$25)+Assumptions!$C$23) -> 1.0625625 | BM17: =J17*Assumptions!$C$31*(1-Assumptions!$C$17)*U17 -> 0 | BN17: =IF(Use_Library!$AJ$16=1,IF(Use_Library!$C$16="For-Sale",S17*Use_Library!$U$16,E17*Use_Library!$AF$16)*(1-Assumptions!$C$17)+BM17,0)*U17 -> 545126.4 | BO17: =(BD17-AT17)*(1+Assumptions!$C$11) -> 3095496.8 | BP17: =BJ17*BK17 -> 1.0755061 | BQ17: =(Parcel!$C$18*BJ17+BO17)*BK17 -> 3521267.4 | BR17: =BN17-BQ17 -> -2976141 | BS17: =IF(AND(Use_Library!$AJ$16=1,U17=1),MAX(0,((1-Use_Library!$AI$16)*BN17-BO17*BK17)/BP17),0) -> 0 | BT17: =BF17+BG17+BH17+BI17 -> 7855056.8 | BU17: =BJ17*BL17 -> 1.1059505 | BV17: =(Parcel!$C$18*BJ17+BT17)*BL17 -> 8678273.9 | BW17: =IF(Use_Library!$C$16="Income",S17*Use_Library!$W$16,0) -> 1825200 | BX17: =BW17*(1+Use_Library!$X$16)*(1-Use_Library!$Y$16) -> 1628991 | BY17: =IF(Use_Library!$C$16="Income",S17*Use_Library!$Z$16,0) -> 421200 | BZ17: =IF(Use_Library!$C$16="Income",Assumptions!$C$19*Assumptions!$C$20*BV17,0) -> 162283.72 | CA17: =BX17*Use_Library!$AA$16 -> 130319.28 | CB17: =(BY17+BZ17)*Use_Library!$AB$16 -> 0 | CC17: =BX17-BY17-BZ17-CA17+CB17 -> 915188 | CD17: =IF(AND(Use_Library!$C$16="Income",Use_Library!$AE$16>0),CC17/Use_Library!$AE$16,0) -> 10766918 | CE17: =IF(Use_Library!$C$16="Income",-Assumptions!$C$19*Assumptions!$C$20*(1-Use_Library!$AB$16)*BU17,0) -> -0.020681274 | CF17: =IF(BV17=0,0,CC17/BV17) -> 0.10545738 | CG17: =IF(Use_Library!$AK$16=1,IF(Use_Library!$C$16="Income",CD17*(1-Assumptions!$C$18),S17*Use_Library!$V$16*(1-Assumptions!$C$16))+BM17,0)*U17 -> 10551579 | CH17: =IF(AND(Use_Library!$AK$16=1,Use_Library!$C$16="Income",Use_Library!$AE$16>0),CE17/Use_Library!$AE$16*(1-Assumptions!$C$18),0) -> -0.23844292 | CI17: =CG17-BV17 -> 1873305.3 | CJ17: =IF(AND(Use_Library!$AK$16=1,U17=1),MAX(0,Parcel!$C$18-((1-Use_Library!$AI$16)*CG17-BV17)/((1-Use_Library!$AI$16)*CH17-BU17)),0) -> 522040.7 | CK17: =IF(Use_Library!$AL$16=1,IF(Use_Library!$C$16="Income",CD17,IF(Use_Library!$AE$16>0,E17*Use_Library!$AG$16/Use_Library!$AE$16,0))+BM17,0)*U17 -> 10766918 | CL17: =IF(Use_Library!$C$16="Income",BT17,BF17) -> 7855056.8 | CM17: =IF(Use_Library!$C$16="Income",BU17,BJ17*BK17) -> 1.1059505 | CN17: =IF(Use_Library!$C$16="Income",BV17,(Parcel!$C$18*BJ17+BF17)*BK17) -> 8678273.9 | CO17: =IF(AND(Use_Library!$AL$16=1,Use_Library!$C$16="Income",Use_Library!$AE$16>0),CE17/Use_Library!$AE$16,0) -> -0.2433091 | CP17: =CK17-CN17 -> 2088643.7 | CQ17: =IF(AND(Use_Library!$AL$16=1,U17=1),MAX(0,Parcel!$C$18-((1-Use_Library!$AI$16)*CK17-CN17)/((1-Use_Library!$AI$16)*CO17-CM17)),0) -> 660770.35 | CR17: =IF(Use_Library!$C$16="Income",Assumptions!$C$21*(Parcel!$C$18*BJ17+BT17),0) -> 5308749.4 | CS17: =IF(AND(Use_Library!$C$16="Income",CC17>0),MIN(Assumptions!$C$26*CD17,PV(Assumptions!$C$29/12,Assumptions!$C$30*12,-CC17/Assumptions!$C$27/12),CC17/Assumptions!$C$28),0) -> 7536842.3 | CT17: =IF(CS17=0,0,CC17/(-PMT(Assumptions!$C$29/12,Assumptions!$C$30*12,CS17)*12)) -> 1.5521793 | CU17: =CS17-CR17 -> 2228092.9 | CV17: =MAX(BS17,CJ17,CQ17) -> 660770.35 | CW17: =IF(CV17<=0,"None works",IF(BS17=CV17,"Land / pad sale",IF(CJ17=CV17,"Build & sell","Build & hold / lease"))) -> Build & hold / lease | CX17: =CV17*(1-Assumptions!$C$32) -> 561654.8 | CY17: =CV17-Parcel!$C$18 -> 360770.35 | CZ17: =IF(Parcel!$C$8=0,0,CV17/Parcel!$C$8) -> 33038.518 | DA17: =IF(S17=0,0,CV17/S17) -> 2823.8049 | DB17: =TRIM(M17&" "&IF(AND(U17=0,N17=1),"Nothing fits. ","")&IF(Parcel!$C$12<Use_Library!$AM$16,"Frontage under "&Use_Library!$AM$16&" LF. ","")&IF(Parcel!$C$10>0.15,"Slope over 15%. ","")&IF(AND(U17=1,Use_Library!$M$16>0,D17>Use_Library!$M$16),"Only "&Use_Library!$M$16&" ac used - rest resold. ","")) | DC17: =CV17+ROW()/1000000 -> 660770.35
A18: =Use_Library!$A$17 -> Workforce rental housing (garden) | B18: =Use_Library!$C$17 -> Income | C18: =Use_Library!$D$17 -> unit | D18: =MAX(0,Parcel!$C$26*(1-Use_Library!$N$17-Assumptions!$C$7)) -> 14.196 | E18: =IF(Use_Library!$M$17>0,MIN(D18,Use_Library!$M$17),D18) -> 14.196 | F18: =IF(D18=0,0,E18/D18) -> 1 | G18: =Parcel!$C$26*F18 -> 15.6 | H18: =G18*Assumptions!$C$7 -> 0.624 | I18: =G18*(1-Use_Library!$N$17) -> 14.82 | J18: =Parcel!$C$8*(1-F18) -> 0 | K18: =IF(AND(Use_Library!$I$17="Y",Parcel!$C$28=0),0,1) -> 0 | L18: =IF(AND(Use_Library!$J$17="Y",Parcel!$C$27=0),0,1) -> 1 | M18: =TRIM(IF(AND(Use_Library!$AN$17>0,Parcel!$C$19<Use_Library!$AN$17),"Traffic under "&TEXT(Use_Library!$AN$17,"#,##0")&" VPD. ","")&IF(AND(Use_Library!$AO$17>0,Parcel!$C$20<Use_Library!$AO$17),"Under "&TEXT(Use_Library!$AO$17,"#,##0")&" households in 3 mi. ","")&IF(AND(Use_Library!$AP$17>0,Parcel!$C$21>Use_Library!$AP$17),"Over "&Use_Library!$AP$17&" mi to highway. ","")&IF(AND(Use_Library!$AQ$17="Y",Parcel!$C$22<>"Y"),"Needs a corner. ","")&IF(AND(Use_Library!$AR$17>0,Parcel!$C$23>Use_Library!$AR$17),"Over "&Use_Library!$AR$17&" mi to substation. ","")) -> Under 4,000 households in 3 mi. | N18: =IF(M18="",1,0) -> 0 | O18: =IF(D18>=Use_Library!$L$17,1,0) -> 1 | P18: =IF(Use_Library!$F$17>0,G18*Use_Library!$F$17,1000000000) -> 312 | Q18: =IF(Use_Library!$G$17>0,E18*43560/Use_Library!$G$17,1000000000) -> 475.6752 | R18: =IF(AND(Use_Library!$H$17="Y",Parcel!$C$28=0),E18*(1-Assumptions!$C$8)/IF(Parcel!$C$27=1,Assumptions!$C$9,Assumptions!$C$10),1000000000) -> 1000000000 | S18: =IF(K18*L18*O18*N18=0,0,IF(MIN(P18,Q18,R18)>=1000000000,E18,IF(Use_Library!$E$17="Y",INT(MIN(P18,Q18,R18)),MIN(P18,Q18,R18)))) -> 0 | T18: =IF(N18=0,"Location fails",IF(O18=0,"Too small - needs "&Use_Library!$L$17&" usable ac",IF(K18=0,"Needs public sewer",IF(L18=0,"Needs public water",IF(R18<=MIN(P18,Q18),"Septic lot size",IF(Q18<=P18,"Site area / parking","Density")))))) -> Location fails | U18: =IF(S18>0,1,0) -> 0 | V18: =IF(Use_Library!$K$17="Y",1,0)*U18 -> 0 | W18: =S18*Use_Library!$O$17*V18 -> 0 | X18: =S18*Use_Library!$P$17*V18 -> 0 | Y18: =IF(Parcel!$C$27=1,W18+Parcel!$C$29,0)*V18 -> 0 | Z18: =S18*Use_Library!$Q$17*Parcel!$C$27*V18 -> 0 | AA18: =IF(Parcel!$C$28=1,W18+Parcel!$C$30,0)*V18 -> 0 | AB18: =S18*Use_Library!$Q$17*Parcel!$C$28*V18 -> 0 | AC18: =IF(Parcel!$C$28=0,S18*Use_Library!$R$17,0)*V18 -> 0 | AD18: =IF(Parcel!$C$27=0,S18*Use_Library!$R$17,0)*V18 -> 0 | AE18: =I18*Parcel!$C$11*V18 -> 0 | AF18: =I18*V18 -> 0 | AG18: =IF(Use_Library!$C$17="For-Sale",IF(Use_Library!$E$17="Y",S18,1),1)*U18 -> 0 | AH18: =Cost_Library!$G$5*Parcel!$C$32*U18 -> 0 | AI18: =AG18*Cost_Library!$G$6*Parcel!$C$32 -> 0 | AJ18: =I18*Cost_Library!$G$7*Parcel!$C$32*V18 -> 0 | AK18: =Cost_Library!$G$8*Parcel!$C$32*V18 -> 0 | AL18: =AC18*Cost_Library!$G$9*Parcel!$C$32 -> 0 | AM18: =Cost_Library!$G$10*U18 -> 0 | AN18: =Cost_Library!$G$11*Parcel!$C$32*V18 -> 0 | AO18: =Use_Library!$S$17*U18 -> 0 | AP18: =Cost_Library!$G$12*U18 -> 0 | AQ18: =AE18*Cost_Library!$G$13*Parcel!$C$32 -> 0 | AR18: =AF18*Cost_Library!$G$14*Parcel!$C$32*Parcel!$C$33 -> 0 | AS18: =W18*Cost_Library!$G$15*Parcel!$C$32 -> 0 | AT18: =X18*Cost_Library!$G$16*Parcel!$C$32 -> 0 | AU18: =H18*Cost_Library!$G$17*Parcel!$C$32*V18 -> 0 | AV18: =G18*Cost_Library!$G$18*Parcel!$C$32*V18 -> 0 | AW18: =Y18*Cost_Library!$G$19*Parcel!$C$32 -> 0 | AX18: =Z18*Cost_Library!$G$20 -> 0 | AY18: =AA18*Cost_Library!$G$21*Parcel!$C$32 -> 0 | AZ18: =AB18*Cost_Library!$G$22 -> 0 | BA18: =AC18*Cost_Library!$G$23*Parcel!$C$32*Parcel!$C$34 -> 0 | BB18: =AD18*Cost_Library!$G$24*Parcel!$C$32 -> 0 | BC18: =W18*Cost_Library!$G$25*Parcel!$C$32 -> 0 | BD18: =SUM(AH18:BC18) -> 0 | BE18: =BD18*Assumptions!$C$11 -> 0 | BF18: =BD18+BE18 -> 0 | BG18: =S18*Use_Library!$T$17 -> 0 | BH18: =BG18*(Assumptions!$C$12+Assumptions!$C$13) -> 0 | BI18: =S18*Use_Library!$AC$17 -> 0 | BJ18: =1+Assumptions!$C$14+Assumptions!$C$15*Use_Library!$AH$17/12 -> 1.0575 | BK18: =1+Assumptions!$C$21*(Assumptions!$C$22*Use_Library!$AH$17/12*Assumptions!$C$24+Assumptions!$C$23) -> 1.0547625 | BL18: =1+Assumptions!$C$21*(Assumptions!$C$22*(Use_Library!$AH$17/12*Assumptions!$C$24+IF(Use_Library!$C$17="Income",Use_Library!$AD$17,0)/12*Assumptions!$C$25)+Assumptions!$C$23) -> 1.091325 | BM18: =J18*Assumptions!$C$31*(1-Assumptions!$C$17)*U18 -> 0 | BN18: =IF(Use_Library!$AJ$17=1,IF(Use_Library!$C$17="For-Sale",S18*Use_Library!$U$17,E18*Use_Library!$AF$17)*(1-Assumptions!$C$17)+BM18,0)*U18 -> 0 | BO18: =(BD18-AT18)*(1+Assumptions!$C$11) -> 0 | BP18: =BJ18*BK18 -> 1.1154113 | BQ18: =(Parcel!$C$18*BJ18+BO18)*BK18 -> 334623.4 | BR18: =BN18-BQ18 -> -334623.4 | BS18: =IF(AND(Use_Library!$AJ$17=1,U18=1),MAX(0,((1-Use_Library!$AI$17)*BN18-BO18*BK18)/BP18),0) -> 0 | BT18: =BF18+BG18+BH18+BI18 -> 0 | BU18: =BJ18*BL18 -> 1.1540762 | BV18: =(Parcel!$C$18*BJ18+BT18)*BL18 -> 346222.86 | BW18: =IF(Use_Library!$C$17="Income",S18*Use_Library!$W$17,0) -> 0 | BX18: =BW18*(1+Use_Library!$X$17)*(1-Use_Library!$Y$17) -> 0 | BY18: =IF(Use_Library!$C$17="Income",S18*Use_Library!$Z$17,0) -> 0 | BZ18: =IF(Use_Library!$C$17="Income",Assumptions!$C$19*Assumptions!$C$20*BV18,0) -> 6474.3674 | CA18: =BX18*Use_Library!$AA$17 -> 0 | CB18: =(BY18+BZ18)*Use_Library!$AB$17 -> 323.71837 | CC18: =BX18-BY18-BZ18-CA18+CB18 -> -6150.649 | CD18: =IF(AND(Use_Library!$C$17="Income",Use_Library!$AE$17>0),CC18/Use_Library!$AE$17,0) -> -106967.81 | CE18: =IF(Use_Library!$C$17="Income",-Assumptions!$C$19*Assumptions!$C$20*(1-Use_Library!$AB$17)*BU18,0) -> -0.020502163 | CF18: =IF(BV18=0,0,CC18/BV18) -> -0.017765 | CG18: =IF(Use_Library!$AK$17=1,IF(Use_Library!$C$17="Income",CD18*(1-Assumptions!$C$18),S18*Use_Library!$V$17*(1-Assumptions!$C$16))+BM18,0)*U18 -> 0 | CH18: =IF(AND(Use_Library!$AK$17=1,Use_Library!$C$17="Income",Use_Library!$AE$17>0),CE18/Use_Library!$AE$17*(1-Assumptions!$C$18),0) -> -0.34942818 | CI18: =CG18-BV18 -> -346222.86 | CJ18: =IF(AND(Use_Library!$AK$17=1,U18=1),MAX(0,Parcel!$C$18-((1-Use_Library!$AI$17)*CG18-BV18)/((1-Use_Library!$AI$17)*CH18-BU18)),0) -> 0 | CK18: =IF(Use_Library!$AL$17=1,IF(Use_Library!$C$17="Income",CD18,IF(Use_Library!$AE$17>0,E18*Use_Library!$AG$17/Use_Library!$AE$17,0))+BM18,0)*U18 -> 0 | CL18: =IF(Use_Library!$C$17="Income",BT18,BF18) -> 0 | CM18: =IF(Use_Library!$C$17="Income",BU18,BJ18*BK18) -> 1.1540762 | CN18: =IF(Use_Library!$C$17="Income",BV18,(Parcel!$C$18*BJ18+BF18)*BK18) -> 346222.86 | CO18: =IF(AND(Use_Library!$AL$17=1,Use_Library!$C$17="Income",Use_Library!$AE$17>0),CE18/Use_Library!$AE$17,0) -> -0.35655936 | CP18: =CK18-CN18 -> -346222.86 | CQ18: =IF(AND(Use_Library!$AL$17=1,U18=1),MAX(0,Parcel!$C$18-((1-Use_Library!$AI$17)*CK18-CN18)/((1-Use_Library!$AI$17)*CO18-CM18)),0) -> 0 | CR18: =IF(Use_Library!$C$17="Income",Assumptions!$C$21*(Parcel!$C$18*BJ18+BT18),0) -> 206212.5 | CS18: =IF(AND(Use_Library!$C$17="Income",CC18>0),MIN(Assumptions!$C$26*CD18,PV(Assumptions!$C$29/12,Assumptions!$C$30*12,-CC18/Assumptions!$C$27/12),CC18/Assumptions!$C$28),0) -> 0 | CT18: =IF(CS18=0,0,CC18/(-PMT(Assumptions!$C$29/12,Assumptions!$C$30*12,CS18)*12)) -> 0 | CU18: =CS18-CR18 -> -206212.5 | CV18: =MAX(BS18,CJ18,CQ18) -> 0 | CW18: =IF(CV18<=0,"None works",IF(BS18=CV18,"Land / pad sale",IF(CJ18=CV18,"Build & sell","Build & hold / lease"))) -> None works | CX18: =CV18*(1-Assumptions!$C$32) -> 0 | CY18: =CV18-Parcel!$C$18 -> -300000 | CZ18: =IF(Parcel!$C$8=0,0,CV18/Parcel!$C$8) -> 0 | DA18: =IF(S18=0,0,CV18/S18) -> 0 | DB18: =TRIM(M18&" "&IF(AND(U18=0,N18=1),"Nothing fits. ","")&IF(Parcel!$C$12<Use_Library!$AM$17,"Frontage under "&Use_Library!$AM$17&" LF. ","")&IF(Parcel!$C$10>0.15,"Slope over 15%. ","")&IF(AND(U18=1,Use_Library!$M$17>0,D18>Use_Library!$M$17),"Only "&Use_Library!$M$17&" ac used - rest resold. ","")) -> Under 4,000 households in 3 mi. | DC18: =CV18+ROW()/1000000 -> 1.8e-05
A19: =Use_Library!$A$18 -> Multifamily - large garden (150+ units) | B19: =Use_Library!$C$18 -> Income | C19: =Use_Library!$D$18 -> unit | D19: =MAX(0,Parcel!$C$26*(1-Use_Library!$N$18-Assumptions!$C$7)) -> 14.196 | E19: =IF(Use_Library!$M$18>0,MIN(D19,Use_Library!$M$18),D19) -> 14.196 | F19: =IF(D19=0,0,E19/D19) -> 1 | G19: =Parcel!$C$26*F19 -> 15.6 | H19: =G19*Assumptions!$C$7 -> 0.624 | I19: =G19*(1-Use_Library!$N$18) -> 14.82 | J19: =Parcel!$C$8*(1-F19) -> 0 | K19: =IF(AND(Use_Library!$I$18="Y",Parcel!$C$28=0),0,1) -> 0 | L19: =IF(AND(Use_Library!$J$18="Y",Parcel!$C$27=0),0,1) -> 1 | M19: =TRIM(IF(AND(Use_Library!$AN$18>0,Parcel!$C$19<Use_Library!$AN$18),"Traffic under "&TEXT(Use_Library!$AN$18,"#,##0")&" VPD. ","")&IF(AND(Use_Library!$AO$18>0,Parcel!$C$20<Use_Library!$AO$18),"Under "&TEXT(Use_Library!$AO$18,"#,##0")&" households in 3 mi. ","")&IF(AND(Use_Library!$AP$18>0,Parcel!$C$21>Use_Library!$AP$18),"Over "&Use_Library!$AP$18&" mi to highway. ","")&IF(AND(Use_Library!$AQ$18="Y",Parcel!$C$22<>"Y"),"Needs a corner. ","")&IF(AND(Use_Library!$AR$18>0,Parcel!$C$23>Use_Library!$AR$18),"Over "&Use_Library!$AR$18&" mi to substation. ","")) -> Under 8,000 households in 3 mi. | N19: =IF(M19="",1,0) -> 0 | O19: =IF(D19>=Use_Library!$L$18,1,0) -> 1 | P19: =IF(Use_Library!$F$18>0,G19*Use_Library!$F$18,1000000000) -> 374.4 | Q19: =IF(Use_Library!$G$18>0,E19*43560/Use_Library!$G$18,1000000000) -> 515.3148 | R19: =IF(AND(Use_Library!$H$18="Y",Parcel!$C$28=0),E19*(1-Assumptions!$C$8)/IF(Parcel!$C$27=1,Assumptions!$C$9,Assumptions!$C$10),1000000000) -> 1000000000 | S19: =IF(K19*L19*O19*N19=0,0,IF(MIN(P19,Q19,R19)>=1000000000,E19,IF(Use_Library!$E$18="Y",INT(MIN(P19,Q19,R19)),MIN(P19,Q19,R19)))) -> 0 | T19: =IF(N19=0,"Location fails",IF(O19=0,"Too small - needs "&Use_Library!$L$18&" usable ac",IF(K19=0,"Needs public sewer",IF(L19=0,"Needs public water",IF(R19<=MIN(P19,Q19),"Septic lot size",IF(Q19<=P19,"Site area / parking","Density")))))) -> Location fails | U19: =IF(S19>0,1,0) -> 0 | V19: =IF(Use_Library!$K$18="Y",1,0)*U19 -> 0 | W19: =S19*Use_Library!$O$18*V19 -> 0 | X19: =S19*Use_Library!$P$18*V19 -> 0 | Y19: =IF(Parcel!$C$27=1,W19+Parcel!$C$29,0)*V19 -> 0 | Z19: =S19*Use_Library!$Q$18*Parcel!$C$27*V19 -> 0 | AA19: =IF(Parcel!$C$28=1,W19+Parcel!$C$30,0)*V19 -> 0 | AB19: =S19*Use_Library!$Q$18*Parcel!$C$28*V19 -> 0 | AC19: =IF(Parcel!$C$28=0,S19*Use_Library!$R$18,0)*V19 -> 0 | AD19: =IF(Parcel!$C$27=0,S19*Use_Library!$R$18,0)*V19 -> 0 | AE19: =I19*Parcel!$C$11*V19 -> 0 | AF19: =I19*V19 -> 0 | AG19: =IF(Use_Library!$C$18="For-Sale",IF(Use_Library!$E$18="Y",S19,1),1)*U19 -> 0 | AH19: =Cost_Library!$G$5*Parcel!$C$32*U19 -> 0 | AI19: =AG19*Cost_Library!$G$6*Parcel!$C$32 -> 0 | AJ19: =I19*Cost_Library!$G$7*Parcel!$C$32*V19 -> 0 | AK19: =Cost_Library!$G$8*Parcel!$C$32*V19 -> 0 | AL19: =AC19*Cost_Library!$G$9*Parcel!$C$32 -> 0 | AM19: =Cost_Library!$G$10*U19 -> 0 | AN19: =Cost_Library!$G$11*Parcel!$C$32*V19 -> 0 | AO19: =Use_Library!$S$18*U19 -> 0 | AP19: =Cost_Library!$G$12*U19 -> 0 | AQ19: =AE19*Cost_Library!$G$13*Parcel!$C$32 -> 0 | AR19: =AF19*Cost_Library!$G$14*Parcel!$C$32*Parcel!$C$33 -> 0 | AS19: =W19*Cost_Library!$G$15*Parcel!$C$32 -> 0 | AT19: =X19*Cost_Library!$G$16*Parcel!$C$32 -> 0 | AU19: =H19*Cost_Library!$G$17*Parcel!$C$32*V19 -> 0 | AV19: =G19*Cost_Library!$G$18*Parcel!$C$32*V19 -> 0 | AW19: =Y19*Cost_Library!$G$19*Parcel!$C$32 -> 0 | AX19: =Z19*Cost_Library!$G$20 -> 0 | AY19: =AA19*Cost_Library!$G$21*Parcel!$C$32 -> 0 | AZ19: =AB19*Cost_Library!$G$22 -> 0 | BA19: =AC19*Cost_Library!$G$23*Parcel!$C$32*Parcel!$C$34 -> 0 | BB19: =AD19*Cost_Library!$G$24*Parcel!$C$32 -> 0 | BC19: =W19*Cost_Library!$G$25*Parcel!$C$32 -> 0 | BD19: =SUM(AH19:BC19) -> 0 | BE19: =BD19*Assumptions!$C$11 -> 0 | BF19: =BD19+BE19 -> 0 | BG19: =S19*Use_Library!$T$18 -> 0 | BH19: =BG19*(Assumptions!$C$12+Assumptions!$C$13) -> 0 | BI19: =S19*Use_Library!$AC$18 -> 0 | BJ19: =1+Assumptions!$C$14+Assumptions!$C$15*Use_Library!$AH$18/12 -> 1.0616667 | BK19: =1+Assumptions!$C$21*(Assumptions!$C$22*Use_Library!$AH$18/12*Assumptions!$C$24+Assumptions!$C$23) -> 1.060125 | BL19: =1+Assumptions!$C$21*(Assumptions!$C$22*(Use_Library!$AH$18/12*Assumptions!$C$24+IF(Use_Library!$C$18="Income",Use_Library!$AD$18,0)/12*Assumptions!$C$25)+Assumptions!$C$23) -> 1.104 | BM19: =J19*Assumptions!$C$31*(1-Assumptions!$C$17)*U19 -> 0 | BN19: =IF(Use_Library!$AJ$18=1,IF(Use_Library!$C$18="For-Sale",S19*Use_Library!$U$18,E19*Use_Library!$AF$18)*(1-Assumptions!$C$17)+BM19,0)*U19 -> 0 | BO19: =(BD19-AT19)*(1+Assumptions!$C$11) -> 0 | BP19: =BJ19*BK19 -> 1.1254994 | BQ19: =(Parcel!$C$18*BJ19+BO19)*BK19 -> 337649.81 | BR19: =BN19-BQ19 -> -337649.81 | BS19: =IF(AND(Use_Library!$AJ$18=1,U19=1),MAX(0,((1-Use_Library!$AI$18)*BN19-BO19*BK19)/BP19),0) -> 0 | BT19: =BF19+BG19+BH19+BI19 -> 0 | BU19: =BJ19*BL19 -> 1.17208 | BV19: =(Parcel!$C$18*BJ19+BT19)*BL19 -> 351624 | BW19: =IF(Use_Library!$C$18="Income",S19*Use_Library!$W$18,0) -> 0 | BX19: =BW19*(1+Use_Library!$X$18)*(1-Use_Library!$Y$18) -> 0 | BY19: =IF(Use_Library!$C$18="Income",S19*Use_Library!$Z$18,0) -> 0 | BZ19: =IF(Use_Library!$C$18="Income",Assumptions!$C$19*Assumptions!$C$20*BV19,0) -> 6575.3688 | CA19: =BX19*Use_Library!$AA$18 -> 0 | CB19: =(BY19+BZ19)*Use_Library!$AB$18 -> 328.76844 | CC19: =BX19-BY19-BZ19-CA19+CB19 -> -6246.6004 | CD19: =IF(AND(Use_Library!$C$18="Income",Use_Library!$AE$18>0),CC19/Use_Library!$AE$18,0) -> -113574.55 | CE19: =IF(Use_Library!$C$18="Income",-Assumptions!$C$19*Assumptions!$C$20*(1-Use_Library!$AB$18)*BU19,0) -> -0.020822001 | CF19: =IF(BV19=0,0,CC19/BV19) -> -0.017765 | CG19: =IF(Use_Library!$AK$18=1,IF(Use_Library!$C$18="Income",CD19*(1-Assumptions!$C$18),S19*Use_Library!$V$18*(1-Assumptions!$C$16))+BM19,0)*U19 -> 0 | CH19: =IF(AND(Use_Library!$AK$18=1,Use_Library!$C$18="Income",Use_Library!$AE$18>0),CE19/Use_Library!$AE$18*(1-Assumptions!$C$18),0) -> -0.3710102 | CI19: =CG19-BV19 -> -351624 | CJ19: =IF(AND(Use_Library!$AK$18=1,U19=1),MAX(0,Parcel!$C$18-((1-Use_Library!$AI$18)*CG19-BV19)/((1-Use_Library!$AI$18)*CH19-BU19)),0) -> 0 | CK19: =IF(Use_Library!$AL$18=1,IF(Use_Library!$C$18="Income",CD19,IF(Use_Library!$AE$18>0,E19*Use_Library!$AG$18/Use_Library!$AE$18,0))+BM19,0)*U19 -> 0 | CL19: =IF(Use_Library!$C$18="Income",BT19,BF19) -> 0 | CM19: =IF(Use_Library!$C$18="Income",BU19,BJ19*BK19) -> 1.17208 | CN19: =IF(Use_Library!$C$18="Income",BV19,(Parcel!$C$18*BJ19+BF19)*BK19) -> 351624 | CO19: =IF(AND(Use_Library!$AL$18=1,Use_Library!$C$18="Income",Use_Library!$AE$18>0),CE19/Use_Library!$AE$18,0) -> -0.37858184 | CP19: =CK19-CN19 -> -351624 | CQ19: =IF(AND(Use_Library!$AL$18=1,U19=1),MAX(0,Parcel!$C$18-((1-Use_Library!$AI$18)*CK19-CN19)/((1-Use_Library!$AI$18)*CO19-CM19)),0) -> 0 | CR19: =IF(Use_Library!$C$18="Income",Assumptions!$C$21*(Parcel!$C$18*BJ19+BT19),0) -> 207025 | CS19: =IF(AND(Use_Library!$C$18="Income",CC19>0),MIN(Assumptions!$C$26*CD19,PV(Assumptions!$C$29/12,Assumptions!$C$30*12,-CC19/Assumptions!$C$27/12),CC19/Assumptions!$C$28),0) -> 0 | CT19: =IF(CS19=0,0,CC19/(-PMT(Assumptions!$C$29/12,Assumptions!$C$30*12,CS19)*12)) -> 0 | CU19: =CS19-CR19 -> -207025 | CV19: =MAX(BS19,CJ19,CQ19) -> 0 | CW19: =IF(CV19<=0,"None works",IF(BS19=CV19,"Land / pad sale",IF(CJ19=CV19,"Build & sell","Build & hold / lease"))) -> None works | CX19: =CV19*(1-Assumptions!$C$32) -> 0 | CY19: =CV19-Parcel!$C$18 -> -300000 | CZ19: =IF(Parcel!$C$8=0,0,CV19/Parcel!$C$8) -> 0 | DA19: =IF(S19=0,0,CV19/S19) -> 0 | DB19: =TRIM(M19&" "&IF(AND(U19=0,N19=1),"Nothing fits. ","")&IF(Parcel!$C$12<Use_Library!$AM$18,"Frontage under "&Use_Library!$AM$18&" LF. ","")&IF(Parcel!$C$10>0.15,"Slope over 15%. ","")&IF(AND(U19=1,Use_Library!$M$18>0,D19>Use_Library!$M$18),"Only "&Use_Library!$M$18&" ac used - rest resold. ","")) -> Under 8,000 households in 3 mi. | DC19: =CV19+ROW()/1000000 -> 1.9e-05
A20: =Use_Library!$A$19 -> Multifamily - mid-rise / wrap | B20: =Use_Library!$C$19 -> Income | C20: =Use_Library!$D$19 -> unit | D20: =MAX(0,Parcel!$C$26*(1-Use_Library!$N$19-Assumptions!$C$7)) -> 14.196 | E20: =IF(Use_Library!$M$19>0,MIN(D20,Use_Library!$M$19),D20) -> 6 | F20: =IF(D20=0,0,E20/D20) -> 0.42265427 | G20: =Parcel!$C$26*F20 -> 6.5934066 | H20: =G20*Assumptions!$C$7 -> 0.26373626 | I20: =G20*(1-Use_Library!$N$19) -> 6.2637363 | J20: =Parcel!$C$8*(1-F20) -> 11.546915 | K20: =IF(AND(Use_Library!$I$19="Y",Parcel!$C$28=0),0,1) -> 0 | L20: =IF(AND(Use_Library!$J$19="Y",Parcel!$C$27=0),0,1) -> 1 | M20: =TRIM(IF(AND(Use_Library!$AN$19>0,Parcel!$C$19<Use_Library!$AN$19),"Traffic under "&TEXT(Use_Library!$AN$19,"#,##0")&" VPD. ","")&IF(AND(Use_Library!$AO$19>0,Parcel!$C$20<Use_Library!$AO$19),"Under "&TEXT(Use_Library!$AO$19,"#,##0")&" households in 3 mi. ","")&IF(AND(Use_Library!$AP$19>0,Parcel!$C$21>Use_Library!$AP$19),"Over "&Use_Library!$AP$19&" mi to highway. ","")&IF(AND(Use_Library!$AQ$19="Y",Parcel!$C$22<>"Y"),"Needs a corner. ","")&IF(AND(Use_Library!$AR$19>0,Parcel!$C$23>Use_Library!$AR$19),"Over "&Use_Library!$AR$19&" mi to substation. ","")) -> Under 15,000 households in 3 mi. | N20: =IF(M20="",1,0) -> 0 | O20: =IF(D20>=Use_Library!$L$19,1,0) -> 1 | P20: =IF(Use_Library!$F$19>0,G20*Use_Library!$F$19,1000000000) -> 395.6044 | Q20: =IF(Use_Library!$G$19>0,E20*43560/Use_Library!$G$19,1000000000) -> 522.72 | R20: =IF(AND(Use_Library!$H$19="Y",Parcel!$C$28=0),E20*(1-Assumptions!$C$8)/IF(Parcel!$C$27=1,Assumptions!$C$9,Assumptions!$C$10),1000000000) -> 1000000000 | S20: =IF(K20*L20*O20*N20=0,0,IF(MIN(P20,Q20,R20)>=1000000000,E20,IF(Use_Library!$E$19="Y",INT(MIN(P20,Q20,R20)),MIN(P20,Q20,R20)))) -> 0 | T20: =IF(N20=0,"Location fails",IF(O20=0,"Too small - needs "&Use_Library!$L$19&" usable ac",IF(K20=0,"Needs public sewer",IF(L20=0,"Needs public water",IF(R20<=MIN(P20,Q20),"Septic lot size",IF(Q20<=P20,"Site area / parking","Density")))))) -> Location fails | U20: =IF(S20>0,1,0) -> 0 | V20: =IF(Use_Library!$K$19="Y",1,0)*U20 -> 0 | W20: =S20*Use_Library!$O$19*V20 -> 0 | X20: =S20*Use_Library!$P$19*V20 -> 0 | Y20: =IF(Parcel!$C$27=1,W20+Parcel!$C$29,0)*V20 -> 0 | Z20: =S20*Use_Library!$Q$19*Parcel!$C$27*V20 -> 0 | AA20: =IF(Parcel!$C$28=1,W20+Parcel!$C$30,0)*V20 -> 0 | AB20: =S20*Use_Library!$Q$19*Parcel!$C$28*V20 -> 0 | AC20: =IF(Parcel!$C$28=0,S20*Use_Library!$R$19,0)*V20 -> 0 | AD20: =IF(Parcel!$C$27=0,S20*Use_Library!$R$19,0)*V20 -> 0 | AE20: =I20*Parcel!$C$11*V20 -> 0 | AF20: =I20*V20 -> 0 | AG20: =IF(Use_Library!$C$19="For-Sale",IF(Use_Library!$E$19="Y",S20,1),1)*U20 -> 0 | AH20: =Cost_Library!$G$5*Parcel!$C$32*U20 -> 0 | AI20: =AG20*Cost_Library!$G$6*Parcel!$C$32 -> 0 | AJ20: =I20*Cost_Library!$G$7*Parcel!$C$32*V20 -> 0 | AK20: =Cost_Library!$G$8*Parcel!$C$32*V20 -> 0 | AL20: =AC20*Cost_Library!$G$9*Parcel!$C$32 -> 0 | AM20: =Cost_Library!$G$10*U20 -> 0 | AN20: =Cost_Library!$G$11*Parcel!$C$32*V20 -> 0 | AO20: =Use_Library!$S$19*U20 -> 0 | AP20: =Cost_Library!$G$12*U20 -> 0 | AQ20: =AE20*Cost_Library!$G$13*Parcel!$C$32 -> 0 | AR20: =AF20*Cost_Library!$G$14*Parcel!$C$32*Parcel!$C$33 -> 0 | AS20: =W20*Cost_Library!$G$15*Parcel!$C$32 -> 0 | AT20: =X20*Cost_Library!$G$16*Parcel!$C$32 -> 0 | AU20: =H20*Cost_Library!$G$17*Parcel!$C$32*V20 -> 0 | AV20: =G20*Cost_Library!$G$18*Parcel!$C$32*V20 -> 0 | AW20: =Y20*Cost_Library!$G$19*Parcel!$C$32 -> 0 | AX20: =Z20*Cost_Library!$G$20 -> 0 | AY20: =AA20*Cost_Library!$G$21*Parcel!$C$32 -> 0 | AZ20: =AB20*Cost_Library!$G$22 -> 0 | BA20: =AC20*Cost_Library!$G$23*Parcel!$C$32*Parcel!$C$34 -> 0 | BB20: =AD20*Cost_Library!$G$24*Parcel!$C$32 -> 0 | BC20: =W20*Cost_Library!$G$25*Parcel!$C$32 -> 0 | BD20: =SUM(AH20:BC20) -> 0 | BE20: =BD20*Assumptions!$C$11 -> 0 | BF20: =BD20+BE20 -> 0 | BG20: =S20*Use_Library!$T$19 -> 0 | BH20: =BG20*(Assumptions!$C$12+Assumptions!$C$13) -> 0 | BI20: =S20*Use_Library!$AC$19 -> 0 | BJ20: =1+Assumptions!$C$14+Assumptions!$C$15*Use_Library!$AH$19/12 -> 1.0741667 | BK20: =1+Assumptions!$C$21*(Assumptions!$C$22*Use_Library!$AH$19/12*Assumptions!$C$24+Assumptions!$C$23) -> 1.0762125 | BL20: =1+Assumptions!$C$21*(Assumptions!$C$22*(Use_Library!$AH$19/12*Assumptions!$C$24+IF(Use_Library!$C$19="Income",Use_Library!$AD$19,0)/12*Assumptions!$C$25)+Assumptions!$C$23) -> 1.1249625 | BM20: =J20*Assumptions!$C$31*(1-Assumptions!$C$17)*U20 -> 0 | BN20: =IF(Use_Library!$AJ$19=1,IF(Use_Library!$C$19="For-Sale",S20*Use_Library!$U$19,E20*Use_Library!$AF$19)*(1-Assumptions!$C$17)+BM20,0)*U20 -> 0 | BO20: =(BD20-AT20)*(1+Assumptions!$C$11) -> 0 | BP20: =BJ20*BK20 -> 1.1560316 | BQ20: =(Parcel!$C$18*BJ20+BO20)*BK20 -> 346809.48 | BR20: =BN20-BQ20 -> -346809.48 | BS20: =IF(AND(Use_Library!$AJ$19=1,U20=1),MAX(0,((1-Use_Library!$AI$19)*BN20-BO20*BK20)/BP20),0) -> 0 | BT20: =BF20+BG20+BH20+BI20 -> 0 | BU20: =BJ20*BL20 -> 1.2083972 | BV20: =(Parcel!$C$18*BJ20+BT20)*BL20 -> 362519.17 | BW20: =IF(Use_Library!$C$19="Income",S20*Use_Library!$W$19,0) -> 0 | BX20: =BW20*(1+Use_Library!$X$19)*(1-Use_Library!$Y$19) -> 0 | BY20: =IF(Use_Library!$C$19="Income",S20*Use_Library!$Z$19,0) -> 0 | BZ20: =IF(Use_Library!$C$19="Income",Assumptions!$C$19*Assumptions!$C$20*BV20,0) -> 6779.1084 | CA20: =BX20*Use_Library!$AA$19 -> 0 | CB20: =(BY20+BZ20)*Use_Library!$AB$19 -> 338.95542 | CC20: =BX20-BY20-BZ20-CA20+CB20 -> -6440.153 | CD20: =IF(AND(Use_Library!$C$19="Income",Use_Library!$AE$19>0),CC20/Use_Library!$AE$19,0) -> -122669.58 | CE20: =IF(Use_Library!$C$19="Income",-Assumptions!$C$19*Assumptions!$C$20*(1-Use_Library!$AB$19)*BU20,0) -> -0.021467177 | CF20: =IF(BV20=0,0,CC20/BV20) -> -0.017765 | CG20: =IF(Use_Library!$AK$19=1,IF(Use_Library!$C$19="Income",CD20*(1-Assumptions!$C$18),S20*Use_Library!$V$19*(1-Assumptions!$C$16))+BM20,0)*U20 -> 0 | CH20: =IF(AND(Use_Library!$AK$19=1,Use_Library!$C$19="Income",Use_Library!$AE$19>0),CE20/Use_Library!$AE$19*(1-Assumptions!$C$18),0) -> -0.40072063 | CI20: =CG20-BV20 -> -362519.17 | CJ20: =IF(AND(Use_Library!$AK$19=1,U20=1),MAX(0,Parcel!$C$18-((1-Use_Library!$AI$19)*CG20-BV20)/((1-Use_Library!$AI$19)*CH20-BU20)),0) -> 0 | CK20: =IF(Use_Library!$AL$19=1,IF(Use_Library!$C$19="Income",CD20,IF(Use_Library!$AE$19>0,E20*Use_Library!$AG$19/Use_Library!$AE$19,0))+BM20,0)*U20 -> 0 | CL20: =IF(Use_Library!$C$19="Income",BT20,BF20) -> 0 | CM20: =IF(Use_Library!$C$19="Income",BU20,BJ20*BK20) -> 1.2083972 | CN20: =IF(Use_Library!$C$19="Income",BV20,(Parcel!$C$18*BJ20+BF20)*BK20) -> 362519.17 | CO20: =IF(AND(Use_Library!$AL$19=1,Use_Library!$C$19="Income",Use_Library!$AE$19>0),CE20/Use_Library!$AE$19,0) -> -0.4088986 | CP20: =CK20-CN20 -> -362519.17 | CQ20: =IF(AND(Use_Library!$AL$19=1,U20=1),MAX(0,Parcel!$C$18-((1-Use_Library!$AI$19)*CK20-CN20)/((1-Use_Library!$AI$19)*CO20-CM20)),0) -> 0 | CR20: =IF(Use_Library!$C$19="Income",Assumptions!$C$21*(Parcel!$C$18*BJ20+BT20),0) -> 209462.5 | CS20: =IF(AND(Use_Library!$C$19="Income",CC20>0),MIN(Assumptions!$C$26*CD20,PV(Assumptions!$C$29/12,Assumptions!$C$30*12,-CC20/Assumptions!$C$27/12),CC20/Assumptions!$C$28),0) -> 0 | CT20: =IF(CS20=0,0,CC20/(-PMT(Assumptions!$C$29/12,Assumptions!$C$30*12,CS20)*12)) -> 0 | CU20: =CS20-CR20 -> -209462.5 | CV20: =MAX(BS20,CJ20,CQ20) -> 0 | CW20: =IF(CV20<=0,"None works",IF(BS20=CV20,"Land / pad sale",IF(CJ20=CV20,"Build & sell","Build & hold / lease"))) -> None works | CX20: =CV20*(1-Assumptions!$C$32) -> 0 | CY20: =CV20-Parcel!$C$18 -> -300000 | CZ20: =IF(Parcel!$C$8=0,0,CV20/Parcel!$C$8) -> 0 | DA20: =IF(S20=0,0,CV20/S20) -> 0 | DB20: =TRIM(M20&" "&IF(AND(U20=0,N20=1),"Nothing fits. ","")&IF(Parcel!$C$12<Use_Library!$AM$19,"Frontage under "&Use_Library!$AM$19&" LF. ","")&IF(Parcel!$C$10>0.15,"Slope over 15%. ","")&IF(AND(U20=1,Use_Library!$M$19>0,D20>Use_Library!$M$19),"Only "&Use_Library!$M$19&" ac used - rest resold. ","")) -> Under 15,000 households in 3 mi. | DC20: =CV20+ROW()/1000000 -> 2e-05
A21: =Use_Library!$A$20 -> Duplex / fourplex rental | B21: =Use_Library!$C$20 -> Income | C21: =Use_Library!$D$20 -> unit | D21: =MAX(0,Parcel!$C$26*(1-Use_Library!$N$20-Assumptions!$C$7)) -> 14.196 | E21: =IF(Use_Library!$M$20>0,MIN(D21,Use_Library!$M$20),D21) -> 14.196 | F21: =IF(D21=0,0,E21/D21) -> 1 | G21: =Parcel!$C$26*F21 -> 15.6 | H21: =G21*Assumptions!$C$7 -> 0.624 | I21: =G21*(1-Use_Library!$N$20) -> 14.82 | J21: =Parcel!$C$8*(1-F21) -> 0 | K21: =IF(AND(Use_Library!$I$20="Y",Parcel!$C$28=0),0,1) -> 0 | L21: =IF(AND(Use_Library!$J$20="Y",Parcel!$C$27=0),0,1) -> 1 | M21: =TRIM(IF(AND(Use_Library!$AN$20>0,Parcel!$C$19<Use_Library!$AN$20),"Traffic under "&TEXT(Use_Library!$AN$20,"#,##0")&" VPD. ","")&IF(AND(Use_Library!$AO$20>0,Parcel!$C$20<Use_Library!$AO$20),"Under "&TEXT(Use_Library!$AO$20,"#,##0")&" households in 3 mi. ","")&IF(AND(Use_Library!$AP$20>0,Parcel!$C$21>Use_Library!$AP$20),"Over "&Use_Library!$AP$20&" mi to highway. ","")&IF(AND(Use_Library!$AQ$20="Y",Parcel!$C$22<>"Y"),"Needs a corner. ","")&IF(AND(Use_Library!$AR$20>0,Parcel!$C$23>Use_Library!$AR$20),"Over "&Use_Library!$AR$20&" mi to substation. ","")) | N21: =IF(M21="",1,0) -> 1 | O21: =IF(D21>=Use_Library!$L$20,1,0) -> 1 | P21: =IF(Use_Library!$F$20>0,G21*Use_Library!$F$20,1000000000) -> 124.8 | Q21: =IF(Use_Library!$G$20>0,E21*43560/Use_Library!$G$20,1000000000) -> 1000000000 | R21: =IF(AND(Use_Library!$H$20="Y",Parcel!$C$28=0),E21*(1-Assumptions!$C$8)/IF(Parcel!$C$27=1,Assumptions!$C$9,Assumptions!$C$10),1000000000) -> 1000000000 | S21: =IF(K21*L21*O21*N21=0,0,IF(MIN(P21,Q21,R21)>=1000000000,E21,IF(Use_Library!$E$20="Y",INT(MIN(P21,Q21,R21)),MIN(P21,Q21,R21)))) -> 0 | T21: =IF(N21=0,"Location fails",IF(O21=0,"Too small - needs "&Use_Library!$L$20&" usable ac",IF(K21=0,"Needs public sewer",IF(L21=0,"Needs public water",IF(R21<=MIN(P21,Q21),"Septic lot size",IF(Q21<=P21,"Site area / parking","Density")))))) -> Needs public sewer | U21: =IF(S21>0,1,0) -> 0 | V21: =IF(Use_Library!$K$20="Y",1,0)*U21 -> 0 | W21: =S21*Use_Library!$O$20*V21 -> 0 | X21: =S21*Use_Library!$P$20*V21 -> 0 | Y21: =IF(Parcel!$C$27=1,W21+Parcel!$C$29,0)*V21 -> 0 | Z21: =S21*Use_Library!$Q$20*Parcel!$C$27*V21 -> 0 | AA21: =IF(Parcel!$C$28=1,W21+Parcel!$C$30,0)*V21 -> 0 | AB21: =S21*Use_Library!$Q$20*Parcel!$C$28*V21 -> 0 | AC21: =IF(Parcel!$C$28=0,S21*Use_Library!$R$20,0)*V21 -> 0 | AD21: =IF(Parcel!$C$27=0,S21*Use_Library!$R$20,0)*V21 -> 0 | AE21: =I21*Parcel!$C$11*V21 -> 0 | AF21: =I21*V21 -> 0 | AG21: =IF(Use_Library!$C$20="For-Sale",IF(Use_Library!$E$20="Y",S21,1),1)*U21 -> 0 | AH21: =Cost_Library!$G$5*Parcel!$C$32*U21 -> 0 | AI21: =AG21*Cost_Library!$G$6*Parcel!$C$32 -> 0 | AJ21: =I21*Cost_Library!$G$7*Parcel!$C$32*V21 -> 0 | AK21: =Cost_Library!$G$8*Parcel!$C$32*V21 -> 0 | AL21: =AC21*Cost_Library!$G$9*Parcel!$C$32 -> 0 | AM21: =Cost_Library!$G$10*U21 -> 0 | AN21: =Cost_Library!$G$11*Parcel!$C$32*V21 -> 0 | AO21: =Use_Library!$S$20*U21 -> 0 | AP21: =Cost_Library!$G$12*U21 -> 0 | AQ21: =AE21*Cost_Library!$G$13*Parcel!$C$32 -> 0 | AR21: =AF21*Cost_Library!$G$14*Parcel!$C$32*Parcel!$C$33 -> 0 | AS21: =W21*Cost_Library!$G$15*Parcel!$C$32 -> 0 | AT21: =X21*Cost_Library!$G$16*Parcel!$C$32 -> 0 | AU21: =H21*Cost_Library!$G$17*Parcel!$C$32*V21 -> 0 | AV21: =G21*Cost_Library!$G$18*Parcel!$C$32*V21 -> 0 | AW21: =Y21*Cost_Library!$G$19*Parcel!$C$32 -> 0 | AX21: =Z21*Cost_Library!$G$20 -> 0 | AY21: =AA21*Cost_Library!$G$21*Parcel!$C$32 -> 0 | AZ21: =AB21*Cost_Library!$G$22 -> 0 | BA21: =AC21*Cost_Library!$G$23*Parcel!$C$32*Parcel!$C$34 -> 0 | BB21: =AD21*Cost_Library!$G$24*Parcel!$C$32 -> 0 | BC21: =W21*Cost_Library!$G$25*Parcel!$C$32 -> 0 | BD21: =SUM(AH21:BC21) -> 0 | BE21: =BD21*Assumptions!$C$11 -> 0 | BF21: =BD21+BE21 -> 0 | BG21: =S21*Use_Library!$T$20 -> 0 | BH21: =BG21*(Assumptions!$C$12+Assumptions!$C$13) -> 0 | BI21: =S21*Use_Library!$AC$20 -> 0 | BJ21: =1+Assumptions!$C$14+Assumptions!$C$15*Use_Library!$AH$20/12 -> 1.045 | BK21: =1+Assumptions!$C$21*(Assumptions!$C$22*Use_Library!$AH$20/12*Assumptions!$C$24+Assumptions!$C$23) -> 1.038675 | BL21: =1+Assumptions!$C$21*(Assumptions!$C$22*(Use_Library!$AH$20/12*Assumptions!$C$24+IF(Use_Library!$C$20="Income",Use_Library!$AD$20,0)/12*Assumptions!$C$25)+Assumptions!$C$23) -> 1.0533 | BM21: =J21*Assumptions!$C$31*(1-Assumptions!$C$17)*U21 -> 0 | BN21: =IF(Use_Library!$AJ$20=1,IF(Use_Library!$C$20="For-Sale",S21*Use_Library!$U$20,E21*Use_Library!$AF$20)*(1-Assumptions!$C$17)+BM21,0)*U21 -> 0 | BO21: =(BD21-AT21)*(1+Assumptions!$C$11) -> 0 | BP21: =BJ21*BK21 -> 1.0854154 | BQ21: =(Parcel!$C$18*BJ21+BO21)*BK21 -> 325624.61 | BR21: =BN21-BQ21 -> -325624.61 | BS21: =IF(AND(Use_Library!$AJ$20=1,U21=1),MAX(0,((1-Use_Library!$AI$20)*BN21-BO21*BK21)/BP21),0) -> 0 | BT21: =BF21+BG21+BH21+BI21 -> 0 | BU21: =BJ21*BL21 -> 1.1006985 | BV21: =(Parcel!$C$18*BJ21+BT21)*BL21 -> 330209.55 | BW21: =IF(Use_Library!$C$20="Income",S21*Use_Library!$W$20,0) -> 0 | BX21: =BW21*(1+Use_Library!$X$20)*(1-Use_Library!$Y$20) -> 0 | BY21: =IF(Use_Library!$C$20="Income",S21*Use_Library!$Z$20,0) -> 0 | BZ21: =IF(Use_Library!$C$20="Income",Assumptions!$C$19*Assumptions!$C$20*BV21,0) -> 6174.9186 | CA21: =BX21*Use_Library!$AA$20 -> 0 | CB21: =(BY21+BZ21)*Use_Library!$AB$20 -> 308.74593 | CC21: =BX21-BY21-BZ21-CA21+CB21 -> -5866.1727 | CD21: =IF(AND(Use_Library!$C$20="Income",Use_Library!$AE$20>0),CC21/Use_Library!$AE$20,0) -> -93858.762 | CE21: =IF(Use_Library!$C$20="Income",-Assumptions!$C$19*Assumptions!$C$20*(1-Use_Library!$AB$20)*BU21,0) -> -0.019553909 | CF21: =IF(BV21=0,0,CC21/BV21) -> -0.017765 | CG21: =IF(Use_Library!$AK$20=1,IF(Use_Library!$C$20="Income",CD21*(1-Assumptions!$C$18),S21*Use_Library!$V$20*(1-Assumptions!$C$16))+BM21,0)*U21 -> 0 | CH21: =IF(AND(Use_Library!$AK$20=1,Use_Library!$C$20="Income",Use_Library!$AE$20>0),CE21/Use_Library!$AE$20*(1-Assumptions!$C$18),0) -> -0.30660529 | CI21: =CG21-BV21 -> -330209.55 | CJ21: =IF(AND(Use_Library!$AK$20=1,U21=1),MAX(0,Parcel!$C$18-((1-Use_Library!$AI$20)*CG21-BV21)/((1-Use_Library!$AI$20)*CH21-BU21)),0) -> 0 | CK21: =IF(Use_Library!$AL$20=1,IF(Use_Library!$C$20="Income",CD21,IF(Use_Library!$AE$20>0,E21*Use_Library!$AG$20/Use_Library!$AE$20,0))+BM21,0)*U21 -> 0 | CL21: =IF(Use_Library!$C$20="Income",BT21,BF21) -> 0 | CM21: =IF(Use_Library!$C$20="Income",BU21,BJ21*BK21) -> 1.1006985 | CN21: =IF(Use_Library!$C$20="Income",BV21,(Parcel!$C$18*BJ21+BF21)*BK21) -> 330209.55 | CO21: =IF(AND(Use_Library!$AL$20=1,Use_Library!$C$20="Income",Use_Library!$AE$20>0),CE21/Use_Library!$AE$20,0) -> -0.31286254 | CP21: =CK21-CN21 -> -330209.55 | CQ21: =IF(AND(Use_Library!$AL$20=1,U21=1),MAX(0,Parcel!$C$18-((1-Use_Library!$AI$20)*CK21-CN21)/((1-Use_Library!$AI$20)*CO21-CM21)),0) -> 0 | CR21: =IF(Use_Library!$C$20="Income",Assumptions!$C$21*(Parcel!$C$18*BJ21+BT21),0) -> 203775 | CS21: =IF(AND(Use_Library!$C$20="Income",CC21>0),MIN(Assumptions!$C$26*CD21,PV(Assumptions!$C$29/12,Assumptions!$C$30*12,-CC21/Assumptions!$C$27/12),CC21/Assumptions!$C$28),0) -> 0 | CT21: =IF(CS21=0,0,CC21/(-PMT(Assumptions!$C$29/12,Assumptions!$C$30*12,CS21)*12)) -> 0 | CU21: =CS21-CR21 -> -203775 | CV21: =MAX(BS21,CJ21,CQ21) -> 0 | CW21: =IF(CV21<=0,"None works",IF(BS21=CV21,"Land / pad sale",IF(CJ21=CV21,"Build & sell","Build & hold / lease"))) -> None works | CX21: =CV21*(1-Assumptions!$C$32) -> 0 | CY21: =CV21-Parcel!$C$18 -> -300000 | CZ21: =IF(Parcel!$C$8=0,0,CV21/Parcel!$C$8) -> 0 | DA21: =IF(S21=0,0,CV21/S21) -> 0 | DB21: =TRIM(M21&" "&IF(AND(U21=0,N21=1),"Nothing fits. ","")&IF(Parcel!$C$12<Use_Library!$AM$20,"Frontage under "&Use_Library!$AM$20&" LF. ","")&IF(Parcel!$C$10>0.15,"Slope over 15%. ","")&IF(AND(U21=1,Use_Library!$M$20>0,D21>Use_Library!$M$20),"Only "&Use_Library!$M$20&" ac used - rest resold. ","")) -> Nothing fits. | DC21: =CV21+ROW()/1000000 -> 2.1e-05
A22: =Use_Library!$A$21 -> Tiny-home long-term rental community | B22: =Use_Library!$C$21 -> Income | C22: =Use_Library!$D$21 -> home | D22: =MAX(0,Parcel!$C$26*(1-Use_Library!$N$21-Assumptions!$C$7)) -> 14.196 | E22: =IF(Use_Library!$M$21>0,MIN(D22,Use_Library!$M$21),D22) -> 14.196 | F22: =IF(D22=0,0,E22/D22) -> 1 | G22: =Parcel!$C$26*F22 -> 15.6 | H22: =G22*Assumptions!$C$7 -> 0.624 | I22: =G22*(1-Use_Library!$N$21) -> 14.82 | J22: =Parcel!$C$8*(1-F22) -> 0 | K22: =IF(AND(Use_Library!$I$21="Y",Parcel!$C$28=0),0,1) -> 1 | L22: =IF(AND(Use_Library!$J$21="Y",Parcel!$C$27=0),0,1) -> 1 | M22: =TRIM(IF(AND(Use_Library!$AN$21>0,Parcel!$C$19<Use_Library!$AN$21),"Traffic under "&TEXT(Use_Library!$AN$21,"#,##0")&" VPD. ","")&IF(AND(Use_Library!$AO$21>0,Parcel!$C$20<Use_Library!$AO$21),"Under "&TEXT(Use_Library!$AO$21,"#,##0")&" households in 3 mi. ","")&IF(AND(Use_Library!$AP$21>0,Parcel!$C$21>Use_Library!$AP$21),"Over "&Use_Library!$AP$21&" mi to highway. ","")&IF(AND(Use_Library!$AQ$21="Y",Parcel!$C$22<>"Y"),"Needs a corner. ","")&IF(AND(Use_Library!$AR$21>0,Parcel!$C$23>Use_Library!$AR$21),"Over "&Use_Library!$AR$21&" mi to substation. ","")) | N22: =IF(M22="",1,0) -> 1 | O22: =IF(D22>=Use_Library!$L$21,1,0) -> 1 | P22: =IF(Use_Library!$F$21>0,G22*Use_Library!$F$21,1000000000) -> 156 | Q22: =IF(Use_Library!$G$21>0,E22*43560/Use_Library!$G$21,1000000000) -> 1000000000 | R22: =IF(AND(Use_Library!$H$21="Y",Parcel!$C$28=0),E22*(1-Assumptions!$C$8)/IF(Parcel!$C$27=1,Assumptions!$C$9,Assumptions!$C$10),1000000000) -> 1000000000 | S22: =IF(K22*L22*O22*N22=0,0,IF(MIN(P22,Q22,R22)>=1000000000,E22,IF(Use_Library!$E$21="Y",INT(MIN(P22,Q22,R22)),MIN(P22,Q22,R22)))) -> 156 | T22: =IF(N22=0,"Location fails",IF(O22=0,"Too small - needs "&Use_Library!$L$21&" usable ac",IF(K22=0,"Needs public sewer",IF(L22=0,"Needs public water",IF(R22<=MIN(P22,Q22),"Septic lot size",IF(Q22<=P22,"Site area / parking","Density")))))) -> Density | U22: =IF(S22>0,1,0) -> 1 | V22: =IF(Use_Library!$K$21="Y",1,0)*U22 -> 1 | W22: =S22*Use_Library!$O$21*V22 -> 3900 | X22: =S22*Use_Library!$P$21*V22 -> 0 | Y22: =IF(Parcel!$C$27=1,W22+Parcel!$C$29,0)*V22 -> 3900 | Z22: =S22*Use_Library!$Q$21*Parcel!$C$27*V22 -> 156 | AA22: =IF(Parcel!$C$28=1,W22+Parcel!$C$30,0)*V22 -> 0 | AB22: =S22*Use_Library!$Q$21*Parcel!$C$28*V22 -> 0 | AC22: =IF(Parcel!$C$28=0,S22*Use_Library!$R$21,0)*V22 -> 39 | AD22: =IF(Parcel!$C$27=0,S22*Use_Library!$R$21,0)*V22 -> 0 | AE22: =I22*Parcel!$C$11*V22 -> 5.187 | AF22: =I22*V22 -> 14.82 | AG22: =IF(Use_Library!$C$21="For-Sale",IF(Use_Library!$E$21="Y",S22,1),1)*U22 -> 1 | AH22: =Cost_Library!$G$5*Parcel!$C$32*U22 -> 6500 | AI22: =AG22*Cost_Library!$G$6*Parcel!$C$32 -> 900 | AJ22: =I22*Cost_Library!$G$7*Parcel!$C$32*V22 -> 74100 | AK22: =Cost_Library!$G$8*Parcel!$C$32*V22 -> 5000 | AL22: =AC22*Cost_Library!$G$9*Parcel!$C$32 -> 19500 | AM22: =Cost_Library!$G$10*U22 -> 2800 | AN22: =Cost_Library!$G$11*Parcel!$C$32*V22 -> 7500 | AO22: =Use_Library!$S$21*U22 -> 25000 | AP22: =Cost_Library!$G$12*U22 -> 10000 | AQ22: =AE22*Cost_Library!$G$13*Parcel!$C$32 -> 20748 | AR22: =AF22*Cost_Library!$G$14*Parcel!$C$32*Parcel!$C$33 -> 74100 | AS22: =W22*Cost_Library!$G$15*Parcel!$C$32 -> 585000 | AT22: =X22*Cost_Library!$G$16*Parcel!$C$32 -> 0 | AU22: =H22*Cost_Library!$G$17*Parcel!$C$32*V22 -> 34320 | AV22: =G22*Cost_Library!$G$18*Parcel!$C$32*V22 -> 10920 | AW22: =Y22*Cost_Library!$G$19*Parcel!$C$32 -> 195000 | AX22: =Z22*Cost_Library!$G$20 -> 390000 | AY22: =AA22*Cost_Library!$G$21*Parcel!$C$32 -> 0 | AZ22: =AB22*Cost_Library!$G$22 -> 0 | BA22: =AC22*Cost_Library!$G$23*Parcel!$C$32*Parcel!$C$34 -> 514800 | BB22: =AD22*Cost_Library!$G$24*Parcel!$C$32 -> 0 | BC22: =W22*Cost_Library!$G$25*Parcel!$C$32 -> 97500 | BD22: =SUM(AH22:BC22) -> 2073688 | BE22: =BD22*Assumptions!$C$11 -> 207368.8 | BF22: =BD22+BE22 -> 2281056.8 | BG22: =S22*Use_Library!$T$21 -> 13260000 | BH22: =BG22*(Assumptions!$C$12+Assumptions!$C$13) -> 1723800 | BI22: =S22*Use_Library!$AC$21 -> 0 | BJ22: =1+Assumptions!$C$14+Assumptions!$C$15*Use_Library!$AH$21/12 -> 1.045 | BK22: =1+Assumptions!$C$21*(Assumptions!$C$22*Use_Library!$AH$21/12*Assumptions!$C$24+Assumptions!$C$23) -> 1.038675 | BL22: =1+Assumptions!$C$21*(Assumptions!$C$22*(Use_Library!$AH$21/12*Assumptions!$C$24+IF(Use_Library!$C$21="Income",Use_Library!$AD$21,0)/12*Assumptions!$C$25)+Assumptions!$C$23) -> 1.0606125 | BM22: =J22*Assumptions!$C$31*(1-Assumptions!$C$17)*U22 -> 0 | BN22: =IF(Use_Library!$AJ$21=1,IF(Use_Library!$C$21="For-Sale",S22*Use_Library!$U$21,E22*Use_Library!$AF$21)*(1-Assumptions!$C$17)+BM22,0)*U22 -> 545126.4 | BO22: =(BD22-AT22)*(1+Assumptions!$C$11) -> 2281056.8 | BP22: =BJ22*BK22 -> 1.0854154 | BQ22: =(Parcel!$C$18*BJ22+BO22)*BK22 -> 2694901.3 | BR22: =BN22-BQ22 -> -2149774.9 | BS22: =IF(AND(Use_Library!$AJ$21=1,U22=1),MAX(0,((1-Use_Library!$AI$21)*BN22-BO22*BK22)/BP22),0) -> 0 | BT22: =BF22+BG22+BH22+BI22 -> 17264857 | BU22: =BJ22*BL22 -> 1.1083401 | BV22: =(Parcel!$C$18*BJ22+BT22)*BL22 -> 18643825 | BW22: =IF(Use_Library!$C$21="Income",S22*Use_Library!$W$21,0) -> 2059200 | BX22: =BW22*(1+Use_Library!$X$21)*(1-Use_Library!$Y$21) -> 1972507.7 | BY22: =IF(Use_Library!$C$21="Income",S22*Use_Library!$Z$21,0) -> 390000 | BZ22: =IF(Use_Library!$C$21="Income",Assumptions!$C$19*Assumptions!$C$20*BV22,0) -> 348639.53 | CA22: =BX22*Use_Library!$AA$21 -> 157800.61 | CB22: =(BY22+BZ22)*Use_Library!$AB$21 -> 36931.976 | CC22: =BX22-BY22-BZ22-CA22+CB22 -> 1112999.5 | CD22: =IF(AND(Use_Library!$C$21="Income",Use_Library!$AE$21>0),CC22/Use_Library!$AE$21,0) -> 16488882 | CE22: =IF(Use_Library!$C$21="Income",-Assumptions!$C$19*Assumptions!$C$20*(1-Use_Library!$AB$21)*BU22,0) -> -0.019689661 | CF22: =IF(BV22=0,0,CC22/BV22) -> 0.059698024 | CG22: =IF(Use_Library!$AK$21=1,IF(Use_Library!$C$21="Income",CD22*(1-Assumptions!$C$18),S22*Use_Library!$V$21*(1-Assumptions!$C$16))+BM22,0)*U22 -> 16159104 | CH22: =IF(AND(Use_Library!$AK$21=1,Use_Library!$C$21="Income",Use_Library!$AE$21>0),CE22/Use_Library!$AE$21*(1-Assumptions!$C$18),0) -> -0.28586471 | CI22: =CG22-BV22 -> -2484720.9 | CJ22: =IF(AND(Use_Library!$AK$21=1,U22=1),MAX(0,Parcel!$C$18-((1-Use_Library!$AI$21)*CG22-BV22)/((1-Use_Library!$AI$21)*CH22-BU22)),0) -> 0 | CK22: =IF(Use_Library!$AL$21=1,IF(Use_Library!$C$21="Income",CD22,IF(Use_Library!$AE$21>0,E22*Use_Library!$AG$21/Use_Library!$AE$21,0))+BM22,0)*U22 -> 16488882 | CL22: =IF(Use_Library!$C$21="Income",BT22,BF22) -> 17264857 | CM22: =IF(Use_Library!$C$21="Income",BU22,BJ22*BK22) -> 1.1083401 | CN22: =IF(Use_Library!$C$21="Income",BV22,(Parcel!$C$18*BJ22+BF22)*BK22) -> 18643825 | CO22: =IF(AND(Use_Library!$AL$21=1,Use_Library!$C$21="Income",Use_Library!$AE$21>0),CE22/Use_Library!$AE$21,0) -> -0.29169868 | CP22: =CK22-CN22 -> -2154943.2 | CQ22: =IF(AND(Use_Library!$AL$21=1,U22=1),MAX(0,Parcel!$C$18-((1-Use_Library!$AI$21)*CK22-CN22)/((1-Use_Library!$AI$21)*CO22-CM22)),0) -> 0 | CR22: =IF(Use_Library!$C$21="Income",Assumptions!$C$21*(Parcel!$C$18*BJ22+BT22),0) -> 11425932 | CS22: =IF(AND(Use_Library!$C$21="Income",CC22>0),MIN(Assumptions!$C$26*CD22,PV(Assumptions!$C$29/12,Assumptions!$C$30*12,-CC22/Assumptions!$C$27/12),CC22/Assumptions!$C$28),0) -> 11381669 | CT22: =IF(CS22=0,0,CC22/(-PMT(Assumptions!$C$29/12,Assumptions!$C$30*12,CS22)*12)) -> 1.25 | CU22: =CS22-CR22 -> -44262.821 | CV22: =MAX(BS22,CJ22,CQ22) -> 0 | CW22: =IF(CV22<=0,"None works",IF(BS22=CV22,"Land / pad sale",IF(CJ22=CV22,"Build & sell","Build & hold / lease"))) -> None works | CX22: =CV22*(1-Assumptions!$C$32) -> 0 | CY22: =CV22-Parcel!$C$18 -> -300000 | CZ22: =IF(Parcel!$C$8=0,0,CV22/Parcel!$C$8) -> 0 | DA22: =IF(S22=0,0,CV22/S22) -> 0 | DB22: =TRIM(M22&" "&IF(AND(U22=0,N22=1),"Nothing fits. ","")&IF(Parcel!$C$12<Use_Library!$AM$21,"Frontage under "&Use_Library!$AM$21&" LF. ","")&IF(Parcel!$C$10>0.15,"Slope over 15%. ","")&IF(AND(U22=1,Use_Library!$M$21>0,D22>Use_Library!$M$21),"Only "&Use_Library!$M$21&" ac used - rest resold. ","")) | DC22: =CV22+ROW()/1000000 -> 2.2e-05
A23: =Use_Library!$A$22 -> Build-to-rent cottages | B23: =Use_Library!$C$22 -> Income | C23: =Use_Library!$D$22 -> home | D23: =MAX(0,Parcel!$C$26*(1-Use_Library!$N$22-Assumptions!$C$7)) -> 14.196 | E23: =IF(Use_Library!$M$22>0,MIN(D23,Use_Library!$M$22),D23) -> 14.196 | F23: =IF(D23=0,0,E23/D23) -> 1 | G23: =Parcel!$C$26*F23 -> 15.6 | H23: =G23*Assumptions!$C$7 -> 0.624 | I23: =G23*(1-Use_Library!$N$22) -> 14.82 | J23: =Parcel!$C$8*(1-F23) -> 0 | K23: =IF(AND(Use_Library!$I$22="Y",Parcel!$C$28=0),0,1) -> 0 | L23: =IF(AND(Use_Library!$J$22="Y",Parcel!$C$27=0),0,1) -> 1 | M23: =TRIM(IF(AND(Use_Library!$AN$22>0,Parcel!$C$19<Use_Library!$AN$22),"Traffic under "&TEXT(Use_Library!$AN$22,"#,##0")&" VPD. ","")&IF(AND(Use_Library!$AO$22>0,Parcel!$C$20<Use_Library!$AO$22),"Under "&TEXT(Use_Library!$AO$22,"#,##0")&" households in 3 mi. ","")&IF(AND(Use_Library!$AP$22>0,Parcel!$C$21>Use_Library!$AP$22),"Over "&Use_Library!$AP$22&" mi to highway. ","")&IF(AND(Use_Library!$AQ$22="Y",Parcel!$C$22<>"Y"),"Needs a corner. ","")&IF(AND(Use_Library!$AR$22>0,Parcel!$C$23>Use_Library!$AR$22),"Over "&Use_Library!$AR$22&" mi to substation. ","")) | N23: =IF(M23="",1,0) -> 1 | O23: =IF(D23>=Use_Library!$L$22,1,0) -> 1 | P23: =IF(Use_Library!$F$22>0,G23*Use_Library!$F$22,1000000000) -> 124.8 | Q23: =IF(Use_Library!$G$22>0,E23*43560/Use_Library!$G$22,1000000000) -> 1000000000 | R23: =IF(AND(Use_Library!$H$22="Y",Parcel!$C$28=0),E23*(1-Assumptions!$C$8)/IF(Parcel!$C$27=1,Assumptions!$C$9,Assumptions!$C$10),1000000000) -> 1000000000 | S23: =IF(K23*L23*O23*N23=0,0,IF(MIN(P23,Q23,R23)>=1000000000,E23,IF(Use_Library!$E$22="Y",INT(MIN(P23,Q23,R23)),MIN(P23,Q23,R23)))) -> 0 | T23: =IF(N23=0,"Location fails",IF(O23=0,"Too small - needs "&Use_Library!$L$22&" usable ac",IF(K23=0,"Needs public sewer",IF(L23=0,"Needs public water",IF(R23<=MIN(P23,Q23),"Septic lot size",IF(Q23<=P23,"Site area / parking","Density")))))) -> Needs public sewer | U23: =IF(S23>0,1,0) -> 0 | V23: =IF(Use_Library!$K$22="Y",1,0)*U23 -> 0 | W23: =S23*Use_Library!$O$22*V23 -> 0 | X23: =S23*Use_Library!$P$22*V23 -> 0 | Y23: =IF(Parcel!$C$27=1,W23+Parcel!$C$29,0)*V23 -> 0 | Z23: =S23*Use_Library!$Q$22*Parcel!$C$27*V23 -> 0 | AA23: =IF(Parcel!$C$28=1,W23+Parcel!$C$30,0)*V23 -> 0 | AB23: =S23*Use_Library!$Q$22*Parcel!$C$28*V23 -> 0 | AC23: =IF(Parcel!$C$28=0,S23*Use_Library!$R$22,0)*V23 -> 0 | AD23: =IF(Parcel!$C$27=0,S23*Use_Library!$R$22,0)*V23 -> 0 | AE23: =I23*Parcel!$C$11*V23 -> 0 | AF23: =I23*V23 -> 0 | AG23: =IF(Use_Library!$C$22="For-Sale",IF(Use_Library!$E$22="Y",S23,1),1)*U23 -> 0 | AH23: =Cost_Library!$G$5*Parcel!$C$32*U23 -> 0 | AI23: =AG23*Cost_Library!$G$6*Parcel!$C$32 -> 0 | AJ23: =I23*Cost_Library!$G$7*Parcel!$C$32*V23 -> 0 | AK23: =Cost_Library!$G$8*Parcel!$C$32*V23 -> 0 | AL23: =AC23*Cost_Library!$G$9*Parcel!$C$32 -> 0 | AM23: =Cost_Library!$G$10*U23 -> 0 | AN23: =Cost_Library!$G$11*Parcel!$C$32*V23 -> 0 | AO23: =Use_Library!$S$22*U23 -> 0 | AP23: =Cost_Library!$G$12*U23 -> 0 | AQ23: =AE23*Cost_Library!$G$13*Parcel!$C$32 -> 0 | AR23: =AF23*Cost_Library!$G$14*Parcel!$C$32*Parcel!$C$33 -> 0 | AS23: =W23*Cost_Library!$G$15*Parcel!$C$32 -> 0 | AT23: =X23*Cost_Library!$G$16*Parcel!$C$32 -> 0 | AU23: =H23*Cost_Library!$G$17*Parcel!$C$32*V23 -> 0 | AV23: =G23*Cost_Library!$G$18*Parcel!$C$32*V23 -> 0 | AW23: =Y23*Cost_Library!$G$19*Parcel!$C$32 -> 0 | AX23: =Z23*Cost_Library!$G$20 -> 0 | AY23: =AA23*Cost_Library!$G$21*Parcel!$C$32 -> 0 | AZ23: =AB23*Cost_Library!$G$22 -> 0 | BA23: =AC23*Cost_Library!$G$23*Parcel!$C$32*Parcel!$C$34 -> 0 | BB23: =AD23*Cost_Library!$G$24*Parcel!$C$32 -> 0 | BC23: =W23*Cost_Library!$G$25*Parcel!$C$32 -> 0 | BD23: =SUM(AH23:BC23) -> 0 | BE23: =BD23*Assumptions!$C$11 -> 0 | BF23: =BD23+BE23 -> 0 | BG23: =S23*Use_Library!$T$22 -> 0 | BH23: =BG23*(Assumptions!$C$12+Assumptions!$C$13) -> 0 | BI23: =S23*Use_Library!$AC$22 -> 0 | BJ23: =1+Assumptions!$C$14+Assumptions!$C$15*Use_Library!$AH$22/12 -> 1.0533333 | BK23: =1+Assumptions!$C$21*(Assumptions!$C$22*Use_Library!$AH$22/12*Assumptions!$C$24+Assumptions!$C$23) -> 1.0494 | BL23: =1+Assumptions!$C$21*(Assumptions!$C$22*(Use_Library!$AH$22/12*Assumptions!$C$24+IF(Use_Library!$C$22="Income",Use_Library!$AD$22,0)/12*Assumptions!$C$25)+Assumptions!$C$23) -> 1.07865 | BM23: =J23*Assumptions!$C$31*(1-Assumptions!$C$17)*U23 -> 0 | BN23: =IF(Use_Library!$AJ$22=1,IF(Use_Library!$C$22="For-Sale",S23*Use_Library!$U$22,E23*Use_Library!$AF$22)*(1-Assumptions!$C$17)+BM23,0)*U23 -> 0 | BO23: =(BD23-AT23)*(1+Assumptions!$C$11) -> 0 | BP23: =BJ23*BK23 -> 1.105368 | BQ23: =(Parcel!$C$18*BJ23+BO23)*BK23 -> 331610.4 | BR23: =BN23-BQ23 -> -331610.4 | BS23: =IF(AND(Use_Library!$AJ$22=1,U23=1),MAX(0,((1-Use_Library!$AI$22)*BN23-BO23*BK23)/BP23),0) -> 0 | BT23: =BF23+BG23+BH23+BI23 -> 0 | BU23: =BJ23*BL23 -> 1.136178 | BV23: =(Parcel!$C$18*BJ23+BT23)*BL23 -> 340853.4 | BW23: =IF(Use_Library!$C$22="Income",S23*Use_Library!$W$22,0) -> 0 | BX23: =BW23*(1+Use_Library!$X$22)*(1-Use_Library!$Y$22) -> 0 | BY23: =IF(Use_Library!$C$22="Income",S23*Use_Library!$Z$22,0) -> 0 | BZ23: =IF(Use_Library!$C$22="Income",Assumptions!$C$19*Assumptions!$C$20*BV23,0) -> 6373.9586 | CA23: =BX23*Use_Library!$AA$22 -> 0 | CB23: =(BY23+BZ23)*Use_Library!$AB$22 -> 318.69793 | CC23: =BX23-BY23-BZ23-CA23+CB23 -> -6055.2607 | CD23: =IF(AND(Use_Library!$C$22="Income",Use_Library!$AE$22>0),CC23/Use_Library!$AE$22,0) -> -105308.88 | CE23: =IF(Use_Library!$C$22="Income",-Assumptions!$C$19*Assumptions!$C$20*(1-Use_Library!$AB$22)*BU23,0) -> -0.020184202 | CF23: =IF(BV23=0,0,CC23/BV23) -> -0.017765 | CG23: =IF(Use_Library!$AK$22=1,IF(Use_Library!$C$22="Income",CD23*(1-Assumptions!$C$18),S23*Use_Library!$V$22*(1-Assumptions!$C$16))+BM23,0)*U23 -> 0 | CH23: =IF(AND(Use_Library!$AK$22=1,Use_Library!$C$22="Income",Use_Library!$AE$22>0),CE23/Use_Library!$AE$22*(1-Assumptions!$C$18),0) -> -0.34400901 | CI23: =CG23-BV23 -> -340853.4 | CJ23: =IF(AND(Use_Library!$AK$22=1,U23=1),MAX(0,Parcel!$C$18-((1-Use_Library!$AI$22)*CG23-BV23)/((1-Use_Library!$AI$22)*CH23-BU23)),0) -> 0 | CK23: =IF(Use_Library!$AL$22=1,IF(Use_Library!$C$22="Income",CD23,IF(Use_Library!$AE$22>0,E23*Use_Library!$AG$22/Use_Library!$AE$22,0))+BM23,0)*U23 -> 0 | CL23: =IF(Use_Library!$C$22="Income",BT23,BF23) -> 0 | CM23: =IF(Use_Library!$C$22="Income",BU23,BJ23*BK23) -> 1.136178 | CN23: =IF(Use_Library!$C$22="Income",BV23,(Parcel!$C$18*BJ23+BF23)*BK23) -> 340853.4 | CO23: =IF(AND(Use_Library!$AL$22=1,Use_Library!$C$22="Income",Use_Library!$AE$22>0),CE23/Use_Library!$AE$22,0) -> -0.3510296 | CP23: =CK23-CN23 -> -340853.4 | CQ23: =IF(AND(Use_Library!$AL$22=1,U23=1),MAX(0,Parcel!$C$18-((1-Use_Library!$AI$22)*CK23-CN23)/((1-Use_Library!$AI$22)*CO23-CM23)),0) -> 0 | CR23: =IF(Use_Library!$C$22="Income",Assumptions!$C$21*(Parcel!$C$18*BJ23+BT23),0) -> 205400 | CS23: =IF(AND(Use_Library!$C$22="Income",CC23>0),MIN(Assumptions!$C$26*CD23,PV(Assumptions!$C$29/12,Assumptions!$C$30*12,-CC23/Assumptions!$C$27/12),CC23/Assumptions!$C$28),0) -> 0 | CT23: =IF(CS23=0,0,CC23/(-PMT(Assumptions!$C$29/12,Assumptions!$C$30*12,CS23)*12)) -> 0 | CU23: =CS23-CR23 -> -205400 | CV23: =MAX(BS23,CJ23,CQ23) -> 0 | CW23: =IF(CV23<=0,"None works",IF(BS23=CV23,"Land / pad sale",IF(CJ23=CV23,"Build & sell","Build & hold / lease"))) -> None works | CX23: =CV23*(1-Assumptions!$C$32) -> 0 | CY23: =CV23-Parcel!$C$18 -> -300000 | CZ23: =IF(Parcel!$C$8=0,0,CV23/Parcel!$C$8) -> 0 | DA23: =IF(S23=0,0,CV23/S23) -> 0 | DB23: =TRIM(M23&" "&IF(AND(U23=0,N23=1),"Nothing fits. ","")&IF(Parcel!$C$12<Use_Library!$AM$22,"Frontage under "&Use_Library!$AM$22&" LF. ","")&IF(Parcel!$C$10>0.15,"Slope over 15%. ","")&IF(AND(U23=1,Use_Library!$M$22>0,D23>Use_Library!$M$22),"Only "&Use_Library!$M$22&" ac used - rest resold. ","")) -> Nothing fits. | DC23: =CV23+ROW()/1000000 -> 2.3e-05
A24: =Use_Library!$A$23 -> Senior housing (assisted living / memory care) | B24: =Use_Library!$C$23 -> Operator Pad | C24: =Use_Library!$D$23 -> acre | D24: =MAX(0,Parcel!$C$26*(1-Use_Library!$N$23-Assumptions!$C$7)) -> 14.196 | E24: =IF(Use_Library!$M$23>0,MIN(D24,Use_Library!$M$23),D24) -> 6 | F24: =IF(D24=0,0,E24/D24) -> 0.42265427 | G24: =Parcel!$C$26*F24 -> 6.5934066 | H24: =G24*Assumptions!$C$7 -> 0.26373626 | I24: =G24*(1-Use_Library!$N$23) -> 6.2637363 | J24: =Parcel!$C$8*(1-F24) -> 11.546915 | K24: =IF(AND(Use_Library!$I$23="Y",Parcel!$C$28=0),0,1) -> 1 | L24: =IF(AND(Use_Library!$J$23="Y",Parcel!$C$27=0),0,1) -> 1 | M24: =TRIM(IF(AND(Use_Library!$AN$23>0,Parcel!$C$19<Use_Library!$AN$23),"Traffic under "&TEXT(Use_Library!$AN$23,"#,##0")&" VPD. ","")&IF(AND(Use_Library!$AO$23>0,Parcel!$C$20<Use_Library!$AO$23),"Under "&TEXT(Use_Library!$AO$23,"#,##0")&" households in 3 mi. ","")&IF(AND(Use_Library!$AP$23>0,Parcel!$C$21>Use_Library!$AP$23),"Over "&Use_Library!$AP$23&" mi to highway. ","")&IF(AND(Use_Library!$AQ$23="Y",Parcel!$C$22<>"Y"),"Needs a corner. ","")&IF(AND(Use_Library!$AR$23>0,Parcel!$C$23>Use_Library!$AR$23),"Over "&Use_Library!$AR$23&" mi to substation. ","")) -> Under 8,000 households in 3 mi. | N24: =IF(M24="",1,0) -> 0 | O24: =IF(D24>=Use_Library!$L$23,1,0) -> 1 | P24: =IF(Use_Library!$F$23>0,G24*Use_Library!$F$23,1000000000) -> 1000000000 | Q24: =IF(Use_Library!$G$23>0,E24*43560/Use_Library!$G$23,1000000000) -> 6 | R24: =IF(AND(Use_Library!$H$23="Y",Parcel!$C$28=0),E24*(1-Assumptions!$C$8)/IF(Parcel!$C$27=1,Assumptions!$C$9,Assumptions!$C$10),1000000000) -> 1000000000 | S24: =IF(K24*L24*O24*N24=0,0,IF(MIN(P24,Q24,R24)>=1000000000,E24,IF(Use_Library!$E$23="Y",INT(MIN(P24,Q24,R24)),MIN(P24,Q24,R24)))) -> 0 | T24: =IF(N24=0,"Location fails",IF(O24=0,"Too small - needs "&Use_Library!$L$23&" usable ac",IF(K24=0,"Needs public sewer",IF(L24=0,"Needs public water",IF(R24<=MIN(P24,Q24),"Septic lot size",IF(Q24<=P24,"Site area / parking","Density")))))) -> Location fails | U24: =IF(S24>0,1,0) -> 0 | V24: =IF(Use_Library!$K$23="Y",1,0)*U24 -> 0 | W24: =S24*Use_Library!$O$23*V24 -> 0 | X24: =S24*Use_Library!$P$23*V24 -> 0 | Y24: =IF(Parcel!$C$27=1,W24+Parcel!$C$29,0)*V24 -> 0 | Z24: =S24*Use_Library!$Q$23*Parcel!$C$27*V24 -> 0 | AA24: =IF(Parcel!$C$28=1,W24+Parcel!$C$30,0)*V24 -> 0 | AB24: =S24*Use_Library!$Q$23*Parcel!$C$28*V24 -> 0 | AC24: =IF(Parcel!$C$28=0,S24*Use_Library!$R$23,0)*V24 -> 0 | AD24: =IF(Parcel!$C$27=0,S24*Use_Library!$R$23,0)*V24 -> 0 | AE24: =I24*Parcel!$C$11*V24 -> 0 | AF24: =I24*V24 -> 0 | AG24: =IF(Use_Library!$C$23="For-Sale",IF(Use_Library!$E$23="Y",S24,1),1)*U24 -> 0 | AH24: =Cost_Library!$G$5*Parcel!$C$32*U24 -> 0 | AI24: =AG24*Cost_Library!$G$6*Parcel!$C$32 -> 0 | AJ24: =I24*Cost_Library!$G$7*Parcel!$C$32*V24 -> 0 | AK24: =Cost_Library!$G$8*Parcel!$C$32*V24 -> 0 | AL24: =AC24*Cost_Library!$G$9*Parcel!$C$32 -> 0 | AM24: =Cost_Library!$G$10*U24 -> 0 | AN24: =Cost_Library!$G$11*Parcel!$C$32*V24 -> 0 | AO24: =Use_Library!$S$23*U24 -> 0 | AP24: =Cost_Library!$G$12*U24 -> 0 | AQ24: =AE24*Cost_Library!$G$13*Parcel!$C$32 -> 0 | AR24: =AF24*Cost_Library!$G$14*Parcel!$C$32*Parcel!$C$33 -> 0 | AS24: =W24*Cost_Library!$G$15*Parcel!$C$32 -> 0 | AT24: =X24*Cost_Library!$G$16*Parcel!$C$32 -> 0 | AU24: =H24*Cost_Library!$G$17*Parcel!$C$32*V24 -> 0 | AV24: =G24*Cost_Library!$G$18*Parcel!$C$32*V24 -> 0 | AW24: =Y24*Cost_Library!$G$19*Parcel!$C$32 -> 0 | AX24: =Z24*Cost_Library!$G$20 -> 0 | AY24: =AA24*Cost_Library!$G$21*Parcel!$C$32 -> 0 | AZ24: =AB24*Cost_Library!$G$22 -> 0 | BA24: =AC24*Cost_Library!$G$23*Parcel!$C$32*Parcel!$C$34 -> 0 | BB24: =AD24*Cost_Library!$G$24*Parcel!$C$32 -> 0 | BC24: =W24*Cost_Library!$G$25*Parcel!$C$32 -> 0 | BD24: =SUM(AH24:BC24) -> 0 | BE24: =BD24*Assumptions!$C$11 -> 0 | BF24: =BD24+BE24 -> 0 | BG24: =S24*Use_Library!$T$23 -> 0 | BH24: =BG24*(Assumptions!$C$12+Assumptions!$C$13) -> 0 | BI24: =S24*Use_Library!$AC$23 -> 0 | BJ24: =1+Assumptions!$C$14+Assumptions!$C$15*Use_Library!$AH$23/12 -> 1.045 | BK24: =1+Assumptions!$C$21*(Assumptions!$C$22*Use_Library!$AH$23/12*Assumptions!$C$24+Assumptions!$C$23) -> 1.038675 | BL24: =1+Assumptions!$C$21*(Assumptions!$C$22*(Use_Library!$AH$23/12*Assumptions!$C$24+IF(Use_Library!$C$23="Income",Use_Library!$AD$23,0)/12*Assumptions!$C$25)+Assumptions!$C$23) -> 1.038675 | BM24: =J24*Assumptions!$C$31*(1-Assumptions!$C$17)*U24 -> 0 | BN24: =IF(Use_Library!$AJ$23=1,IF(Use_Library!$C$23="For-Sale",S24*Use_Library!$U$23,E24*Use_Library!$AF$23)*(1-Assumptions!$C$17)+BM24,0)*U24 -> 0 | BO24: =(BD24-AT24)*(1+Assumptions!$C$11) -> 0 | BP24: =BJ24*BK24 -> 1.0854154 | BQ24: =(Parcel!$C$18*BJ24+BO24)*BK24 -> 325624.61 | BR24: =BN24-BQ24 -> -325624.61 | BS24: =IF(AND(Use_Library!$AJ$23=1,U24=1),MAX(0,((1-Use_Library!$AI$23)*BN24-BO24*BK24)/BP24),0) -> 0 | BT24: =BF24+BG24+BH24+BI24 -> 0 | BU24: =BJ24*BL24 -> 1.0854154 | BV24: =(Parcel!$C$18*BJ24+BT24)*BL24 -> 325624.61 | BW24: =IF(Use_Library!$C$23="Income",S24*Use_Library!$W$23,0) -> 0 | BX24: =BW24*(1+Use_Library!$X$23)*(1-Use_Library!$Y$23) -> 0 | BY24: =IF(Use_Library!$C$23="Income",S24*Use_Library!$Z$23,0) -> 0 | BZ24: =IF(Use_Library!$C$23="Income",Assumptions!$C$19*Assumptions!$C$20*BV24,0) -> 0 | CA24: =BX24*Use_Library!$AA$23 -> 0 | CB24: =(BY24+BZ24)*Use_Library!$AB$23 -> 0 | CC24: =BX24-BY24-BZ24-CA24+CB24 -> 0 | CD24: =IF(AND(Use_Library!$C$23="Income",Use_Library!$AE$23>0),CC24/Use_Library!$AE$23,0) -> 0 | CE24: =IF(Use_Library!$C$23="Income",-Assumptions!$C$19*Assumptions!$C$20*(1-Use_Library!$AB$23)*BU24,0) -> 0 | CF24: =IF(BV24=0,0,CC24/BV24) -> 0 | CG24: =IF(Use_Library!$AK$23=1,IF(Use_Library!$C$23="Income",CD24*(1-Assumptions!$C$18),S24*Use_Library!$V$23*(1-Assumptions!$C$16))+BM24,0)*U24 -> 0 | CH24: =IF(AND(Use_Library!$AK$23=1,Use_Library!$C$23="Income",Use_Library!$AE$23>0),CE24/Use_Library!$AE$23*(1-Assumptions!$C$18),0) -> 0 | CI24: =CG24-BV24 -> -325624.61 | CJ24: =IF(AND(Use_Library!$AK$23=1,U24=1),MAX(0,Parcel!$C$18-((1-Use_Library!$AI$23)*CG24-BV24)/((1-Use_Library!$AI$23)*CH24-BU24)),0) -> 0 | CK24: =IF(Use_Library!$AL$23=1,IF(Use_Library!$C$23="Income",CD24,IF(Use_Library!$AE$23>0,E24*Use_Library!$AG$23/Use_Library!$AE$23,0))+BM24,0)*U24 -> 0 | CL24: =IF(Use_Library!$C$23="Income",BT24,BF24) -> 0 | CM24: =IF(Use_Library!$C$23="Income",BU24,BJ24*BK24) -> 1.0854154 | CN24: =IF(Use_Library!$C$23="Income",BV24,(Parcel!$C$18*BJ24+BF24)*BK24) -> 325624.61 | CO24: =IF(AND(Use_Library!$AL$23=1,Use_Library!$C$23="Income",Use_Library!$AE$23>0),CE24/Use_Library!$AE$23,0) -> 0 | CP24: =CK24-CN24 -> -325624.61 | CQ24: =IF(AND(Use_Library!$AL$23=1,U24=1),MAX(0,Parcel!$C$18-((1-Use_Library!$AI$23)*CK24-CN24)/((1-Use_Library!$AI$23)*CO24-CM24)),0) -> 0 | CR24: =IF(Use_Library!$C$23="Income",Assumptions!$C$21*(Parcel!$C$18*BJ24+BT24),0) -> 0 | CS24: =IF(AND(Use_Library!$C$23="Income",CC24>0),MIN(Assumptions!$C$26*CD24,PV(Assumptions!$C$29/12,Assumptions!$C$30*12,-CC24/Assumptions!$C$27/12),CC24/Assumptions!$C$28),0) -> 0 | CT24: =IF(CS24=0,0,CC24/(-PMT(Assumptions!$C$29/12,Assumptions!$C$30*12,CS24)*12)) -> 0 | CU24: =CS24-CR24 -> 0 | CV24: =MAX(BS24,CJ24,CQ24) -> 0 | CW24: =IF(CV24<=0,"None works",IF(BS24=CV24,"Land / pad sale",IF(CJ24=CV24,"Build & sell","Build & hold / lease"))) -> None works | CX24: =CV24*(1-Assumptions!$C$32) -> 0 | CY24: =CV24-Parcel!$C$18 -> -300000 | CZ24: =IF(Parcel!$C$8=0,0,CV24/Parcel!$C$8) -> 0 | DA24: =IF(S24=0,0,CV24/S24) -> 0 | DB24: =TRIM(M24&" "&IF(AND(U24=0,N24=1),"Nothing fits. ","")&IF(Parcel!$C$12<Use_Library!$AM$23,"Frontage under "&Use_Library!$AM$23&" LF. ","")&IF(Parcel!$C$10>0.15,"Slope over 15%. ","")&IF(AND(U24=1,Use_Library!$M$23>0,D24>Use_Library!$M$23),"Only "&Use_Library!$M$23&" ac used - rest resold. ","")) -> Under 8,000 households in 3 mi. | DC24: =CV24+ROW()/1000000 -> 2.4e-05
A25: =Use_Library!$A$24 -> Medical office building | B25: =Use_Library!$C$24 -> Income | C25: =Use_Library!$D$24 -> bldg SF | D25: =MAX(0,Parcel!$C$26*(1-Use_Library!$N$24-Assumptions!$C$7)) -> 13.728 | E25: =IF(Use_Library!$M$24>0,MIN(D25,Use_Library!$M$24),D25) -> 4 | F25: =IF(D25=0,0,E25/D25) -> 0.29137529 | G25: =Parcel!$C$26*F25 -> 4.5454545 | H25: =G25*Assumptions!$C$7 -> 0.18181818 | I25: =G25*(1-Use_Library!$N$24) -> 4.1818182 | J25: =Parcel!$C$8*(1-F25) -> 14.172494 | K25: =IF(AND(Use_Library!$I$24="Y",Parcel!$C$28=0),0,1) -> 1 | L25: =IF(AND(Use_Library!$J$24="Y",Parcel!$C$27=0),0,1) -> 1 | M25: =TRIM(IF(AND(Use_Library!$AN$24>0,Parcel!$C$19<Use_Library!$AN$24),"Traffic under "&TEXT(Use_Library!$AN$24,"#,##0")&" VPD. ","")&IF(AND(Use_Library!$AO$24>0,Parcel!$C$20<Use_Library!$AO$24),"Under "&TEXT(Use_Library!$AO$24,"#,##0")&" households in 3 mi. ","")&IF(AND(Use_Library!$AP$24>0,Parcel!$C$21>Use_Library!$AP$24),"Over "&Use_Library!$AP$24&" mi to highway. ","")&IF(AND(Use_Library!$AQ$24="Y",Parcel!$C$22<>"Y"),"Needs a corner. ","")&IF(AND(Use_Library!$AR$24>0,Parcel!$C$23>Use_Library!$AR$24),"Over "&Use_Library!$AR$24&" mi to substation. ","")) -> Under 10,000 households in 3 mi. | N25: =IF(M25="",1,0) -> 0 | O25: =IF(D25>=Use_Library!$L$24,1,0) -> 1 | P25: =IF(Use_Library!$F$24>0,G25*Use_Library!$F$24,1000000000) -> 1000000000 | Q25: =IF(Use_Library!$G$24>0,E25*43560/Use_Library!$G$24,1000000000) -> 38336.634 | R25: =IF(AND(Use_Library!$H$24="Y",Parcel!$C$28=0),E25*(1-Assumptions!$C$8)/IF(Parcel!$C$27=1,Assumptions!$C$9,Assumptions!$C$10),1000000000) -> 1000000000 | S25: =IF(K25*L25*O25*N25=0,0,IF(MIN(P25,Q25,R25)>=1000000000,E25,IF(Use_Library!$E$24="Y",INT(MIN(P25,Q25,R25)),MIN(P25,Q25,R25)))) -> 0 | T25: =IF(N25=0,"Location fails",IF(O25=0,"Too small - needs "&Use_Library!$L$24&" usable ac",IF(K25=0,"Needs public sewer",IF(L25=0,"Needs public water",IF(R25<=MIN(P25,Q25),"Septic lot size",IF(Q25<=P25,"Site area / parking","Density")))))) -> Location fails | U25: =IF(S25>0,1,0) -> 0 | V25: =IF(Use_Library!$K$24="Y",1,0)*U25 -> 0 | W25: =S25*Use_Library!$O$24*V25 -> 0 | X25: =S25*Use_Library!$P$24*V25 -> 0 | Y25: =IF(Parcel!$C$27=1,W25+Parcel!$C$29,0)*V25 -> 0 | Z25: =S25*Use_Library!$Q$24*Parcel!$C$27*V25 -> 0 | AA25: =IF(Parcel!$C$28=1,W25+Parcel!$C$30,0)*V25 -> 0 | AB25: =S25*Use_Library!$Q$24*Parcel!$C$28*V25 -> 0 | AC25: =IF(Parcel!$C$28=0,S25*Use_Library!$R$24,0)*V25 -> 0 | AD25: =IF(Parcel!$C$27=0,S25*Use_Library!$R$24,0)*V25 -> 0 | AE25: =I25*Parcel!$C$11*V25 -> 0 | AF25: =I25*V25 -> 0 | AG25: =IF(Use_Library!$C$24="For-Sale",IF(Use_Library!$E$24="Y",S25,1),1)*U25 -> 0 | AH25: =Cost_Library!$G$5*Parcel!$C$32*U25 -> 0 | AI25: =AG25*Cost_Library!$G$6*Parcel!$C$32 -> 0 | AJ25: =I25*Cost_Library!$G$7*Parcel!$C$32*V25 -> 0 | AK25: =Cost_Library!$G$8*Parcel!$C$32*V25 -> 0 | AL25: =AC25*Cost_Library!$G$9*Parcel!$C$32 -> 0 | AM25: =Cost_Library!$G$10*U25 -> 0 | AN25: =Cost_Library!$G$11*Parcel!$C$32*V25 -> 0 | AO25: =Use_Library!$S$24*U25 -> 0 | AP25: =Cost_Library!$G$12*U25 -> 0 | AQ25: =AE25*Cost_Library!$G$13*Parcel!$C$32 -> 0 | AR25: =AF25*Cost_Library!$G$14*Parcel!$C$32*Parcel!$C$33 -> 0 | AS25: =W25*Cost_Library!$G$15*Parcel!$C$32 -> 0 | AT25: =X25*Cost_Library!$G$16*Parcel!$C$32 -> 0 | AU25: =H25*Cost_Library!$G$17*Parcel!$C$32*V25 -> 0 | AV25: =G25*Cost_Library!$G$18*Parcel!$C$32*V25 -> 0 | AW25: =Y25*Cost_Library!$G$19*Parcel!$C$32 -> 0 | AX25: =Z25*Cost_Library!$G$20 -> 0 | AY25: =AA25*Cost_Library!$G$21*Parcel!$C$32 -> 0 | AZ25: =AB25*Cost_Library!$G$22 -> 0 | BA25: =AC25*Cost_Library!$G$23*Parcel!$C$32*Parcel!$C$34 -> 0 | BB25: =AD25*Cost_Library!$G$24*Parcel!$C$32 -> 0 | BC25: =W25*Cost_Library!$G$25*Parcel!$C$32 -> 0 | BD25: =SUM(AH25:BC25) -> 0 | BE25: =BD25*Assumptions!$C$11 -> 0 | BF25: =BD25+BE25 -> 0 | BG25: =S25*Use_Library!$T$24 -> 0 | BH25: =BG25*(Assumptions!$C$12+Assumptions!$C$13) -> 0 | BI25: =S25*Use_Library!$AC$24 -> 0 | BJ25: =1+Assumptions!$C$14+Assumptions!$C$15*Use_Library!$AH$24/12 -> 1.0491667 | BK25: =1+Assumptions!$C$21*(Assumptions!$C$22*Use_Library!$AH$24/12*Assumptions!$C$24+Assumptions!$C$23) -> 1.0440375 | BL25: =1+Assumptions!$C$21*(Assumptions!$C$22*(Use_Library!$AH$24/12*Assumptions!$C$24+IF(Use_Library!$C$24="Income",Use_Library!$AD$24,0)/12*Assumptions!$C$25)+Assumptions!$C$23) -> 1.0732875 | BM25: =J25*Assumptions!$C$31*(1-Assumptions!$C$17)*U25 -> 0 | BN25: =IF(Use_Library!$AJ$24=1,IF(Use_Library!$C$24="For-Sale",S25*Use_Library!$U$24,E25*Use_Library!$AF$24)*(1-Assumptions!$C$17)+BM25,0)*U25 -> 0 | BO25: =(BD25-AT25)*(1+Assumptions!$C$11) -> 0 | BP25: =BJ25*BK25 -> 1.0953693 | BQ25: =(Parcel!$C$18*BJ25+BO25)*BK25 -> 328610.8 | BR25: =BN25-BQ25 -> -328610.8 | BS25: =IF(AND(Use_Library!$AJ$24=1,U25=1),MAX(0,((1-Use_Library!$AI$24)*BN25-BO25*BK25)/BP25),0) -> 0 | BT25: =BF25+BG25+BH25+BI25 -> 0 | BU25: =BJ25*BL25 -> 1.1260575 | BV25: =(Parcel!$C$18*BJ25+BT25)*BL25 -> 337817.24 | BW25: =IF(Use_Library!$C$24="Income",S25*Use_Library!$W$24,0) -> 0 | BX25: =BW25*(1+Use_Library!$X$24)*(1-Use_Library!$Y$24) -> 0 | BY25: =IF(Use_Library!$C$24="Income",S25*Use_Library!$Z$24,0) -> 0 | BZ25: =IF(Use_Library!$C$24="Income",Assumptions!$C$19*Assumptions!$C$20*BV25,0) -> 6317.1824 | CA25: =BX25*Use_Library!$AA$24 -> 0 | CB25: =(BY25+BZ25)*Use_Library!$AB$24 -> 5685.4642 | CC25: =BX25-BY25-BZ25-CA25+CB25 -> -631.71824 | CD25: =IF(AND(Use_Library!$C$24="Income",Use_Library!$AE$24>0),CC25/Use_Library!$AE$24,0) -> -9358.7887 | CE25: =IF(Use_Library!$C$24="Income",-Assumptions!$C$19*Assumptions!$C$20*(1-Use_Library!$AB$24)*BU25,0) -> -0.0021057275 | CF25: =IF(BV25=0,0,CC25/BV25) -> -0.00187 | CG25: =IF(Use_Library!$AK$24=1,IF(Use_Library!$C$24="Income",CD25*(1-Assumptions!$C$18),S25*Use_Library!$V$24*(1-Assumptions!$C$16))+BM25,0)*U25 -> 0 | CH25: =IF(AND(Use_Library!$AK$24=1,Use_Library!$C$24="Income",Use_Library!$AE$24>0),CE25/Use_Library!$AE$24*(1-Assumptions!$C$18),0) -> -0.030572043 | CI25: =CG25-BV25 -> -337817.24 | CJ25: =IF(AND(Use_Library!$AK$24=1,U25=1),MAX(0,Parcel!$C$18-((1-Use_Library!$AI$24)*CG25-BV25)/((1-Use_Library!$AI$24)*CH25-BU25)),0) -> 0 | CK25: =IF(Use_Library!$AL$24=1,IF(Use_Library!$C$24="Income",CD25,IF(Use_Library!$AE$24>0,E25*Use_Library!$AG$24/Use_Library!$AE$24,0))+BM25,0)*U25 -> 0 | CL25: =IF(Use_Library!$C$24="Income",BT25,BF25) -> 0 | CM25: =IF(Use_Library!$C$24="Income",BU25,BJ25*BK25) -> 1.1260575 | CN25: =IF(Use_Library!$C$24="Income",BV25,(Parcel!$C$18*BJ25+BF25)*BK25) -> 337817.24 | CO25: =IF(AND(Use_Library!$AL$24=1,Use_Library!$C$24="Income",Use_Library!$AE$24>0),CE25/Use_Library!$AE$24,0) -> -0.031195962 | CP25: =CK25-CN25 -> -337817.24 | CQ25: =IF(AND(Use_Library!$AL$24=1,U25=1),MAX(0,Parcel!$C$18-((1-Use_Library!$AI$24)*CK25-CN25)/((1-Use_Library!$AI$24)*CO25-CM25)),0) -> 0 | CR25: =IF(Use_Library!$C$24="Income",Assumptions!$C$21*(Parcel!$C$18*BJ25+BT25),0) -> 204587.5 | CS25: =IF(AND(Use_Library!$C$24="Income",CC25>0),MIN(Assumptions!$C$26*CD25,PV(Assumptions!$C$29/12,Assumptions!$C$30*12,-CC25/Assumptions!$C$27/12),CC25/Assumptions!$C$28),0) -> 0 | CT25: =IF(CS25=0,0,CC25/(-PMT(Assumptions!$C$29/12,Assumptions!$C$30*12,CS25)*12)) -> 0 | CU25: =CS25-CR25 -> -204587.5 | CV25: =MAX(BS25,CJ25,CQ25) -> 0 | CW25: =IF(CV25<=0,"None works",IF(BS25=CV25,"Land / pad sale",IF(CJ25=CV25,"Build & sell","Build & hold / lease"))) -> None works | CX25: =CV25*(1-Assumptions!$C$32) -> 0 | CY25: =CV25-Parcel!$C$18 -> -300000 | CZ25: =IF(Parcel!$C$8=0,0,CV25/Parcel!$C$8) -> 0 | DA25: =IF(S25=0,0,CV25/S25) -> 0 | DB25: =TRIM(M25&" "&IF(AND(U25=0,N25=1),"Nothing fits. ","")&IF(Parcel!$C$12<Use_Library!$AM$24,"Frontage under "&Use_Library!$AM$24&" LF. ","")&IF(Parcel!$C$10>0.15,"Slope over 15%. ","")&IF(AND(U25=1,Use_Library!$M$24>0,D25>Use_Library!$M$24),"Only "&Use_Library!$M$24&" ac used - rest resold. ","")) -> Under 10,000 households in 3 mi. | DC25: =CV25+ROW()/1000000 -> 2.5e-05
A26: =Use_Library!$A$25 -> Urgent care / freestanding ER | B26: =Use_Library!$C$25 -> Income | C26: =Use_Library!$D$25 -> bldg SF | D26: =MAX(0,Parcel!$C$26*(1-Use_Library!$N$25-Assumptions!$C$7)) -> 13.728 | E26: =IF(Use_Library!$M$25>0,MIN(D26,Use_Library!$M$25),D26) -> 1.5 | F26: =IF(D26=0,0,E26/D26) -> 0.10926573 | G26: =Parcel!$C$26*F26 -> 1.7045455 | H26: =G26*Assumptions!$C$7 -> 0.068181818 | I26: =G26*(1-Use_Library!$N$25) -> 1.5681818 | J26: =Parcel!$C$8*(1-F26) -> 17.814685 | K26: =IF(AND(Use_Library!$I$25="Y",Parcel!$C$28=0),0,1) -> 1 | L26: =IF(AND(Use_Library!$J$25="Y",Parcel!$C$27=0),0,1) -> 1 | M26: =TRIM(IF(AND(Use_Library!$AN$25>0,Parcel!$C$19<Use_Library!$AN$25),"Traffic under "&TEXT(Use_Library!$AN$25,"#,##0")&" VPD. ","")&IF(AND(Use_Library!$AO$25>0,Parcel!$C$20<Use_Library!$AO$25),"Under "&TEXT(Use_Library!$AO$25,"#,##0")&" households in 3 mi. ","")&IF(AND(Use_Library!$AP$25>0,Parcel!$C$21>Use_Library!$AP$25),"Over "&Use_Library!$AP$25&" mi to highway. ","")&IF(AND(Use_Library!$AQ$25="Y",Parcel!$C$22<>"Y"),"Needs a corner. ","")&IF(AND(Use_Library!$AR$25>0,Parcel!$C$23>Use_Library!$AR$25),"Over "&Use_Library!$AR$25&" mi to substation. ","")) -> Traffic under 15,000 VPD. Under 8,000 households in 3 mi. | N26: =IF(M26="",1,0) -> 0 | O26: =IF(D26>=Use_Library!$L$25,1,0) -> 1 | P26: =IF(Use_Library!$F$25>0,G26*Use_Library!$F$25,1000000000) -> 1000000000 | Q26: =IF(Use_Library!$G$25>0,E26*43560/Use_Library!$G$25,1000000000) -> 13068 | R26: =IF(AND(Use_Library!$H$25="Y",Parcel!$C$28=0),E26*(1-Assumptions!$C$8)/IF(Parcel!$C$27=1,Assumptions!$C$9,Assumptions!$C$10),1000000000) -> 1000000000 | S26: =IF(K26*L26*O26*N26=0,0,IF(MIN(P26,Q26,R26)>=1000000000,E26,IF(Use_Library!$E$25="Y",INT(MIN(P26,Q26,R26)),MIN(P26,Q26,R26)))) -> 0 | T26: =IF(N26=0,"Location fails",IF(O26=0,"Too small - needs "&Use_Library!$L$25&" usable ac",IF(K26=0,"Needs public sewer",IF(L26=0,"Needs public water",IF(R26<=MIN(P26,Q26),"Septic lot size",IF(Q26<=P26,"Site area / parking","Density")))))) -> Location fails | U26: =IF(S26>0,1,0) -> 0 | V26: =IF(Use_Library!$K$25="Y",1,0)*U26 -> 0 | W26: =S26*Use_Library!$O$25*V26 -> 0 | X26: =S26*Use_Library!$P$25*V26 -> 0 | Y26: =IF(Parcel!$C$27=1,W26+Parcel!$C$29,0)*V26 -> 0 | Z26: =S26*Use_Library!$Q$25*Parcel!$C$27*V26 -> 0 | AA26: =IF(Parcel!$C$28=1,W26+Parcel!$C$30,0)*V26 -> 0 | AB26: =S26*Use_Library!$Q$25*Parcel!$C$28*V26 -> 0 | AC26: =IF(Parcel!$C$28=0,S26*Use_Library!$R$25,0)*V26 -> 0 | AD26: =IF(Parcel!$C$27=0,S26*Use_Library!$R$25,0)*V26 -> 0 | AE26: =I26*Parcel!$C$11*V26 -> 0 | AF26: =I26*V26 -> 0 | AG26: =IF(Use_Library!$C$25="For-Sale",IF(Use_Library!$E$25="Y",S26,1),1)*U26 -> 0 | AH26: =Cost_Library!$G$5*Parcel!$C$32*U26 -> 0 | AI26: =AG26*Cost_Library!$G$6*Parcel!$C$32 -> 0 | AJ26: =I26*Cost_Library!$G$7*Parcel!$C$32*V26 -> 0 | AK26: =Cost_Library!$G$8*Parcel!$C$32*V26 -> 0 | AL26: =AC26*Cost_Library!$G$9*Parcel!$C$32 -> 0 | AM26: =Cost_Library!$G$10*U26 -> 0 | AN26: =Cost_Library!$G$11*Parcel!$C$32*V26 -> 0 | AO26: =Use_Library!$S$25*U26 -> 0 | AP26: =Cost_Library!$G$12*U26 -> 0 | AQ26: =AE26*Cost_Library!$G$13*Parcel!$C$32 -> 0 | AR26: =AF26*Cost_Library!$G$14*Parcel!$C$32*Parcel!$C$33 -> 0 | AS26: =W26*Cost_Library!$G$15*Parcel!$C$32 -> 0 | AT26: =X26*Cost_Library!$G$16*Parcel!$C$32 -> 0 | AU26: =H26*Cost_Library!$G$17*Parcel!$C$32*V26 -> 0 | AV26: =G26*Cost_Library!$G$18*Parcel!$C$32*V26 -> 0 | AW26: =Y26*Cost_Library!$G$19*Parcel!$C$32 -> 0 | AX26: =Z26*Cost_Library!$G$20 -> 0 | AY26: =AA26*Cost_Library!$G$21*Parcel!$C$32 -> 0 | AZ26: =AB26*Cost_Library!$G$22 -> 0 | BA26: =AC26*Cost_Library!$G$23*Parcel!$C$32*Parcel!$C$34 -> 0 | BB26: =AD26*Cost_Library!$G$24*Parcel!$C$32 -> 0 | BC26: =W26*Cost_Library!$G$25*Parcel!$C$32 -> 0 | BD26: =SUM(AH26:BC26) -> 0 | BE26: =BD26*Assumptions!$C$11 -> 0 | BF26: =BD26+BE26 -> 0 | BG26: =S26*Use_Library!$T$25 -> 0 | BH26: =BG26*(Assumptions!$C$12+Assumptions!$C$13) -> 0 | BI26: =S26*Use_Library!$AC$25 -> 0 | BJ26: =1+Assumptions!$C$14+Assumptions!$C$15*Use_Library!$AH$25/12 -> 1.0491667 | BK26: =1+Assumptions!$C$21*(Assumptions!$C$22*Use_Library!$AH$25/12*Assumptions!$C$24+Assumptions!$C$23) -> 1.0440375 | BL26: =1+Assumptions!$C$21*(Assumptions!$C$22*(Use_Library!$AH$25/12*Assumptions!$C$24+IF(Use_Library!$C$25="Income",Use_Library!$AD$25,0)/12*Assumptions!$C$25)+Assumptions!$C$23) -> 1.0586625 | BM26: =J26*Assumptions!$C$31*(1-Assumptions!$C$17)*U26 -> 0 | BN26: =IF(Use_Library!$AJ$25=1,IF(Use_Library!$C$25="For-Sale",S26*Use_Library!$U$25,E26*Use_Library!$AF$25)*(1-Assumptions!$C$17)+BM26,0)*U26 -> 0 | BO26: =(BD26-AT26)*(1+Assumptions!$C$11) -> 0 | BP26: =BJ26*BK26 -> 1.0953693 | BQ26: =(Parcel!$C$18*BJ26+BO26)*BK26 -> 328610.8 | BR26: =BN26-BQ26 -> -328610.8 | BS26: =IF(AND(Use_Library!$AJ$25=1,U26=1),MAX(0,((1-Use_Library!$AI$25)*BN26-BO26*BK26)/BP26),0) -> 0 | BT26: =BF26+BG26+BH26+BI26 -> 0 | BU26: =BJ26*BL26 -> 1.1107134 | BV26: =(Parcel!$C$18*BJ26+BT26)*BL26 -> 333214.02 | BW26: =IF(Use_Library!$C$25="Income",S26*Use_Library!$W$25,0) -> 0 | BX26: =BW26*(1+Use_Library!$X$25)*(1-Use_Library!$Y$25) -> 0 | BY26: =IF(Use_Library!$C$25="Income",S26*Use_Library!$Z$25,0) -> 0 | BZ26: =IF(Use_Library!$C$25="Income",Assumptions!$C$19*Assumptions!$C$20*BV26,0) -> 6231.1022 | CA26: =BX26*Use_Library!$AA$25 -> 0 | CB26: =(BY26+BZ26)*Use_Library!$AB$25 -> 6231.1022 | CC26: =BX26-BY26-BZ26-CA26+CB26 -> 0 | CD26: =IF(AND(Use_Library!$C$25="Income",Use_Library!$AE$25>0),CC26/Use_Library!$AE$25,0) -> 0 | CE26: =IF(Use_Library!$C$25="Income",-Assumptions!$C$19*Assumptions!$C$20*(1-Use_Library!$AB$25)*BU26,0) -> 0 | CF26: =IF(BV26=0,0,CC26/BV26) -> 0 | CG26: =IF(Use_Library!$AK$25=1,IF(Use_Library!$C$25="Income",CD26*(1-Assumptions!$C$18),S26*Use_Library!$V$25*(1-Assumptions!$C$16))+BM26,0)*U26 -> 0 | CH26: =IF(AND(Use_Library!$AK$25=1,Use_Library!$C$25="Income",Use_Library!$AE$25>0),CE26/Use_Library!$AE$25*(1-Assumptions!$C$18),0) -> 0 | CI26: =CG26-BV26 -> -333214.02 | CJ26: =IF(AND(Use_Library!$AK$25=1,U26=1),MAX(0,Parcel!$C$18-((1-Use_Library!$AI$25)*CG26-BV26)/((1-Use_Library!$AI$25)*CH26-BU26)),0) -> 0 | CK26: =IF(Use_Library!$AL$25=1,IF(Use_Library!$C$25="Income",CD26,IF(Use_Library!$AE$25>0,E26*Use_Library!$AG$25/Use_Library!$AE$25,0))+BM26,0)*U26 -> 0 | CL26: =IF(Use_Library!$C$25="Income",BT26,BF26) -> 0 | CM26: =IF(Use_Library!$C$25="Income",BU26,BJ26*BK26) -> 1.1107134 | CN26: =IF(Use_Library!$C$25="Income",BV26,(Parcel!$C$18*BJ26+BF26)*BK26) -> 333214.02 | CO26: =IF(AND(Use_Library!$AL$25=1,Use_Library!$C$25="Income",Use_Library!$AE$25>0),CE26/Use_Library!$AE$25,0) -> 0 | CP26: =CK26-CN26 -> -333214.02 | CQ26: =IF(AND(Use_Library!$AL$25=1,U26=1),MAX(0,Parcel!$C$18-((1-Use_Library!$AI$25)*CK26-CN26)/((1-Use_Library!$AI$25)*CO26-CM26)),0) -> 0 | CR26: =IF(Use_Library!$C$25="Income",Assumptions!$C$21*(Parcel!$C$18*BJ26+BT26),0) -> 204587.5 | CS26: =IF(AND(Use_Library!$C$25="Income",CC26>0),MIN(Assumptions!$C$26*CD26,PV(Assumptions!$C$29/12,Assumptions!$C$30*12,-CC26/Assumptions!$C$27/12),CC26/Assumptions!$C$28),0) -> 0 | CT26: =IF(CS26=0,0,CC26/(-PMT(Assumptions!$C$29/12,Assumptions!$C$30*12,CS26)*12)) -> 0 | CU26: =CS26-CR26 -> -204587.5 | CV26: =MAX(BS26,CJ26,CQ26) -> 0 | CW26: =IF(CV26<=0,"None works",IF(BS26=CV26,"Land / pad sale",IF(CJ26=CV26,"Build & sell","Build & hold / lease"))) -> None works | CX26: =CV26*(1-Assumptions!$C$32) -> 0 | CY26: =CV26-Parcel!$C$18 -> -300000 | CZ26: =IF(Parcel!$C$8=0,0,CV26/Parcel!$C$8) -> 0 | DA26: =IF(S26=0,0,CV26/S26) -> 0 | DB26: =TRIM(M26&" "&IF(AND(U26=0,N26=1),"Nothing fits. ","")&IF(Parcel!$C$12<Use_Library!$AM$25,"Frontage under "&Use_Library!$AM$25&" LF. ","")&IF(Parcel!$C$10>0.15,"Slope over 15%. ","")&IF(AND(U26=1,Use_Library!$M$25>0,D26>Use_Library!$M$25),"Only "&Use_Library!$M$25&" ac used - rest resold. ","")) -> Traffic under 15,000 VPD. Under 8,000 households in 3 mi. | DC26: =CV26+ROW()/1000000 -> 2.6e-05
